Workbook

Sheet Start Here
B1: Money Tracker
B2: Income | Budgets | Daily Spending | Insights - all amounts in Kenya Shillings (KES)
B4: HOW TO USE IT - 5 SIMPLE STEPS
B5: 1 | C5: Settings | D5: Look at the lists once (categories, payment methods, income sources) and rename them to suit you.
B6: 2 | C6: Budget | D6: For each category choose Daily, Weekly or Monthly and type the amount. Set it once - it repeats every month by itself.
B7: 3 | C7: Income | D7: Every time money comes in, add a row: date, source, amount.
B8: 4 | C8: Transactions | D8: Every time you spend, add a row: date, time, item, category, amount, how you paid.
B9: 5 | C9: Dashboard | D9: Pick the Year and Month at the top to see totals, overspending alerts, weekly, daily and category analysis.
B11: FINDING THINGS
B12: Search sheet: filter by date range, product name, category or time of day and see matching transactions and their total instantly. Transactions & Income sheets: use the small filter arrows on row 4 to sort or filter by any column.
B14: Open the Search sheet
B16: COLOUR GUIDE
C17: Yellow cell, blue text | D17: You type here.
C18: White / grey cell | D18: Automatic - formulas live here, please don't type over them.
B19: OK | C19: Green | D19: Within budget.
B20: Watch | C20: Amber | D20: Close to the limit (default: 80% of budget used - change on Settings).
B21: OVER | C21: Red | D21: You are overspending.
B23: WHAT A ROW LOOKS LIKE (EXAMPLE)
B24: Time | C24: Date | D24: Item / Product | E24: Category | F24: Amount (KES) | G24: Paid With
B25: 1:15 PM | C25: 46321 | D25: Lunch at Java House | E25: Eating Out | F25: 1450 | G25: M-Pesa
B27: HANDY SHORTCUTS
C28: Ctrl + ; | D28: type today's date
C29: Ctrl + Shift + ; | D29: type the current time
C30: Alt + Down Arrow | D30: open a dropdown list in the selected cell
C31: Ctrl + D | D31: copy the cell above into the selected cell
B33: GOOD TO KNOW
B34: - | C34: Capacity: 5,000 transactions, 2,000 income entries and 40 budget lines. Plenty for a year or more of daily use.
B35: - | C35: Budgets are not tied to a month: set once, they apply to every month. Use the Starts/Ends columns to keep history when a budget changes.
B36: - | C36: Overspending alerts: total budget, each category, each week and each day are checked automatically. The Dashboard banner tells you in plain words where you stand.
B37: - | C37: Savings, chama contributions or loan repayments count as money going out - give them a category (e.g. 'Loans & Debt') if you want them budgeted.
B38: - | C38: The Dashboard and Year View are protected so formulas can't be damaged by accident (Review > Unprotect Sheet - no password).
B39: - | C39: Back up often: save a copy of this file at month-end (File > Save a Copy).
B41: ALL SHEETS
C42: Dashboard | D42: Totals, alerts, charts and analysis for any month
C43: Transactions | D43: Your daily spending log
C44: Income | D44: Where your money comes from
C45: Budget | D45: Daily, weekly or monthly budgets per category
C46: Search | D46: Find any transaction by date, time, product or category
C47: Year View | D47: Month-by-month overview for the whole year
C48: Settings | D48: Categories, payment methods, income sources and alert level

Sheet Dashboard
B1: Personal Finance Dashboard
B2: ="Analysis for "&TEXT(PeriodStart,"mmmm yyyy")&" | All amounts in Kenya Shillings (KES)" -> Analysis for October 2026 | All amounts in Kenya Shillings (KES)
B3: Choose the period to analyse: | C3: Year | D3: Month
B4: Use the two dropdowns | C4: 2026 | D4: October | F4: =IF(IsCurrent=1,"Current month: day "&DaysElapsed&" of "&DaysInMonth&" ("&DaysLeft&" days to go)",IF(PeriodEnd<TODAY(),"Past month - full results","Future month - nothing to analyse yet")) -> Current month: day 27 of 31 (4 days to go)
B6: TOTAL INCOME | D6: TOTAL SPENT | F6: NET SAVINGS | H6: SAVINGS RATE | J6: BUDGET USED | L6: BUDGET STATUS
B7: =SUMIFS(Income!$D$5:$D$2004,Income!$A$5:$A$2004,">="&PeriodStart,Income!$A$5:$A$2004,"<="&PeriodEnd) -> 0 | D7: =SUMIFS(Transactions!$E$5:$E$5004,Transactions!$A$5:$A$5004,">="&PeriodStart,Transactions!$A$5:$A$5004,"<="&PeriodEnd) -> 0 | F7: =B7-D7 -> 0 | H7: =IF(B7=0,0,F7/B7) -> 0 | J7: =IF(C13=0,0,D7/C13) -> 0 | L7: =IF(C13=0,"NO BUDGET",IF(D7>C13,"OVERSPENDING",IF(J7>=WarnPct,"WATCH OUT","ON TRACK"))) -> NO BUDGET
B8: =COUNTIFS(Income!$A$5:$A$2004,">="&PeriodStart,Income!$A$5:$A$2004,"<="&PeriodEnd)&" income entries" -> 0 income entries | D8: =COUNTIFS(Transactions!$A$5:$A$5004,">="&PeriodStart,Transactions!$A$5:$A$5004,"<="&PeriodEnd)&" transactions" -> 0 transactions | F8: =IF(F7>=0,"Income minus spending","Spending is above income") -> Income minus spending | H8: =IF(B7=0,"No income recorded",IF(H7>=0.2,"Healthy saving habit",IF(H7>=0,"Room to improve","Spending exceeds income"))) -> No income recorded | J8: ="of KES "&TEXT(C13,"#,##0")&" budget" -> of KES 0 budget | L8: =IF(C13=0,"Add budgets to track",IF(D7>C13,"Over by KES "&TEXT(D7-C13,"#,##0"),"KES "&TEXT(C13-D7,"#,##0")&" left")) -> Add budgets to track
B10: =IF(C13=0,"No budget set yet - add your budgets on the Budget sheet to switch on overspending alerts.",IF(C14>C13,"OVERSPENDING: you have spent KES "&TEXT(C14-C13,"#,##0")&" more than your total budget for this period."&IF(C22>0," Watch out: "&C22&IF(C22=1," category is"," categories are")&" over its own budget.",""),IF(AND(IsCurrent=1,C16>0,C17>0.1*C16),"HEADS UP: you are spending faster than planned. At this pace you will finish near KES "&TEXT(C18,"#,##0")&" against a budget of KES "&TEXT(C13,"#,##0")&"."&IF(C22>0," Watch out: "&C22&IF(C22=1," category is"," categories are")&" over its own budget.",""),"ON TRACK: you are within budget."&IF(IsCurrent=1," You can spend about KES "&TEXT(C20,"#,##0")&" per day for the rest of the month.","")&IF(C22>0," Watch out: "&C22&IF(C22=1," category is"," categories are")&" over its own budget.","")))) -> No budget set yet - add your budgets on the Budget sheet to switch on overspending alerts.
B12: SPENDING HEALTH | E12: WEEKLY BREAKDOWN
B13: Total budget for the month | C13: =C42 -> 0 | E13: Week | F13: Dates | G13: Spent | H13: Budget | I13: Status
B14: Spent so far | C14: =D7 -> 0 | E14: Week 1 | F14: =IF((PeriodStart+7*0)>PeriodEnd,"",TEXT((PeriodStart+7*0),"d mmm")&" - "&TEXT(MIN(PeriodEnd,PeriodStart+7*1-1),"d mmm")) -> 1 Oct - 7 Oct | G14: =IF($F14="","",SUMIFS(Transactions!$E$5:$E$5004,Transactions!$A$5:$A$5004,">="&(PeriodStart+7*0),Transactions!$A$5:$A$5004,"<="&MIN(PeriodEnd,PeriodStart+7*1-1))) -> 0 | H14: =IF($F14="","",$C$13*(MIN(PeriodEnd,PeriodStart+7*1-1)-(PeriodStart+7*0)+1)/DaysInMonth) -> 0 | I14: =IF($F14="","",IF((PeriodStart+7*0)>TODAY(),"Upcoming",IF(H14=0,IF(G14>0,"No budget","-"),IF(G14>H14,"OVER",IF(G14>=WarnPct*H14,"Watch","OK"))))) -> -
B15: Budget remaining | C15: =C13-C14 -> 0 | E15: Week 2 | F15: =IF((PeriodStart+7*1)>PeriodEnd,"",TEXT((PeriodStart+7*1),"d mmm")&" - "&TEXT(MIN(PeriodEnd,PeriodStart+7*2-1),"d mmm")) -> 8 Oct - 14 Oct | G15: =IF($F15="","",SUMIFS(Transactions!$E$5:$E$5004,Transactions!$A$5:$A$5004,">="&(PeriodStart+7*1),Transactions!$A$5:$A$5004,"<="&MIN(PeriodEnd,PeriodStart+7*2-1))) -> 0 | H15: =IF($F15="","",$C$13*(MIN(PeriodEnd,PeriodStart+7*2-1)-(PeriodStart+7*1)+1)/DaysInMonth) -> 0 | I15: =IF($F15="","",IF((PeriodStart+7*1)>TODAY(),"Upcoming",IF(H15=0,IF(G15>0,"No budget","-"),IF(G15>H15,"OVER",IF(G15>=WarnPct*H15,"Watch","OK"))))) -> -
B16: Expected spend by today (pace) | C16: =IF(IsCurrent=1,C13*DaysElapsed/DaysInMonth,IF(PeriodEnd<TODAY(),C13,0)) -> 0 | E16: Week 3 | F16: =IF((PeriodStart+7*2)>PeriodEnd,"",TEXT((PeriodStart+7*2),"d mmm")&" - "&TEXT(MIN(PeriodEnd,PeriodStart+7*3-1),"d mmm")) -> 15 Oct - 21 Oct | G16: =IF($F16="","",SUMIFS(Transactions!$E$5:$E$5004,Transactions!$A$5:$A$5004,">="&(PeriodStart+7*2),Transactions!$A$5:$A$5004,"<="&MIN(PeriodEnd,PeriodStart+7*3-1))) -> 0 | H16: =IF($F16="","",$C$13*(MIN(PeriodEnd,PeriodStart+7*3-1)-(PeriodStart+7*2)+1)/DaysInMonth) -> 0 | I16: =IF($F16="","",IF((PeriodStart+7*2)>TODAY(),"Upcoming",IF(H16=0,IF(G16>0,"No budget","-"),IF(G16>H16,"OVER",IF(G16>=WarnPct*H16,"Watch","OK"))))) -> -
B17: Ahead (+) / behind (-) of pace | C17: =IF(C13=0,0,C14-C16) -> 0 | E17: Week 4 | F17: =IF((PeriodStart+7*3)>PeriodEnd,"",TEXT((PeriodStart+7*3),"d mmm")&" - "&TEXT(MIN(PeriodEnd,PeriodStart+7*4-1),"d mmm")) -> 22 Oct - 28 Oct | G17: =IF($F17="","",SUMIFS(Transactions!$E$5:$E$5004,Transactions!$A$5:$A$5004,">="&(PeriodStart+7*3),Transactions!$A$5:$A$5004,"<="&MIN(PeriodEnd,PeriodStart+7*4-1))) -> 0 | H17: =IF($F17="","",$C$13*(MIN(PeriodEnd,PeriodStart+7*4-1)-(PeriodStart+7*3)+1)/DaysInMonth) -> 0 | I17: =IF($F17="","",IF((PeriodStart+7*3)>TODAY(),"Upcoming",IF(H17=0,IF(G17>0,"No budget","-"),IF(G17>H17,"OVER",IF(G17>=WarnPct*H17,"Watch","OK"))))) -> -
B18: Projected month-end spend | C18: =IF(IsCurrent=1,IF(DaysElapsed=0,0,C14/DaysElapsed*DaysInMonth),C14) -> 0 | E18: Week 5 | F18: =IF((PeriodStart+7*4)>PeriodEnd,"",TEXT((PeriodStart+7*4),"d mmm")&" - "&TEXT(MIN(PeriodEnd,PeriodStart+7*5-1),"d mmm")) -> 29 Oct - 31 Oct | G18: =IF($F18="","",SUMIFS(Transactions!$E$5:$E$5004,Transactions!$A$5:$A$5004,">="&(PeriodStart+7*4),Transactions!$A$5:$A$5004,"<="&MIN(PeriodEnd,PeriodStart+7*5-1))) -> 0 | H18: =IF($F18="","",$C$13*(MIN(PeriodEnd,PeriodStart+7*5-1)-(PeriodStart+7*4)+1)/DaysInMonth) -> 0 | I18: =IF($F18="","",IF((PeriodStart+7*4)>TODAY(),"Upcoming",IF(H18=0,IF(G18>0,"No budget","-"),IF(G18>H18,"OVER",IF(G18>=WarnPct*H18,"Watch","OK"))))) -> Upcoming
B19: Projected over (+) / under (-) budget | C19: =IF(C13=0,0,C18-C13) -> 0 | E19: Total | G19: =SUM(G14:G18) -> 0 | H19: =SUM(H14:H18) -> 0
B20: Safe to spend per day (rest of month) | C20: =IF(AND(IsCurrent=1,DaysLeft>0),MAX(C15,0)/DaysLeft,0) -> 0
B21: Average spend per day | C21: =IF(DaysElapsed=0,0,C14/DaysElapsed) -> 0 | E21: Weekly budget = your monthly budget spread evenly across the days of each week.
B22: Categories over budget | C22: =COUNTIF(G26:G41,"OVER") -> 0
B24: BUDGET vs ACTUAL BY CATEGORY
B25: Category | C25: Budget | D25: Spent | E25: Remaining | F25: % Used | G25: Status
B26: =IF(Settings!$B$6="","",Settings!$B$6) -> Food & Groceries | C26: =IF($B26="","",SUMPRODUCT((Budget!$A$5:$A$44=$B26)*Budget!$C$5:$C$44*((Budget!$B$5:$B$44="Monthly")+(Budget!$B$5:$B$44="Daily")*DaysInMonth+(Budget!$B$5:$B$44="Weekly")*DaysInMonth/7)*(Budget!$D$5:$D$44<=PeriodEnd)*(((Budget!$E$5:$E$44="")+(Budget!$E$5:$E$44>=PeriodStart))>0))) -> 0 | D26: =IF($B26="","",SUMIFS(Transactions!$E$5:$E$5004,Transactions!$D$5:$D$5004,$B26,Transactions!$A$5:$A$5004,">="&PeriodStart,Transactions!$A$5:$A$5004,"<="&PeriodEnd)) -> 0 | E26: =IF($B26="","",C26-D26) -> 0 | F26: =IF($B26="","",IF(C26=0,0,D26/C26)) -> 0 | G26: =IF($B26="","",IF(C26=0,IF(D26>0,"No budget","-"),IF(D26>C26,"OVER",IF(D26>=WarnPct*C26,"Watch","OK")))) -> -
B27: =IF(Settings!$B$7="","",Settings!$B$7) -> Eating Out | C27: =IF($B27="","",SUMPRODUCT((Budget!$A$5:$A$44=$B27)*Budget!$C$5:$C$44*((Budget!$B$5:$B$44="Monthly")+(Budget!$B$5:$B$44="Daily")*DaysInMonth+(Budget!$B$5:$B$44="Weekly")*DaysInMonth/7)*(Budget!$D$5:$D$44<=PeriodEnd)*(((Budget!$E$5:$E$44="")+(Budget!$E$5:$E$44>=PeriodStart))>0))) -> 0 | D27: =IF($B27="","",SUMIFS(Transactions!$E$5:$E$5004,Transactions!$D$5:$D$5004,$B27,Transactions!$A$5:$A$5004,">="&PeriodStart,Transactions!$A$5:$A$5004,"<="&PeriodEnd)) -> 0 | E27: =IF($B27="","",C27-D27) -> 0 | F27: =IF($B27="","",IF(C27=0,0,D27/C27)) -> 0 | G27: =IF($B27="","",IF(C27=0,IF(D27>0,"No budget","-"),IF(D27>C27,"OVER",IF(D27>=WarnPct*C27,"Watch","OK")))) -> -
B28: =IF(Settings!$B$8="","",Settings!$B$8) -> Rent & Housing | C28: =IF($B28="","",SUMPRODUCT((Budget!$A$5:$A$44=$B28)*Budget!$C$5:$C$44*((Budget!$B$5:$B$44="Monthly")+(Budget!$B$5:$B$44="Daily")*DaysInMonth+(Budget!$B$5:$B$44="Weekly")*DaysInMonth/7)*(Budget!$D$5:$D$44<=PeriodEnd)*(((Budget!$E$5:$E$44="")+(Budget!$E$5:$E$44>=PeriodStart))>0))) -> 0 | D28: =IF($B28="","",SUMIFS(Transactions!$E$5:$E$5004,Transactions!$D$5:$D$5004,$B28,Transactions!$A$5:$A$5004,">="&PeriodStart,Transactions!$A$5:$A$5004,"<="&PeriodEnd)) -> 0 | E28: =IF($B28="","",C28-D28) -> 0 | F28: =IF($B28="","",IF(C28=0,0,D28/C28)) -> 0 | G28: =IF($B28="","",IF(C28=0,IF(D28>0,"No budget","-"),IF(D28>C28,"OVER",IF(D28>=WarnPct*C28,"Watch","OK")))) -> -
B29: =IF(Settings!$B$9="","",Settings!$B$9) -> Utilities | C29: =IF($B29="","",SUMPRODUCT((Budget!$A$5:$A$44=$B29)*Budget!$C$5:$C$44*((Budget!$B$5:$B$44="Monthly")+(Budget!$B$5:$B$44="Daily")*DaysInMonth+(Budget!$B$5:$B$44="Weekly")*DaysInMonth/7)*(Budget!$D$5:$D$44<=PeriodEnd)*(((Budget!$E$5:$E$44="")+(Budget!$E$5:$E$44>=PeriodStart))>0))) -> 0 | D29: =IF($B29="","",SUMIFS(Transactions!$E$5:$E$5004,Transactions!$D$5:$D$5004,$B29,Transactions!$A$5:$A$5004,">="&PeriodStart,Transactions!$A$5:$A$5004,"<="&PeriodEnd)) -> 0 | E29: =IF($B29="","",C29-D29) -> 0 | F29: =IF($B29="","",IF(C29=0,0,D29/C29)) -> 0 | G29: =IF($B29="","",IF(C29=0,IF(D29>0,"No budget","-"),IF(D29>C29,"OVER",IF(D29>=WarnPct*C29,"Watch","OK")))) -> -
B30: =IF(Settings!$B$10="","",Settings!$B$10) -> Transport & Fuel | C30: =IF($B30="","",SUMPRODUCT((Budget!$A$5:$A$44=$B30)*Budget!$C$5:$C$44*((Budget!$B$5:$B$44="Monthly")+(Budget!$B$5:$B$44="Daily")*DaysInMonth+(Budget!$B$5:$B$44="Weekly")*DaysInMonth/7)*(Budget!$D$5:$D$44<=PeriodEnd)*(((Budget!$E$5:$E$44="")+(Budget!$E$5:$E$44>=PeriodStart))>0))) -> 0 | D30: =IF($B30="","",SUMIFS(Transactions!$E$5:$E$5004,Transactions!$D$5:$D$5004,$B30,Transactions!$A$5:$A$5004,">="&PeriodStart,Transactions!$A$5:$A$5004,"<="&PeriodEnd)) -> 0 | E30: =IF($B30="","",C30-D30) -> 0 | F30: =IF($B30="","",IF(C30=0,0,D30/C30)) -> 0 | G30: =IF($B30="","",IF(C30=0,IF(D30>0,"No budget","-"),IF(D30>C30,"OVER",IF(D30>=WarnPct*C30,"Watch","OK")))) -> -
B31: =IF(Settings!$B$11="","",Settings!$B$11) -> Airtime & Data | C31: =IF($B31="","",SUMPRODUCT((Budget!$A$5:$A$44=$B31)*Budget!$C$5:$C$44*((Budget!$B$5:$B$44="Monthly")+(Budget!$B$5:$B$44="Daily")*DaysInMonth+(Budget!$B$5:$B$44="Weekly")*DaysInMonth/7)*(Budget!$D$5:$D$44<=PeriodEnd)*(((Budget!$E$5:$E$44="")+(Budget!$E$5:$E$44>=PeriodStart))>0))) -> 0 | D31: =IF($B31="","",SUMIFS(Transactions!$E$5:$E$5004,Transactions!$D$5:$D$5004,$B31,Transactions!$A$5:$A$5004,">="&PeriodStart,Transactions!$A$5:$A$5004,"<="&PeriodEnd)) -> 0 | E31: =IF($B31="","",C31-D31) -> 0 | F31: =IF($B31="","",IF(C31=0,0,D31/C31)) -> 0 | G31: =IF($B31="","",IF(C31=0,IF(D31>0,"No budget","-"),IF(D31>C31,"OVER",IF(D31>=WarnPct*C31,"Watch","OK")))) -> -
B32: =IF(Settings!$B$12="","",Settings!$B$12) -> Health & Medical | C32: =IF($B32="","",SUMPRODUCT((Budget!$A$5:$A$44=$B32)*Budget!$C$5:$C$44*((Budget!$B$5:$B$44="Monthly")+(Budget!$B$5:$B$44="Daily")*DaysInMonth+(Budget!$B$5:$B$44="Weekly")*DaysInMonth/7)*(Budget!$D$5:$D$44<=PeriodEnd)*(((Budget!$E$5:$E$44="")+(Budget!$E$5:$E$44>=PeriodStart))>0))) -> 0 | D32: =IF($B32="","",SUMIFS(Transactions!$E$5:$E$5004,Transactions!$D$5:$D$5004,$B32,Transactions!$A$5:$A$5004,">="&PeriodStart,Transactions!$A$5:$A$5004,"<="&PeriodEnd)) -> 0 | E32: =IF($B32="","",C32-D32) -> 0 | F32: =IF($B32="","",IF(C32=0,0,D32/C32)) -> 0 | G32: =IF($B32="","",IF(C32=0,IF(D32>0,"No budget","-"),IF(D32>C32,"OVER",IF(D32>=WarnPct*C32,"Watch","OK")))) -> -
B33: =IF(Settings!$B$13="","",Settings!$B$13) -> Education & School Fees | C33: =IF($B33="","",SUMPRODUCT((Budget!$A$5:$A$44=$B33)*Budget!$C$5:$C$44*((Budget!$B$5:$B$44="Monthly")+(Budget!$B$5:$B$44="Daily")*DaysInMonth+(Budget!$B$5:$B$44="Weekly")*DaysInMonth/7)*(Budget!$D$5:$D$44<=PeriodEnd)*(((Budget!$E$5:$E$44="")+(Budget!$E$5:$E$44>=PeriodStart))>0))) -> 0 | D33: =IF($B33="","",SUMIFS(Transactions!$E$5:$E$5004,Transactions!$D$5:$D$5004,$B33,Transactions!$A$5:$A$5004,">="&PeriodStart,Transactions!$A$5:$A$5004,"<="&PeriodEnd)) -> 0 | E33: =IF($B33="","",C33-D33) -> 0 | F33: =IF($B33="","",IF(C33=0,0,D33/C33)) -> 0 | G33: =IF($B33="","",IF(C33=0,IF(D33>0,"No budget","-"),IF(D33>C33,"OVER",IF(D33>=WarnPct*C33,"Watch","OK")))) -> -
B34: =IF(Settings!$B$14="","",Settings!$B$14) -> Business Expenses | C34: =IF($B34="","",SUMPRODUCT((Budget!$A$5:$A$44=$B34)*Budget!$C$5:$C$44*((Budget!$B$5:$B$44="Monthly")+(Budget!$B$5:$B$44="Daily")*DaysInMonth+(Budget!$B$5:$B$44="Weekly")*DaysInMonth/7)*(Budget!$D$5:$D$44<=PeriodEnd)*(((Budget!$E$5:$E$44="")+(Budget!$E$5:$E$44>=PeriodStart))>0))) -> 0 | D34: =IF($B34="","",SUMIFS(Transactions!$E$5:$E$5004,Transactions!$D$5:$D$5004,$B34,Transactions!$A$5:$A$5004,">="&PeriodStart,Transactions!$A$5:$A$5004,"<="&PeriodEnd)) -> 0 | E34: =IF($B34="","",C34-D34) -> 0 | F34: =IF($B34="","",IF(C34=0,0,D34/C34)) -> 0 | G34: =IF($B34="","",IF(C34=0,IF(D34>0,"No budget","-"),IF(D34>C34,"OVER",IF(D34>=WarnPct*C34,"Watch","OK")))) -> -
B35: =IF(Settings!$B$15="","",Settings!$B$15) -> Shopping & Clothing | C35: =IF($B35="","",SUMPRODUCT((Budget!$A$5:$A$44=$B35)*Budget!$C$5:$C$44*((Budget!$B$5:$B$44="Monthly")+(Budget!$B$5:$B$44="Daily")*DaysInMonth+(Budget!$B$5:$B$44="Weekly")*DaysInMonth/7)*(Budget!$D$5:$D$44<=PeriodEnd)*(((Budget!$E$5:$E$44="")+(Budget!$E$5:$E$44>=PeriodStart))>0))) -> 0 | D35: =IF($B35="","",SUMIFS(Transactions!$E$5:$E$5004,Transactions!$D$5:$D$5004,$B35,Transactions!$A$5:$A$5004,">="&PeriodStart,Transactions!$A$5:$A$5004,"<="&PeriodEnd)) -> 0 | E35: =IF($B35="","",C35-D35) -> 0 | F35: =IF($B35="","",IF(C35=0,0,D35/C35)) -> 0 | G35: =IF($B35="","",IF(C35=0,IF(D35>0,"No budget","-"),IF(D35>C35,"OVER",IF(D35>=WarnPct*C35,"Watch","OK")))) -> -
B36: =IF(Settings!$B$16="","",Settings!$B$16) -> Entertainment & Leisure | C36: =IF($B36="","",SUMPRODUCT((Budget!$A$5:$A$44=$B36)*Budget!$C$5:$C$44*((Budget!$B$5:$B$44="Monthly")+(Budget!$B$5:$B$44="Daily")*DaysInMonth+(Budget!$B$5:$B$44="Weekly")*DaysInMonth/7)*(Budget!$D$5:$D$44<=PeriodEnd)*(((Budget!$E$5:$E$44="")+(Budget!$E$5:$E$44>=PeriodStart))>0))) -> 0 | D36: =IF($B36="","",SUMIFS(Transactions!$E$5:$E$5004,Transactions!$D$5:$D$5004,$B36,Transactions!$A$5:$A$5004,">="&PeriodStart,Transactions!$A$5:$A$5004,"<="&PeriodEnd)) -> 0 | E36: =IF($B36="","",C36-D36) -> 0 | F36: =IF($B36="","",IF(C36=0,0,D36/C36)) -> 0 | G36: =IF($B36="","",IF(C36=0,IF(D36>0,"No budget","-"),IF(D36>C36,"OVER",IF(D36>=WarnPct*C36,"Watch","OK")))) -> -
B37: =IF(Settings!$B$17="","",Settings!$B$17) -> Personal Care | C37: =IF($B37="","",SUMPRODUCT((Budget!$A$5:$A$44=$B37)*Budget!$C$5:$C$44*((Budget!$B$5:$B$44="Monthly")+(Budget!$B$5:$B$44="Daily")*DaysInMonth+(Budget!$B$5:$B$44="Weekly")*DaysInMonth/7)*(Budget!$D$5:$D$44<=PeriodEnd)*(((Budget!$E$5:$E$44="")+(Budget!$E$5:$E$44>=PeriodStart))>0))) -> 0 | D37: =IF($B37="","",SUMIFS(Transactions!$E$5:$E$5004,Transactions!$D$5:$D$5004,$B37,Transactions!$A$5:$A$5004,">="&PeriodStart,Transactions!$A$5:$A$5004,"<="&PeriodEnd)) -> 0 | E37: =IF($B37="","",C37-D37) -> 0 | F37: =IF($B37="","",IF(C37=0,0,D37/C37)) -> 0 | G37: =IF($B37="","",IF(C37=0,IF(D37>0,"No budget","-"),IF(D37>C37,"OVER",IF(D37>=WarnPct*C37,"Watch","OK")))) -> -
B38: =IF(Settings!$B$18="","",Settings!$B$18) -> Family & Support | C38: =IF($B38="","",SUMPRODUCT((Budget!$A$5:$A$44=$B38)*Budget!$C$5:$C$44*((Budget!$B$5:$B$44="Monthly")+(Budget!$B$5:$B$44="Daily")*DaysInMonth+(Budget!$B$5:$B$44="Weekly")*DaysInMonth/7)*(Budget!$D$5:$D$44<=PeriodEnd)*(((Budget!$E$5:$E$44="")+(Budget!$E$5:$E$44>=PeriodStart))>0))) -> 0 | D38: =IF($B38="","",SUMIFS(Transactions!$E$5:$E$5004,Transactions!$D$5:$D$5004,$B38,Transactions!$A$5:$A$5004,">="&PeriodStart,Transactions!$A$5:$A$5004,"<="&PeriodEnd)) -> 0 | E38: =IF($B38="","",C38-D38) -> 0 | F38: =IF($B38="","",IF(C38=0,0,D38/C38)) -> 0 | G38: =IF($B38="","",IF(C38=0,IF(D38>0,"No budget","-"),IF(D38>C38,"OVER",IF(D38>=WarnPct*C38,"Watch","OK")))) -> -
B39: =IF(Settings!$B$19="","",Settings!$B$19) -> Giving & Church | C39: =IF($B39="","",SUMPRODUCT((Budget!$A$5:$A$44=$B39)*Budget!$C$5:$C$44*((Budget!$B$5:$B$44="Monthly")+(Budget!$B$5:$B$44="Daily")*DaysInMonth+(Budget!$B$5:$B$44="Weekly")*DaysInMonth/7)*(Budget!$D$5:$D$44<=PeriodEnd)*(((Budget!$E$5:$E$44="")+(Budget!$E$5:$E$44>=PeriodStart))>0))) -> 0 | D39: =IF($B39="","",SUMIFS(Transactions!$E$5:$E$5004,Transactions!$D$5:$D$5004,$B39,Transactions!$A$5:$A$5004,">="&PeriodStart,Transactions!$A$5:$A$5004,"<="&PeriodEnd)) -> 0 | E39: =IF($B39="","",C39-D39) -> 0 | F39: =IF($B39="","",IF(C39=0,0,D39/C39)) -> 0 | G39: =IF($B39="","",IF(C39=0,IF(D39>0,"No budget","-"),IF(D39>C39,"OVER",IF(D39>=WarnPct*C39,"Watch","OK")))) -> -
B40: =IF(Settings!$B$20="","",Settings!$B$20) -> Loans & Debt | C40: =IF($B40="","",SUMPRODUCT((Budget!$A$5:$A$44=$B40)*Budget!$C$5:$C$44*((Budget!$B$5:$B$44="Monthly")+(Budget!$B$5:$B$44="Daily")*DaysInMonth+(Budget!$B$5:$B$44="Weekly")*DaysInMonth/7)*(Budget!$D$5:$D$44<=PeriodEnd)*(((Budget!$E$5:$E$44="")+(Budget!$E$5:$E$44>=PeriodStart))>0))) -> 0 | D40: =IF($B40="","",SUMIFS(Transactions!$E$5:$E$5004,Transactions!$D$5:$D$5004,$B40,Transactions!$A$5:$A$5004,">="&PeriodStart,Transactions!$A$5:$A$5004,"<="&PeriodEnd)) -> 0 | E40: =IF($B40="","",C40-D40) -> 0 | F40: =IF($B40="","",IF(C40=0,0,D40/C40)) -> 0 | G40: =IF($B40="","",IF(C40=0,IF(D40>0,"No budget","-"),IF(D40>C40,"OVER",IF(D40>=WarnPct*C40,"Watch","OK")))) -> -
B41: =IF(Settings!$B$21="","",Settings!$B$21) -> Other | C41: =IF($B41="","",SUMPRODUCT((Budget!$A$5:$A$44=$B41)*Budget!$C$5:$C$44*((Budget!$B$5:$B$44="Monthly")+(Budget!$B$5:$B$44="Daily")*DaysInMonth+(Budget!$B$5:$B$44="Weekly")*DaysInMonth/7)*(Budget!$D$5:$D$44<=PeriodEnd)*(((Budget!$E$5:$E$44="")+(Budget!$E$5:$E$44>=PeriodStart))>0))) -> 0 | D41: =IF($B41="","",SUMIFS(Transactions!$E$5:$E$5004,Transactions!$D$5:$D$5004,$B41,Transactions!$A$5:$A$5004,">="&PeriodStart,Transactions!$A$5:$A$5004,"<="&PeriodEnd)) -> 0 | E41: =IF($B41="","",C41-D41) -> 0 | F41: =IF($B41="","",IF(C41=0,0,D41/C41)) -> 0 | G41: =IF($B41="","",IF(C41=0,IF(D41>0,"No budget","-"),IF(D41>C41,"OVER",IF(D41>=WarnPct*C41,"Watch","OK")))) -> -
B42: TOTAL | C42: =SUM(C26:C41) -> 0 | D42: =SUM(D26:D41) -> 0 | E42: =C42-D42 -> 0 | F42: =IF(C42=0,0,D42/C42) -> 0 | G42: =IF(C42=0,"-",IF(D42>C42,"OVER",IF(D42>=WarnPct*C42,"Watch","OK"))) -> -
B45: INCOME BY SOURCE | F45: SPENDING BY PAYMENT METHOD
B46: Source | C46: Amount (KES) | D46: Share | F46: Method | G46: Amount (KES) | H46: Share
B47: =IF(Settings!$E$6="","",Settings!$E$6) -> Salary | C47: =IF($B47="","",SUMIFS(Income!$D$5:$D$2004,Income!$B$5:$B$2004,$B47,Income!$A$5:$A$2004,">="&PeriodStart,Income!$A$5:$A$2004,"<="&PeriodEnd)) -> 0 | D47: =IF($B47="","",IF($C$55=0,0,C47/$C$55)) -> 0 | F47: =IF(Settings!$D$6="","",Settings!$D$6) -> Cash | G47: =IF($F47="","",SUMIFS(Transactions!$E$5:$E$5004,Transactions!$F$5:$F$5004,$F47,Transactions!$A$5:$A$5004,">="&PeriodStart,Transactions!$A$5:$A$5004,"<="&PeriodEnd)) -> 0 | H47: =IF($F47="","",IF($G$55=0,0,G47/$G$55)) -> 0
B48: =IF(Settings!$E$7="","",Settings!$E$7) -> Business Income | C48: =IF($B48="","",SUMIFS(Income!$D$5:$D$2004,Income!$B$5:$B$2004,$B48,Income!$A$5:$A$2004,">="&PeriodStart,Income!$A$5:$A$2004,"<="&PeriodEnd)) -> 0 | D48: =IF($B48="","",IF($C$55=0,0,C48/$C$55)) -> 0 | F48: =IF(Settings!$D$7="","",Settings!$D$7) -> M-Pesa | G48: =IF($F48="","",SUMIFS(Transactions!$E$5:$E$5004,Transactions!$F$5:$F$5004,$F48,Transactions!$A$5:$A$5004,">="&PeriodStart,Transactions!$A$5:$A$5004,"<="&PeriodEnd)) -> 0 | H48: =IF($F48="","",IF($G$55=0,0,G48/$G$55)) -> 0
B49: =IF(Settings!$E$8="","",Settings!$E$8) -> Freelance / Client Project | C49: =IF($B49="","",SUMIFS(Income!$D$5:$D$2004,Income!$B$5:$B$2004,$B49,Income!$A$5:$A$2004,">="&PeriodStart,Income!$A$5:$A$2004,"<="&PeriodEnd)) -> 0 | D49: =IF($B49="","",IF($C$55=0,0,C49/$C$55)) -> 0 | F49: =IF(Settings!$D$8="","",Settings!$D$8) -> Bank Card | G49: =IF($F49="","",SUMIFS(Transactions!$E$5:$E$5004,Transactions!$F$5:$F$5004,$F49,Transactions!$A$5:$A$5004,">="&PeriodStart,Transactions!$A$5:$A$5004,"<="&PeriodEnd)) -> 0 | H49: =IF($F49="","",IF($G$55=0,0,G49/$G$55)) -> 0
B50: =IF(Settings!$E$9="","",Settings!$E$9) -> Side Hustle | C50: =IF($B50="","",SUMIFS(Income!$D$5:$D$2004,Income!$B$5:$B$2004,$B50,Income!$A$5:$A$2004,">="&PeriodStart,Income!$A$5:$A$2004,"<="&PeriodEnd)) -> 0 | D50: =IF($B50="","",IF($C$55=0,0,C50/$C$55)) -> 0 | F50: =IF(Settings!$D$9="","",Settings!$D$9) -> Bank Transfer | G50: =IF($F50="","",SUMIFS(Transactions!$E$5:$E$5004,Transactions!$F$5:$F$5004,$F50,Transactions!$A$5:$A$5004,">="&PeriodStart,Transactions!$A$5:$A$5004,"<="&PeriodEnd)) -> 0 | H50: =IF($F50="","",IF($G$55=0,0,G50/$G$55)) -> 0
B51: =IF(Settings!$E$10="","",Settings!$E$10) -> Gift / Support | C51: =IF($B51="","",SUMIFS(Income!$D$5:$D$2004,Income!$B$5:$B$2004,$B51,Income!$A$5:$A$2004,">="&PeriodStart,Income!$A$5:$A$2004,"<="&PeriodEnd)) -> 0 | D51: =IF($B51="","",IF($C$55=0,0,C51/$C$55)) -> 0 | F51: =IF(Settings!$D$10="","",Settings!$D$10) -> Airtel Money | G51: =IF($F51="","",SUMIFS(Transactions!$E$5:$E$5004,Transactions!$F$5:$F$5004,$F51,Transactions!$A$5:$A$5004,">="&PeriodStart,Transactions!$A$5:$A$5004,"<="&PeriodEnd)) -> 0 | H51: =IF($F51="","",IF($G$55=0,0,G51/$G$55)) -> 0
B52: =IF(Settings!$E$11="","",Settings!$E$11) -> Interest & Dividends | C52: =IF($B52="","",SUMIFS(Income!$D$5:$D$2004,Income!$B$5:$B$2004,$B52,Income!$A$5:$A$2004,">="&PeriodStart,Income!$A$5:$A$2004,"<="&PeriodEnd)) -> 0 | D52: =IF($B52="","",IF($C$55=0,0,C52/$C$55)) -> 0 | F52: =IF(Settings!$D$11="","",Settings!$D$11) -> Other | G52: =IF($F52="","",SUMIFS(Transactions!$E$5:$E$5004,Transactions!$F$5:$F$5004,$F52,Transactions!$A$5:$A$5004,">="&PeriodStart,Transactions!$A$5:$A$5004,"<="&PeriodEnd)) -> 0 | H52: =IF($F52="","",IF($G$55=0,0,G52/$G$55)) -> 0
B53: =IF(Settings!$E$12="","",Settings!$E$12) -> Rental Income | C53: =IF($B53="","",SUMIFS(Income!$D$5:$D$2004,Income!$B$5:$B$2004,$B53,Income!$A$5:$A$2004,">="&PeriodStart,Income!$A$5:$A$2004,"<="&PeriodEnd)) -> 0 | D53: =IF($B53="","",IF($C$55=0,0,C53/$C$55)) -> 0 | F53: =IF(Settings!$D$12="","",Settings!$D$12) | G53: =IF($F53="","",SUMIFS(Transactions!$E$5:$E$5004,Transactions!$F$5:$F$5004,$F53,Transactions!$A$5:$A$5004,">="&PeriodStart,Transactions!$A$5:$A$5004,"<="&PeriodEnd)) | H53: =IF($F53="","",IF($G$55=0,0,G53/$G$55))
B54: =IF(Settings!$E$13="","",Settings!$E$13) -> Other Income | C54: =IF($B54="","",SUMIFS(Income!$D$5:$D$2004,Income!$B$5:$B$2004,$B54,Income!$A$5:$A$2004,">="&PeriodStart,Income!$A$5:$A$2004,"<="&PeriodEnd)) -> 0 | D54: =IF($B54="","",IF($C$55=0,0,C54/$C$55)) -> 0 | F54: =IF(Settings!$D$13="","",Settings!$D$13) | G54: =IF($F54="","",SUMIFS(Transactions!$E$5:$E$5004,Transactions!$F$5:$F$5004,$F54,Transactions!$A$5:$A$5004,">="&PeriodStart,Transactions!$A$5:$A$5004,"<="&PeriodEnd)) | H54: =IF($F54="","",IF($G$55=0,0,G54/$G$55))
B55: TOTAL | C55: =SUM(C47:C54) -> 0 | F55: TOTAL | G55: =SUM(G47:G54) -> 0
B58: TOP 5 BIGGEST EXPENSES THIS PERIOD
B59: Item | C59: Date | D59: Amount | E59: Category | G59: Paid With
B60: =IF(LARGE(Transactions!$J$5:$J$5004,1)=0,"",INDEX(Transactions!$C$5:$C$5004,MATCH(LARGE(Transactions!$J$5:$J$5004,1),Transactions!$J$5:$J$5004,0))&"") | C60: =IF(LARGE(Transactions!$J$5:$J$5004,1)=0,"",INDEX(Transactions!$A$5:$A$5004,MATCH(LARGE(Transactions!$J$5:$J$5004,1),Transactions!$J$5:$J$5004,0))) | D60: =IF(LARGE(Transactions!$J$5:$J$5004,1)=0,"",INDEX(Transactions!$E$5:$E$5004,MATCH(LARGE(Transactions!$J$5:$J$5004,1),Transactions!$J$5:$J$5004,0))) | E60: =IF(LARGE(Transactions!$J$5:$J$5004,1)=0,"",INDEX(Transactions!$D$5:$D$5004,MATCH(LARGE(Transactions!$J$5:$J$5004,1),Transactions!$J$5:$J$5004,0))&"") | G60: =IF(LARGE(Transactions!$J$5:$J$5004,1)=0,"",INDEX(Transactions!$F$5:$F$5004,MATCH(LARGE(Transactions!$J$5:$J$5004,1),Transactions!$J$5:$J$5004,0))&"")
B61: =IF(LARGE(Transactions!$J$5:$J$5004,2)=0,"",INDEX(Transactions!$C$5:$C$5004,MATCH(LARGE(Transactions!$J$5:$J$5004,2),Transactions!$J$5:$J$5004,0))&"") | C61: =IF(LARGE(Transactions!$J$5:$J$5004,2)=0,"",INDEX(Transactions!$A$5:$A$5004,MATCH(LARGE(Transactions!$J$5:$J$5004,2),Transactions!$J$5:$J$5004,0))) | D61: =IF(LARGE(Transactions!$J$5:$J$5004,2)=0,"",INDEX(Transactions!$E$5:$E$5004,MATCH(LARGE(Transactions!$J$5:$J$5004,2),Transactions!$J$5:$J$5004,0))) | E61: =IF(LARGE(Transactions!$J$5:$J$5004,2)=0,"",INDEX(Transactions!$D$5:$D$5004,MATCH(LARGE(Transactions!$J$5:$J$5004,2),Transactions!$J$5:$J$5004,0))&"") | G61: =IF(LARGE(Transactions!$J$5:$J$5004,2)=0,"",INDEX(Transactions!$F$5:$F$5004,MATCH(LARGE(Transactions!$J$5:$J$5004,2),Transactions!$J$5:$J$5004,0))&"")
B62: =IF(LARGE(Transactions!$J$5:$J$5004,3)=0,"",INDEX(Transactions!$C$5:$C$5004,MATCH(LARGE(Transactions!$J$5:$J$5004,3),Transactions!$J$5:$J$5004,0))&"") | C62: =IF(LARGE(Transactions!$J$5:$J$5004,3)=0,"",INDEX(Transactions!$A$5:$A$5004,MATCH(LARGE(Transactions!$J$5:$J$5004,3),Transactions!$J$5:$J$5004,0))) | D62: =IF(LARGE(Transactions!$J$5:$J$5004,3)=0,"",INDEX(Transactions!$E$5:$E$5004,MATCH(LARGE(Transactions!$J$5:$J$5004,3),Transactions!$J$5:$J$5004,0))) | E62: =IF(LARGE(Transactions!$J$5:$J$5004,3)=0,"",INDEX(Transactions!$D$5:$D$5004,MATCH(LARGE(Transactions!$J$5:$J$5004,3),Transactions!$J$5:$J$5004,0))&"") | G62: =IF(LARGE(Transactions!$J$5:$J$5004,3)=0,"",INDEX(Transactions!$F$5:$F$5004,MATCH(LARGE(Transactions!$J$5:$J$5004,3),Transactions!$J$5:$J$5004,0))&"")
B63: =IF(LARGE(Transactions!$J$5:$J$5004,4)=0,"",INDEX(Transactions!$C$5:$C$5004,MATCH(LARGE(Transactions!$J$5:$J$5004,4),Transactions!$J$5:$J$5004,0))&"") | C63: =IF(LARGE(Transactions!$J$5:$J$5004,4)=0,"",INDEX(Transactions!$A$5:$A$5004,MATCH(LARGE(Transactions!$J$5:$J$5004,4),Transactions!$J$5:$J$5004,0))) | D63: =IF(LARGE(Transactions!$J$5:$J$5004,4)=0,"",INDEX(Transactions!$E$5:$E$5004,MATCH(LARGE(Transactions!$J$5:$J$5004,4),Transactions!$J$5:$J$5004,0))) | E63: =IF(LARGE(Transactions!$J$5:$J$5004,4)=0,"",INDEX(Transactions!$D$5:$D$5004,MATCH(LARGE(Transactions!$J$5:$J$5004,4),Transactions!$J$5:$J$5004,0))&"") | G63: =IF(LARGE(Transactions!$J$5:$J$5004,4)=0,"",INDEX(Transactions!$F$5:$F$5004,MATCH(LARGE(Transactions!$J$5:$J$5004,4),Transactions!$J$5:$J$5004,0))&"")
B64: =IF(LARGE(Transactions!$J$5:$J$5004,5)=0,"",INDEX(Transactions!$C$5:$C$5004,MATCH(LARGE(Transactions!$J$5:$J$5004,5),Transactions!$J$5:$J$5004,0))&"") | C64: =IF(LARGE(Transactions!$J$5:$J$5004,5)=0,"",INDEX(Transactions!$A$5:$A$5004,MATCH(LARGE(Transactions!$J$5:$J$5004,5),Transactions!$J$5:$J$5004,0))) | D64: =IF(LARGE(Transactions!$J$5:$J$5004,5)=0,"",INDEX(Transactions!$E$5:$E$5004,MATCH(LARGE(Transactions!$J$5:$J$5004,5),Transactions!$J$5:$J$5004,0))) | E64: =IF(LARGE(Transactions!$J$5:$J$5004,5)=0,"",INDEX(Transactions!$D$5:$D$5004,MATCH(LARGE(Transactions!$J$5:$J$5004,5),Transactions!$J$5:$J$5004,0))&"") | G64: =IF(LARGE(Transactions!$J$5:$J$5004,5)=0,"",INDEX(Transactions!$F$5:$F$5004,MATCH(LARGE(Transactions!$J$5:$J$5004,5),Transactions!$J$5:$J$5004,0))&"")
B67: DAILY SPENDING vs DAILY ALLOWANCE
B68: Date | C68: Day | D68: Spent | E68: Daily allowance | F68: Status
A69: =IF(B69="","",DAY(B69)) -> 1 | B69: =IF(1>DaysInMonth,"",PeriodStart+0) -> 46296 | C69: =IF(B69="","",TEXT(B69,"dddd")) -> Thursday | D69: =IF(B69="","",SUMIFS(Transactions!$E$5:$E$5004,Transactions!$A$5:$A$5004,B69)) -> 0 | E69: =IF(B69="","",IF($C$13=0,0,$C$13/DaysInMonth)) -> 0 | F69: =IF(B69="","",IF(B69>TODAY(),"-",IF(E69=0,IF(D69>0,"No budget","-"),IF(D69>E69,"OVER",IF(D69=0,"No spend","OK"))))) -> -
A70: =IF(B70="","",DAY(B70)) -> 2 | B70: =IF(2>DaysInMonth,"",PeriodStart+1) -> 46297 | C70: =IF(B70="","",TEXT(B70,"dddd")) -> Friday | D70: =IF(B70="","",SUMIFS(Transactions!$E$5:$E$5004,Transactions!$A$5:$A$5004,B70)) -> 0 | E70: =IF(B70="","",IF($C$13=0,0,$C$13/DaysInMonth)) -> 0 | F70: =IF(B70="","",IF(B70>TODAY(),"-",IF(E70=0,IF(D70>0,"No budget","-"),IF(D70>E70,"OVER",IF(D70=0,"No spend","OK"))))) -> -
A71: =IF(B71="","",DAY(B71)) -> 3 | B71: =IF(3>DaysInMonth,"",PeriodStart+2) -> 46298 | C71: =IF(B71="","",TEXT(B71,"dddd")) -> Saturday | D71: =IF(B71="","",SUMIFS(Transactions!$E$5:$E$5004,Transactions!$A$5:$A$5004,B71)) -> 0 | E71: =IF(B71="","",IF($C$13=0,0,$C$13/DaysInMonth)) -> 0 | F71: =IF(B71="","",IF(B71>TODAY(),"-",IF(E71=0,IF(D71>0,"No budget","-"),IF(D71>E71,"OVER",IF(D71=0,"No spend","OK"))))) -> -
A72: =IF(B72="","",DAY(B72)) -> 4 | B72: =IF(4>DaysInMonth,"",PeriodStart+3) -> 46299 | C72: =IF(B72="","",TEXT(B72,"dddd")) -> Sunday | D72: =IF(B72="","",SUMIFS(Transactions!$E$5:$E$5004,Transactions!$A$5:$A$5004,B72)) -> 0 | E72: =IF(B72="","",IF($C$13=0,0,$C$13/DaysInMonth)) -> 0 | F72: =IF(B72="","",IF(B72>TODAY(),"-",IF(E72=0,IF(D72>0,"No budget","-"),IF(D72>E72,"OVER",IF(D72=0,"No spend","OK"))))) -> -
A73: =IF(B73="","",DAY(B73)) -> 5 | B73: =IF(5>DaysInMonth,"",PeriodStart+4) -> 46300 | C73: =IF(B73="","",TEXT(B73,"dddd")) -> Monday | D73: =IF(B73="","",SUMIFS(Transactions!$E$5:$E$5004,Transactions!$A$5:$A$5004,B73)) -> 0 | E73: =IF(B73="","",IF($C$13=0,0,$C$13/DaysInMonth)) -> 0 | F73: =IF(B73="","",IF(B73>TODAY(),"-",IF(E73=0,IF(D73>0,"No budget","-"),IF(D73>E73,"OVER",IF(D73=0,"No spend","OK"))))) -> -
A74: =IF(B74="","",DAY(B74)) -> 6 | B74: =IF(6>DaysInMonth,"",PeriodStart+5) -> 46301 | C74: =IF(B74="","",TEXT(B74,"dddd")) -> Tuesday | D74: =IF(B74="","",SUMIFS(Transactions!$E$5:$E$5004,Transactions!$A$5:$A$5004,B74)) -> 0 | E74: =IF(B74="","",IF($C$13=0,0,$C$13/DaysInMonth)) -> 0 | F74: =IF(B74="","",IF(B74>TODAY(),"-",IF(E74=0,IF(D74>0,"No budget","-"),IF(D74>E74,"OVER",IF(D74=0,"No spend","OK"))))) -> -
A75: =IF(B75="","",DAY(B75)) -> 7 | B75: =IF(7>DaysInMonth,"",PeriodStart+6) -> 46302 | C75: =IF(B75="","",TEXT(B75,"dddd")) -> Wednesday | D75: =IF(B75="","",SUMIFS(Transactions!$E$5:$E$5004,Transactions!$A$5:$A$5004,B75)) -> 0 | E75: =IF(B75="","",IF($C$13=0,0,$C$13/DaysInMonth)) -> 0 | F75: =IF(B75="","",IF(B75>TODAY(),"-",IF(E75=0,IF(D75>0,"No budget","-"),IF(D75>E75,"OVER",IF(D75=0,"No spend","OK"))))) -> -
A76: =IF(B76="","",DAY(B76)) -> 8 | B76: =IF(8>DaysInMonth,"",PeriodStart+7) -> 46303 | C76: =IF(B76="","",TEXT(B76,"dddd")) -> Thursday | D76: =IF(B76="","",SUMIFS(Transactions!$E$5:$E$5004,Transactions!$A$5:$A$5004,B76)) -> 0 | E76: =IF(B76="","",IF($C$13=0,0,$C$13/DaysInMonth)) -> 0 | F76: =IF(B76="","",IF(B76>TODAY(),"-",IF(E76=0,IF(D76>0,"No budget","-"),IF(D76>E76,"OVER",IF(D76=0,"No spend","OK"))))) -> -
A77: =IF(B77="","",DAY(B77)) -> 9 | B77: =IF(9>DaysInMonth,"",PeriodStart+8) -> 46304 | C77: =IF(B77="","",TEXT(B77,"dddd")) -> Friday | D77: =IF(B77="","",SUMIFS(Transactions!$E$5:$E$5004,Transactions!$A$5:$A$5004,B77)) -> 0 | E77: =IF(B77="","",IF($C$13=0,0,$C$13/DaysInMonth)) -> 0 | F77: =IF(B77="","",IF(B77>TODAY(),"-",IF(E77=0,IF(D77>0,"No budget","-"),IF(D77>E77,"OVER",IF(D77=0,"No spend","OK"))))) -> -
A78: =IF(B78="","",DAY(B78)) -> 10 | B78: =IF(10>DaysInMonth,"",PeriodStart+9) -> 46305 | C78: =IF(B78="","",TEXT(B78,"dddd")) -> Saturday | D78: =IF(B78="","",SUMIFS(Transactions!$E$5:$E$5004,Transactions!$A$5:$A$5004,B78)) -> 0 | E78: =IF(B78="","",IF($C$13=0,0,$C$13/DaysInMonth)) -> 0 | F78: =IF(B78="","",IF(B78>TODAY(),"-",IF(E78=0,IF(D78>0,"No budget","-"),IF(D78>E78,"OVER",IF(D78=0,"No spend","OK"))))) -> -
A79: =IF(B79="","",DAY(B79)) -> 11 | B79: =IF(11>DaysInMonth,"",PeriodStart+10) -> 46306 | C79: =IF(B79="","",TEXT(B79,"dddd")) -> Sunday | D79: =IF(B79="","",SUMIFS(Transactions!$E$5:$E$5004,Transactions!$A$5:$A$5004,B79)) -> 0 | E79: =IF(B79="","",IF($C$13=0,0,$C$13/DaysInMonth)) -> 0 | F79: =IF(B79="","",IF(B79>TODAY(),"-",IF(E79=0,IF(D79>0,"No budget","-"),IF(D79>E79,"OVER",IF(D79=0,"No spend","OK"))))) -> -
A80: =IF(B80="","",DAY(B80)) -> 12 | B80: =IF(12>DaysInMonth,"",PeriodStart+11) -> 46307 | C80: =IF(B80="","",TEXT(B80,"dddd")) -> Monday | D80: =IF(B80="","",SUMIFS(Transactions!$E$5:$E$5004,Transactions!$A$5:$A$5004,B80)) -> 0 | E80: =IF(B80="","",IF($C$13=0,0,$C$13/DaysInMonth)) -> 0 | F80: =IF(B80="","",IF(B80>TODAY(),"-",IF(E80=0,IF(D80>0,"No budget","-"),IF(D80>E80,"OVER",IF(D80=0,"No spend","OK"))))) -> -
A81: =IF(B81="","",DAY(B81)) -> 13 | B81: =IF(13>DaysInMonth,"",PeriodStart+12) -> 46308 | C81: =IF(B81="","",TEXT(B81,"dddd")) -> Tuesday | D81: =IF(B81="","",SUMIFS(Transactions!$E$5:$E$5004,Transactions!$A$5:$A$5004,B81)) -> 0 | E81: =IF(B81="","",IF($C$13=0,0,$C$13/DaysInMonth)) -> 0 | F81: =IF(B81="","",IF(B81>TODAY(),"-",IF(E81=0,IF(D81>0,"No budget","-"),IF(D81>E81,"OVER",IF(D81=0,"No spend","OK"))))) -> -
A82: =IF(B82="","",DAY(B82)) -> 14 | B82: =IF(14>DaysInMonth,"",PeriodStart+13) -> 46309 | C82: =IF(B82="","",TEXT(B82,"dddd")) -> Wednesday | D82: =IF(B82="","",SUMIFS(Transactions!$E$5:$E$5004,Transactions!$A$5:$A$5004,B82)) -> 0 | E82: =IF(B82="","",IF($C$13=0,0,$C$13/DaysInMonth)) -> 0 | F82: =IF(B82="","",IF(B82>TODAY(),"-",IF(E82=0,IF(D82>0,"No budget","-"),IF(D82>E82,"OVER",IF(D82=0,"No spend","OK"))))) -> -
A83: =IF(B83="","",DAY(B83)) -> 15 | B83: =IF(15>DaysInMonth,"",PeriodStart+14) -> 46310 | C83: =IF(B83="","",TEXT(B83,"dddd")) -> Thursday | D83: =IF(B83="","",SUMIFS(Transactions!$E$5:$E$5004,Transactions!$A$5:$A$5004,B83)) -> 0 | E83: =IF(B83="","",IF($C$13=0,0,$C$13/DaysInMonth)) -> 0 | F83: =IF(B83="","",IF(B83>TODAY(),"-",IF(E83=0,IF(D83>0,"No budget","-"),IF(D83>E83,"OVER",IF(D83=0,"No spend","OK"))))) -> -
A84: =IF(B84="","",DAY(B84)) -> 16 | B84: =IF(16>DaysInMonth,"",PeriodStart+15) -> 46311 | C84: =IF(B84="","",TEXT(B84,"dddd")) -> Friday | D84: =IF(B84="","",SUMIFS(Transactions!$E$5:$E$5004,Transactions!$A$5:$A$5004,B84)) -> 0 | E84: =IF(B84="","",IF($C$13=0,0,$C$13/DaysInMonth)) -> 0 | F84: =IF(B84="","",IF(B84>TODAY(),"-",IF(E84=0,IF(D84>0,"No budget","-"),IF(D84>E84,"OVER",IF(D84=0,"No spend","OK"))))) -> -
A85: =IF(B85="","",DAY(B85)) -> 17 | B85: =IF(17>DaysInMonth,"",PeriodStart+16) -> 46312 | C85: =IF(B85="","",TEXT(B85,"dddd")) -> Saturday | D85: =IF(B85="","",SUMIFS(Transactions!$E$5:$E$5004,Transactions!$A$5:$A$5004,B85)) -> 0 | E85: =IF(B85="","",IF($C$13=0,0,$C$13/DaysInMonth)) -> 0 | F85: =IF(B85="","",IF(B85>TODAY(),"-",IF(E85=0,IF(D85>0,"No budget","-"),IF(D85>E85,"OVER",IF(D85=0,"No spend","OK"))))) -> -
A86: =IF(B86="","",DAY(B86)) -> 18 | B86: =IF(18>DaysInMonth,"",PeriodStart+17) -> 46313 | C86: =IF(B86="","",TEXT(B86,"dddd")) -> Sunday | D86: =IF(B86="","",SUMIFS(Transactions!$E$5:$E$5004,Transactions!$A$5:$A$5004,B86)) -> 0 | E86: =IF(B86="","",IF($C$13=0,0,$C$13/DaysInMonth)) -> 0 | F86: =IF(B86="","",IF(B86>TODAY(),"-",IF(E86=0,IF(D86>0,"No budget","-"),IF(D86>E86,"OVER",IF(D86=0,"No spend","OK"))))) -> -
A87: =IF(B87="","",DAY(B87)) -> 19 | B87: =IF(19>DaysInMonth,"",PeriodStart+18) -> 46314 | C87: =IF(B87="","",TEXT(B87,"dddd")) -> Monday | D87: =IF(B87="","",SUMIFS(Transactions!$E$5:$E$5004,Transactions!$A$5:$A$5004,B87)) -> 0 | E87: =IF(B87="","",IF($C$13=0,0,$C$13/DaysInMonth)) -> 0 | F87: =IF(B87="","",IF(B87>TODAY(),"-",IF(E87=0,IF(D87>0,"No budget","-"),IF(D87>E87,"OVER",IF(D87=0,"No spend","OK"))))) -> -
A88: =IF(B88="","",DAY(B88)) -> 20 | B88: =IF(20>DaysInMonth,"",PeriodStart+19) -> 46315 | C88: =IF(B88="","",TEXT(B88,"dddd")) -> Tuesday | D88: =IF(B88="","",SUMIFS(Transactions!$E$5:$E$5004,Transactions!$A$5:$A$5004,B88)) -> 0 | E88: =IF(B88="","",IF($C$13=0,0,$C$13/DaysInMonth)) -> 0 | F88: =IF(B88="","",IF(B88>TODAY(),"-",IF(E88=0,IF(D88>0,"No budget","-"),IF(D88>E88,"OVER",IF(D88=0,"No spend","OK"))))) -> -
A89: =IF(B89="","",DAY(B89)) -> 21 | B89: =IF(21>DaysInMonth,"",PeriodStart+20) -> 46316 | C89: =IF(B89="","",TEXT(B89,"dddd")) -> Wednesday | D89: =IF(B89="","",SUMIFS(Transactions!$E$5:$E$5004,Transactions!$A$5:$A$5004,B89)) -> 0 | E89: =IF(B89="","",IF($C$13=0,0,$C$13/DaysInMonth)) -> 0 | F89: =IF(B89="","",IF(B89>TODAY(),"-",IF(E89=0,IF(D89>0,"No budget","-"),IF(D89>E89,"OVER",IF(D89=0,"No spend","OK"))))) -> -
A90: =IF(B90="","",DAY(B90)) -> 22 | B90: =IF(22>DaysInMonth,"",PeriodStart+21) -> 46317 | C90: =IF(B90="","",TEXT(B90,"dddd")) -> Thursday | D90: =IF(B90="","",SUMIFS(Transactions!$E$5:$E$5004,Transactions!$A$5:$A$5004,B90)) -> 0 | E90: =IF(B90="","",IF($C$13=0,0,$C$13/DaysInMonth)) -> 0 | F90: =IF(B90="","",IF(B90>TODAY(),"-",IF(E90=0,IF(D90>0,"No budget","-"),IF(D90>E90,"OVER",IF(D90=0,"No spend","OK"))))) -> -
A91: =IF(B91="","",DAY(B91)) -> 23 | B91: =IF(23>DaysInMonth,"",PeriodStart+22) -> 46318 | C91: =IF(B91="","",TEXT(B91,"dddd")) -> Friday | D91: =IF(B91="","",SUMIFS(Transactions!$E$5:$E$5004,Transactions!$A$5:$A$5004,B91)) -> 0 | E91: =IF(B91="","",IF($C$13=0,0,$C$13/DaysInMonth)) -> 0 | F91: =IF(B91="","",IF(B91>TODAY(),"-",IF(E91=0,IF(D91>0,"No budget","-"),IF(D91>E91,"OVER",IF(D91=0,"No spend","OK"))))) -> -
A92: =IF(B92="","",DAY(B92)) -> 24 | B92: =IF(24>DaysInMonth,"",PeriodStart+23) -> 46319 | C92: =IF(B92="","",TEXT(B92,"dddd")) -> Saturday | D92: =IF(B92="","",SUMIFS(Transactions!$E$5:$E$5004,Transactions!$A$5:$A$5004,B92)) -> 0 | E92: =IF(B92="","",IF($C$13=0,0,$C$13/DaysInMonth)) -> 0 | F92: =IF(B92="","",IF(B92>TODAY(),"-",IF(E92=0,IF(D92>0,"No budget","-"),IF(D92>E92,"OVER",IF(D92=0,"No spend","OK"))))) -> -
A93: =IF(B93="","",DAY(B93)) -> 25 | B93: =IF(25>DaysInMonth,"",PeriodStart+24) -> 46320 | C93: =IF(B93="","",TEXT(B93,"dddd")) -> Sunday | D93: =IF(B93="","",SUMIFS(Transactions!$E$5:$E$5004,Transactions!$A$5:$A$5004,B93)) -> 0 | E93: =IF(B93="","",IF($C$13=0,0,$C$13/DaysInMonth)) -> 0 | F93: =IF(B93="","",IF(B93>TODAY(),"-",IF(E93=0,IF(D93>0,"No budget","-"),IF(D93>E93,"OVER",IF(D93=0,"No spend","OK"))))) -> -
A94: =IF(B94="","",DAY(B94)) -> 26 | B94: =IF(26>DaysInMonth,"",PeriodStart+25) -> 46321 | C94: =IF(B94="","",TEXT(B94,"dddd")) -> Monday | D94: =IF(B94="","",SUMIFS(Transactions!$E$5:$E$5004,Transactions!$A$5:$A$5004,B94)) -> 0 | E94: =IF(B94="","",IF($C$13=0,0,$C$13/DaysInMonth)) -> 0 | F94: =IF(B94="","",IF(B94>TODAY(),"-",IF(E94=0,IF(D94>0,"No budget","-"),IF(D94>E94,"OVER",IF(D94=0,"No spend","OK"))))) -> -
A95: =IF(B95="","",DAY(B95)) -> 27 | B95: =IF(27>DaysInMonth,"",PeriodStart+26) -> 46322 | C95: =IF(B95="","",TEXT(B95,"dddd")) -> Tuesday | D95: =IF(B95="","",SUMIFS(Transactions!$E$5:$E$5004,Transactions!$A$5:$A$5004,B95)) -> 0 | E95: =IF(B95="","",IF($C$13=0,0,$C$13/DaysInMonth)) -> 0 | F95: =IF(B95="","",IF(B95>TODAY(),"-",IF(E95=0,IF(D95>0,"No budget","-"),IF(D95>E95,"OVER",IF(D95=0,"No spend","OK"))))) -> -
A96: =IF(B96="","",DAY(B96)) -> 28 | B96: =IF(28>DaysInMonth,"",PeriodStart+27) -> 46323 | C96: =IF(B96="","",TEXT(B96,"dddd")) -> Wednesday | D96: =IF(B96="","",SUMIFS(Transactions!$E$5:$E$5004,Transactions!$A$5:$A$5004,B96)) -> 0 | E96: =IF(B96="","",IF($C$13=0,0,$C$13/DaysInMonth)) -> 0 | F96: =IF(B96="","",IF(B96>TODAY(),"-",IF(E96=0,IF(D96>0,"No budget","-"),IF(D96>E96,"OVER",IF(D96=0,"No spend","OK"))))) -> -
A97: =IF(B97="","",DAY(B97)) -> 29 | B97: =IF(29>DaysInMonth,"",PeriodStart+28) -> 46324 | C97: =IF(B97="","",TEXT(B97,"dddd")) -> Thursday | D97: =IF(B97="","",SUMIFS(Transactions!$E$5:$E$5004,Transactions!$A$5:$A$5004,B97)) -> 0 | E97: =IF(B97="","",IF($C$13=0,0,$C$13/DaysInMonth)) -> 0 | F97: =IF(B97="","",IF(B97>TODAY(),"-",IF(E97=0,IF(D97>0,"No budget","-"),IF(D97>E97,"OVER",IF(D97=0,"No spend","OK"))))) -> -
A98: =IF(B98="","",DAY(B98)) -> 30 | B98: =IF(30>DaysInMonth,"",PeriodStart+29) -> 46325 | C98: =IF(B98="","",TEXT(B98,"dddd")) -> Friday | D98: =IF(B98="","",SUMIFS(Transactions!$E$5:$E$5004,Transactions!$A$5:$A$5004,B98)) -> 0 | E98: =IF(B98="","",IF($C$13=0,0,$C$13/DaysInMonth)) -> 0 | F98: =IF(B98="","",IF(B98>TODAY(),"-",IF(E98=0,IF(D98>0,"No budget","-"),IF(D98>E98,"OVER",IF(D98=0,"No spend","OK"))))) -> -
A99: =IF(B99="","",DAY(B99)) -> 31 | B99: =IF(31>DaysInMonth,"",PeriodStart+30) -> 46326 | C99: =IF(B99="","",TEXT(B99,"dddd")) -> Saturday | D99: =IF(B99="","",SUMIFS(Transactions!$E$5:$E$5004,Transactions!$A$5:$A$5004,B99)) -> 0 | E99: =IF(B99="","",IF($C$13=0,0,$C$13/DaysInMonth)) -> 0 | F99: =IF(B99="","",IF(B99>TODAY(),"-",IF(E99=0,IF(D99>0,"No budget","-"),IF(D99>E99,"OVER",IF(D99=0,"No spend","OK"))))) -> -
B101: Sample or real, every figure on this page is calculated from the Transactions, Income and Budget sheets - nothing here needs typing except the Year and Month at the top.

Sheet Transactions
A1: Daily Transactions
A2: Record every spend on its own row the day it happens. Shortcuts: Ctrl+; = today's date | Ctrl+Shift+; = current time | Alt+Down Arrow = open a dropdown. Use the filter arrows on row 4 to find anything by date, time or item.
A3: Records: | B3: =COUNT(E5:E5004) -> 0 | C3: Total recorded (all dates, KES): | D3: =SUM(E5:E5004) -> 0
A4: Date | B4: Time | C4: Item / Product | D4: Category | E4: Amount (KES) | F4: Paid With | G4: Notes | H4: match # | I4: match amt | J4: top key
H5: =N(H4)+IFERROR(IF(AND($A5<>"",$E5<>"",$A5>=IF(Search!$E$4="",0,Search!$E$4),$A5<=IF(Search!$E$5="",99999,Search!$E$5),OR(Search!$E$6="",ISNUMBER(SEARCH(Search!$E$6,$C5))),OR(Search!$E$7="All",Search!$E$7="",$D5=Search!$E$7),OR(Search!$E$8="",Search!$E$9="",AND($B5<>"",MOD($B5,1)>=Search!$E$8,MOD($B5,1)<=Search!$E$9))),1,0),0) -> 0 | I5: =IF(H5>N(H4),$E5,0) -> 0 | J5: =IFERROR(IF(AND($A5<>"",$E5<>"",$A5>=PeriodStart,$A5<=PeriodEnd),$E5+ROW()/1000000,0),0) -> 0
H6: =N(H5)+IFERROR(IF(AND($A6<>"",$E6<>"",$A6>=IF(Search!$E$4="",0,Search!$E$4),$A6<=IF(Search!$E$5="",99999,Search!$E$5),OR(Search!$E$6="",ISNUMBER(SEARCH(Search!$E$6,$C6))),OR(Search!$E$7="All",Search!$E$7="",$D6=Search!$E$7),OR(Search!$E$8="",Search!$E$9="",AND($B6<>"",MOD($B6,1)>=Search!$E$8,MOD($B6,1)<=Search!$E$9))),1,0),0) -> 0 | I6: =IF(H6>N(H5),$E6,0) -> 0 | J6: =IFERROR(IF(AND($A6<>"",$E6<>"",$A6>=PeriodStart,$A6<=PeriodEnd),$E6+ROW()/1000000,0),0) -> 0
H7: =N(H6)+IFERROR(IF(AND($A7<>"",$E7<>"",$A7>=IF(Search!$E$4="",0,Search!$E$4),$A7<=IF(Search!$E$5="",99999,Search!$E$5),OR(Search!$E$6="",ISNUMBER(SEARCH(Search!$E$6,$C7))),OR(Search!$E$7="All",Search!$E$7="",$D7=Search!$E$7),OR(Search!$E$8="",Search!$E$9="",AND($B7<>"",MOD($B7,1)>=Search!$E$8,MOD($B7,1)<=Search!$E$9))),1,0),0) -> 0 | I7: =IF(H7>N(H6),$E7,0) -> 0 | J7: =IFERROR(IF(AND($A7<>"",$E7<>"",$A7>=PeriodStart,$A7<=PeriodEnd),$E7+ROW()/1000000,0),0) -> 0
H8: =N(H7)+IFERROR(IF(AND($A8<>"",$E8<>"",$A8>=IF(Search!$E$4="",0,Search!$E$4),$A8<=IF(Search!$E$5="",99999,Search!$E$5),OR(Search!$E$6="",ISNUMBER(SEARCH(Search!$E$6,$C8))),OR(Search!$E$7="All",Search!$E$7="",$D8=Search!$E$7),OR(Search!$E$8="",Search!$E$9="",AND($B8<>"",MOD($B8,1)>=Search!$E$8,MOD($B8,1)<=Search!$E$9))),1,0),0) -> 0 | I8: =IF(H8>N(H7),$E8,0) -> 0 | J8: =IFERROR(IF(AND($A8<>"",$E8<>"",$A8>=PeriodStart,$A8<=PeriodEnd),$E8+ROW()/1000000,0),0) -> 0
H9: =N(H8)+IFERROR(IF(AND($A9<>"",$E9<>"",$A9>=IF(Search!$E$4="",0,Search!$E$4),$A9<=IF(Search!$E$5="",99999,Search!$E$5),OR(Search!$E$6="",ISNUMBER(SEARCH(Search!$E$6,$C9))),OR(Search!$E$7="All",Search!$E$7="",$D9=Search!$E$7),OR(Search!$E$8="",Search!$E$9="",AND($B9<>"",MOD($B9,1)>=Search!$E$8,MOD($B9,1)<=Search!$E$9))),1,0),0) -> 0 | I9: =IF(H9>N(H8),$E9,0) -> 0 | J9: =IFERROR(IF(AND($A9<>"",$E9<>"",$A9>=PeriodStart,$A9<=PeriodEnd),$E9+ROW()/1000000,0),0) -> 0
H10: =N(H9)+IFERROR(IF(AND($A10<>"",$E10<>"",$A10>=IF(Search!$E$4="",0,Search!$E$4),$A10<=IF(Search!$E$5="",99999,Search!$E$5),OR(Search!$E$6="",ISNUMBER(SEARCH(Search!$E$6,$C10))),OR(Search!$E$7="All",Search!$E$7="",$D10=Search!$E$7),OR(Search!$E$8="",Search!$E$9="",AND($B10<>"",MOD($B10,1)>=Search!$E$8,MOD($B10,1)<=Search!$E$9))),1,0),0) -> 0 | I10: =IF(H10>N(H9),$E10,0) -> 0 | J10: =IFERROR(IF(AND($A10<>"",$E10<>"",$A10>=PeriodStart,$A10<=PeriodEnd),$E10+ROW()/1000000,0),0) -> 0
H11: =N(H10)+IFERROR(IF(AND($A11<>"",$E11<>"",$A11>=IF(Search!$E$4="",0,Search!$E$4),$A11<=IF(Search!$E$5="",99999,Search!$E$5),OR(Search!$E$6="",ISNUMBER(SEARCH(Search!$E$6,$C11))),OR(Search!$E$7="All",Search!$E$7="",$D11=Search!$E$7),OR(Search!$E$8="",Search!$E$9="",AND($B11<>"",MOD($B11,1)>=Search!$E$8,MOD($B11,1)<=Search!$E$9))),1,0),0) -> 0 | I11: =IF(H11>N(H10),$E11,0) -> 0 | J11: =IFERROR(IF(AND($A11<>"",$E11<>"",$A11>=PeriodStart,$A11<=PeriodEnd),$E11+ROW()/1000000,0),0) -> 0
H12: =N(H11)+IFERROR(IF(AND($A12<>"",$E12<>"",$A12>=IF(Search!$E$4="",0,Search!$E$4),$A12<=IF(Search!$E$5="",99999,Search!$E$5),OR(Search!$E$6="",ISNUMBER(SEARCH(Search!$E$6,$C12))),OR(Search!$E$7="All",Search!$E$7="",$D12=Search!$E$7),OR(Search!$E$8="",Search!$E$9="",AND($B12<>"",MOD($B12,1)>=Search!$E$8,MOD($B12,1)<=Search!$E$9))),1,0),0) -> 0 | I12: =IF(H12>N(H11),$E12,0) -> 0 | J12: =IFERROR(IF(AND($A12<>"",$E12<>"",$A12>=PeriodStart,$A12<=PeriodEnd),$E12+ROW()/1000000,0),0) -> 0
H13: =N(H12)+IFERROR(IF(AND($A13<>"",$E13<>"",$A13>=IF(Search!$E$4="",0,Search!$E$4),$A13<=IF(Search!$E$5="",99999,Search!$E$5),OR(Search!$E$6="",ISNUMBER(SEARCH(Search!$E$6,$C13))),OR(Search!$E$7="All",Search!$E$7="",$D13=Search!$E$7),OR(Search!$E$8="",Search!$E$9="",AND($B13<>"",MOD($B13,1)>=Search!$E$8,MOD($B13,1)<=Search!$E$9))),1,0),0) -> 0 | I13: =IF(H13>N(H12),$E13,0) -> 0 | J13: =IFERROR(IF(AND($A13<>"",$E13<>"",$A13>=PeriodStart,$A13<=PeriodEnd),$E13+ROW()/1000000,0),0) -> 0
H14: =N(H13)+IFERROR(IF(AND($A14<>"",$E14<>"",$A14>=IF(Search!$E$4="",0,Search!$E$4),$A14<=IF(Search!$E$5="",99999,Search!$E$5),OR(Search!$E$6="",ISNUMBER(SEARCH(Search!$E$6,$C14))),OR(Search!$E$7="All",Search!$E$7="",$D14=Search!$E$7),OR(Search!$E$8="",Search!$E$9="",AND($B14<>"",MOD($B14,1)>=Search!$E$8,MOD($B14,1)<=Search!$E$9))),1,0),0) -> 0 | I14: =IF(H14>N(H13),$E14,0) -> 0 | J14: =IFERROR(IF(AND($A14<>"",$E14<>"",$A14>=PeriodStart,$A14<=PeriodEnd),$E14+ROW()/1000000,0),0) -> 0
H15: =N(H14)+IFERROR(IF(AND($A15<>"",$E15<>"",$A15>=IF(Search!$E$4="",0,Search!$E$4),$A15<=IF(Search!$E$5="",99999,Search!$E$5),OR(Search!$E$6="",ISNUMBER(SEARCH(Search!$E$6,$C15))),OR(Search!$E$7="All",Search!$E$7="",$D15=Search!$E$7),OR(Search!$E$8="",Search!$E$9="",AND($B15<>"",MOD($B15,1)>=Search!$E$8,MOD($B15,1)<=Search!$E$9))),1,0),0) -> 0 | I15: =IF(H15>N(H14),$E15,0) -> 0 | J15: =IFERROR(IF(AND($A15<>"",$E15<>"",$A15>=PeriodStart,$A15<=PeriodEnd),$E15+ROW()/1000000,0),0) -> 0
H16: =N(H15)+IFERROR(IF(AND($A16<>"",$E16<>"",$A16>=IF(Search!$E$4="",0,Search!$E$4),$A16<=IF(Search!$E$5="",99999,Search!$E$5),OR(Search!$E$6="",ISNUMBER(SEARCH(Search!$E$6,$C16))),OR(Search!$E$7="All",Search!$E$7="",$D16=Search!$E$7),OR(Search!$E$8="",Search!$E$9="",AND($B16<>"",MOD($B16,1)>=Search!$E$8,MOD($B16,1)<=Search!$E$9))),1,0),0) -> 0 | I16: =IF(H16>N(H15),$E16,0) -> 0 | J16: =IFERROR(IF(AND($A16<>"",$E16<>"",$A16>=PeriodStart,$A16<=PeriodEnd),$E16+ROW()/1000000,0),0) -> 0
... H1004: =N(H1003)+IFERROR(IF(AND($A1004<>"",$E1004<>"",$A1004>=IF(Search!$E$4="",0,Search!$E$4),$A1004<=IF(Search!$E$5="",99999,Search!$E$5),OR(Search!$E$6="",ISNUMBER(SEARCH(Search!$E$6,$C1004))),OR(Search!$E$7="All",Search!$E$7="",$D1004=Search!$E$7),OR(Search!$E$8="",Search!$E$9="",AND($B1004<>"",MOD($B1004,1)>=Search!$E$8,MOD($B1004,1)<=Search!$E$9))),1,0),0) -> 0 | I1004: =IF(H1004>N(H1003),$E1004,0) -> 0 | J1004: =IFERROR(IF(AND($A1004<>"",$E1004<>"",$A1004>=PeriodStart,$A1004<=PeriodEnd),$E1004+ROW()/1000000,0),0) -> 0

Sheet Income
A1: Income Sources & Receipts
A2: Record every payment you receive - salary, client payments, side income, gifts. Pick the source from the dropdown (edit the list on the Settings sheet).
A3: Entries: | B3: =COUNT(D5:D2004) -> 0 | C3: Total income recorded (all dates, KES): | D3: =SUM(D5:D2004) -> 0
A4: Date | B4: Income Source | C4: Description | D4: Amount (KES) | E4: Received Via | F4: Notes

Sheet Budget
A1: Budgets
A2: Set a budget ONCE and it repeats automatically every month. Choose Daily, Weekly or Monthly and type the amount. Need to change a budget later without altering past months? Put an 'Ends' date on the old line and add a new line with a 'Starts' date.
E3: All lines combined: | F3: =SUM(F5:F44) -> 0 | G3: =SUM(G5:G44) -> 0 | H3: =SUM(H5:H44) -> 0
A4: Category | B4: Budget Period | C4: Budget Amount (KES) | D4: Starts (optional) | E4: Ends (optional) | F4: Per Day | G4: Per Week | H4: Per Month (avg)
A5: =Settings!$B$6 -> Food & Groceries | B5: Monthly | F5: =IF(OR($C5="",$B5=""),"",IF($B5="Daily",$C5,IF($B5="Weekly",$C5/7,$C5*12/365))) | G5: =IF($F5="","",$F5*7) | H5: =IF($F5="","",$F5*365/12)
A6: =Settings!$B$7 -> Eating Out | B6: Monthly | F6: =IF(OR($C6="",$B6=""),"",IF($B6="Daily",$C6,IF($B6="Weekly",$C6/7,$C6*12/365))) | G6: =IF($F6="","",$F6*7) | H6: =IF($F6="","",$F6*365/12)
A7: =Settings!$B$8 -> Rent & Housing | B7: Monthly | F7: =IF(OR($C7="",$B7=""),"",IF($B7="Daily",$C7,IF($B7="Weekly",$C7/7,$C7*12/365))) | G7: =IF($F7="","",$F7*7) | H7: =IF($F7="","",$F7*365/12)
A8: =Settings!$B$9 -> Utilities | B8: Monthly | F8: =IF(OR($C8="",$B8=""),"",IF($B8="Daily",$C8,IF($B8="Weekly",$C8/7,$C8*12/365))) | G8: =IF($F8="","",$F8*7) | H8: =IF($F8="","",$F8*365/12)
A9: =Settings!$B$10 -> Transport & Fuel | B9: Monthly | F9: =IF(OR($C9="",$B9=""),"",IF($B9="Daily",$C9,IF($B9="Weekly",$C9/7,$C9*12/365))) | G9: =IF($F9="","",$F9*7) | H9: =IF($F9="","",$F9*365/12)
A10: =Settings!$B$11 -> Airtime & Data | B10: Monthly | F10: =IF(OR($C10="",$B10=""),"",IF($B10="Daily",$C10,IF($B10="Weekly",$C10/7,$C10*12/365))) | G10: =IF($F10="","",$F10*7) | H10: =IF($F10="","",$F10*365/12)
A11: =Settings!$B$12 -> Health & Medical | B11: Monthly | F11: =IF(OR($C11="",$B11=""),"",IF($B11="Daily",$C11,IF($B11="Weekly",$C11/7,$C11*12/365))) | G11: =IF($F11="","",$F11*7) | H11: =IF($F11="","",$F11*365/12)
A12: =Settings!$B$13 -> Education & School Fees | B12: Monthly | F12: =IF(OR($C12="",$B12=""),"",IF($B12="Daily",$C12,IF($B12="Weekly",$C12/7,$C12*12/365))) | G12: =IF($F12="","",$F12*7) | H12: =IF($F12="","",$F12*365/12)
A13: =Settings!$B$14 -> Business Expenses | B13: Monthly | F13: =IF(OR($C13="",$B13=""),"",IF($B13="Daily",$C13,IF($B13="Weekly",$C13/7,$C13*12/365))) | G13: =IF($F13="","",$F13*7) | H13: =IF($F13="","",$F13*365/12)
A14: =Settings!$B$15 -> Shopping & Clothing | B14: Monthly | F14: =IF(OR($C14="",$B14=""),"",IF($B14="Daily",$C14,IF($B14="Weekly",$C14/7,$C14*12/365))) | G14: =IF($F14="","",$F14*7) | H14: =IF($F14="","",$F14*365/12)
A15: =Settings!$B$16 -> Entertainment & Leisure | B15: Monthly | F15: =IF(OR($C15="",$B15=""),"",IF($B15="Daily",$C15,IF($B15="Weekly",$C15/7,$C15*12/365))) | G15: =IF($F15="","",$F15*7) | H15: =IF($F15="","",$F15*365/12)
A16: =Settings!$B$17 -> Personal Care | B16: Monthly | F16: =IF(OR($C16="",$B16=""),"",IF($B16="Daily",$C16,IF($B16="Weekly",$C16/7,$C16*12/365))) | G16: =IF($F16="","",$F16*7) | H16: =IF($F16="","",$F16*365/12)
A17: =Settings!$B$18 -> Family & Support | B17: Monthly | F17: =IF(OR($C17="",$B17=""),"",IF($B17="Daily",$C17,IF($B17="Weekly",$C17/7,$C17*12/365))) | G17: =IF($F17="","",$F17*7) | H17: =IF($F17="","",$F17*365/12)
A18: =Settings!$B$19 -> Giving & Church | B18: Monthly | F18: =IF(OR($C18="",$B18=""),"",IF($B18="Daily",$C18,IF($B18="Weekly",$C18/7,$C18*12/365))) | G18: =IF($F18="","",$F18*7) | H18: =IF($F18="","",$F18*365/12)
A19: =Settings!$B$20 -> Loans & Debt | B19: Monthly | F19: =IF(OR($C19="",$B19=""),"",IF($B19="Daily",$C19,IF($B19="Weekly",$C19/7,$C19*12/365))) | G19: =IF($F19="","",$F19*7) | H19: =IF($F19="","",$F19*365/12)
A20: =Settings!$B$21 -> Other | B20: Monthly | F20: =IF(OR($C20="",$B20=""),"",IF($B20="Daily",$C20,IF($B20="Weekly",$C20/7,$C20*12/365))) | G20: =IF($F20="","",$F20*7) | H20: =IF($F20="","",$F20*365/12)
F21: =IF(OR($C21="",$B21=""),"",IF($B21="Daily",$C21,IF($B21="Weekly",$C21/7,$C21*12/365))) | G21: =IF($F21="","",$F21*7) | H21: =IF($F21="","",$F21*365/12)
F22: =IF(OR($C22="",$B22=""),"",IF($B22="Daily",$C22,IF($B22="Weekly",$C22/7,$C22*12/365))) | G22: =IF($F22="","",$F22*7) | H22: =IF($F22="","",$F22*365/12)
F23: =IF(OR($C23="",$B23=""),"",IF($B23="Daily",$C23,IF($B23="Weekly",$C23/7,$C23*12/365))) | G23: =IF($F23="","",$F23*7) | H23: =IF($F23="","",$F23*365/12)
F24: =IF(OR($C24="",$B24=""),"",IF($B24="Daily",$C24,IF($B24="Weekly",$C24/7,$C24*12/365))) | G24: =IF($F24="","",$F24*7) | H24: =IF($F24="","",$F24*365/12)
F25: =IF(OR($C25="",$B25=""),"",IF($B25="Daily",$C25,IF($B25="Weekly",$C25/7,$C25*12/365))) | G25: =IF($F25="","",$F25*7) | H25: =IF($F25="","",$F25*365/12)
F26: =IF(OR($C26="",$B26=""),"",IF($B26="Daily",$C26,IF($B26="Weekly",$C26/7,$C26*12/365))) | G26: =IF($F26="","",$F26*7) | H26: =IF($F26="","",$F26*365/12)
F27: =IF(OR($C27="",$B27=""),"",IF($B27="Daily",$C27,IF($B27="Weekly",$C27/7,$C27*12/365))) | G27: =IF($F27="","",$F27*7) | H27: =IF($F27="","",$F27*365/12)
F28: =IF(OR($C28="",$B28=""),"",IF($B28="Daily",$C28,IF($B28="Weekly",$C28/7,$C28*12/365))) | G28: =IF($F28="","",$F28*7) | H28: =IF($F28="","",$F28*365/12)
F29: =IF(OR($C29="",$B29=""),"",IF($B29="Daily",$C29,IF($B29="Weekly",$C29/7,$C29*12/365))) | G29: =IF($F29="","",$F29*7) | H29: =IF($F29="","",$F29*365/12)
F30: =IF(OR($C30="",$B30=""),"",IF($B30="Daily",$C30,IF($B30="Weekly",$C30/7,$C30*12/365))) | G30: =IF($F30="","",$F30*7) | H30: =IF($F30="","",$F30*365/12)
F31: =IF(OR($C31="",$B31=""),"",IF($B31="Daily",$C31,IF($B31="Weekly",$C31/7,$C31*12/365))) | G31: =IF($F31="","",$F31*7) | H31: =IF($F31="","",$F31*365/12)
F32: =IF(OR($C32="",$B32=""),"",IF($B32="Daily",$C32,IF($B32="Weekly",$C32/7,$C32*12/365))) | G32: =IF($F32="","",$F32*7) | H32: =IF($F32="","",$F32*365/12)
... F44: =IF(OR($C44="",$B44=""),"",IF($B44="Daily",$C44,IF($B44="Weekly",$C44/7,$C44*12/365))) | G44: =IF($F44="","",$F44*7) | H44: =IF($F44="","",$F44*365/12)

Sheet Search
B1: Search Transactions
B2: Fill in any of the yellow boxes - leave the rest empty. Results appear below instantly.
C4: From date | F4: Leave empty for 'any date'
C5: To date | F5: Leave empty for 'any date'
C6: Product / item contains | F6: Type part of the name, e.g. 'naivas' or 'uber'
C7: Category | E7: All | F7: Pick a category or 'All'
C8: Time from | F8: Optional - e.g. 6:00 PM (use with 'Time to')
C9: Time to | F9: Optional - e.g. 11:30 PM
C11: Matches found | E11: =MAX(Transactions!$H$5:$H$5004) -> 0 | F11: =IF(E11>100,"Showing the first 100 matches - narrow your search to see the rest.",IF(E11=0,"No transactions match these filters.","Showing all matches.")) -> No transactions match these filters.
C12: Total amount (KES) | E12: =SUM(Transactions!$I$5:$I$5004) -> 0
B14: # | C14: Date | D14: Time | E14: Item / Product | F14: Category | G14: Amount (KES) | H14: Paid With | I14: Notes
B15: =IF($K15="","",1) | C15: =IF($K15="","",IF(INDEX(Transactions!$A$5:$A$5004,$K15)="","",INDEX(Transactions!$A$5:$A$5004,$K15))) | D15: =IF($K15="","",IF(INDEX(Transactions!$B$5:$B$5004,$K15)="","",INDEX(Transactions!$B$5:$B$5004,$K15))) | E15: =IF($K15="","",IF(INDEX(Transactions!$C$5:$C$5004,$K15)="","",INDEX(Transactions!$C$5:$C$5004,$K15))) | F15: =IF($K15="","",IF(INDEX(Transactions!$D$5:$D$5004,$K15)="","",INDEX(Transactions!$D$5:$D$5004,$K15))) | G15: =IF($K15="","",IF(INDEX(Transactions!$E$5:$E$5004,$K15)="","",INDEX(Transactions!$E$5:$E$5004,$K15))) | H15: =IF($K15="","",IF(INDEX(Transactions!$F$5:$F$5004,$K15)="","",INDEX(Transactions!$F$5:$F$5004,$K15))) | I15: =IF($K15="","",IF(INDEX(Transactions!$G$5:$G$5004,$K15)="","",INDEX(Transactions!$G$5:$G$5004,$K15))) | K15: =IFERROR(MATCH(1,Transactions!$H$5:$H$5004,0),"")
B16: =IF($K16="","",2) | C16: =IF($K16="","",IF(INDEX(Transactions!$A$5:$A$5004,$K16)="","",INDEX(Transactions!$A$5:$A$5004,$K16))) | D16: =IF($K16="","",IF(INDEX(Transactions!$B$5:$B$5004,$K16)="","",INDEX(Transactions!$B$5:$B$5004,$K16))) | E16: =IF($K16="","",IF(INDEX(Transactions!$C$5:$C$5004,$K16)="","",INDEX(Transactions!$C$5:$C$5004,$K16))) | F16: =IF($K16="","",IF(INDEX(Transactions!$D$5:$D$5004,$K16)="","",INDEX(Transactions!$D$5:$D$5004,$K16))) | G16: =IF($K16="","",IF(INDEX(Transactions!$E$5:$E$5004,$K16)="","",INDEX(Transactions!$E$5:$E$5004,$K16))) | H16: =IF($K16="","",IF(INDEX(Transactions!$F$5:$F$5004,$K16)="","",INDEX(Transactions!$F$5:$F$5004,$K16))) | I16: =IF($K16="","",IF(INDEX(Transactions!$G$5:$G$5004,$K16)="","",INDEX(Transactions!$G$5:$G$5004,$K16))) | K16: =IFERROR(MATCH(2,Transactions!$H$5:$H$5004,0),"")
B17: =IF($K17="","",3) | C17: =IF($K17="","",IF(INDEX(Transactions!$A$5:$A$5004,$K17)="","",INDEX(Transactions!$A$5:$A$5004,$K17))) | D17: =IF($K17="","",IF(INDEX(Transactions!$B$5:$B$5004,$K17)="","",INDEX(Transactions!$B$5:$B$5004,$K17))) | E17: =IF($K17="","",IF(INDEX(Transactions!$C$5:$C$5004,$K17)="","",INDEX(Transactions!$C$5:$C$5004,$K17))) | F17: =IF($K17="","",IF(INDEX(Transactions!$D$5:$D$5004,$K17)="","",INDEX(Transactions!$D$5:$D$5004,$K17))) | G17: =IF($K17="","",IF(INDEX(Transactions!$E$5:$E$5004,$K17)="","",INDEX(Transactions!$E$5:$E$5004,$K17))) | H17: =IF($K17="","",IF(INDEX(Transactions!$F$5:$F$5004,$K17)="","",INDEX(Transactions!$F$5:$F$5004,$K17))) | I17: =IF($K17="","",IF(INDEX(Transactions!$G$5:$G$5004,$K17)="","",INDEX(Transactions!$G$5:$G$5004,$K17))) | K17: =IFERROR(MATCH(3,Transactions!$H$5:$H$5004,0),"")
B18: =IF($K18="","",4) | C18: =IF($K18="","",IF(INDEX(Transactions!$A$5:$A$5004,$K18)="","",INDEX(Transactions!$A$5:$A$5004,$K18))) | D18: =IF($K18="","",IF(INDEX(Transactions!$B$5:$B$5004,$K18)="","",INDEX(Transactions!$B$5:$B$5004,$K18))) | E18: =IF($K18="","",IF(INDEX(Transactions!$C$5:$C$5004,$K18)="","",INDEX(Transactions!$C$5:$C$5004,$K18))) | F18: =IF($K18="","",IF(INDEX(Transactions!$D$5:$D$5004,$K18)="","",INDEX(Transactions!$D$5:$D$5004,$K18))) | G18: =IF($K18="","",IF(INDEX(Transactions!$E$5:$E$5004,$K18)="","",INDEX(Transactions!$E$5:$E$5004,$K18))) | H18: =IF($K18="","",IF(INDEX(Transactions!$F$5:$F$5004,$K18)="","",INDEX(Transactions!$F$5:$F$5004,$K18))) | I18: =IF($K18="","",IF(INDEX(Transactions!$G$5:$G$5004,$K18)="","",INDEX(Transactions!$G$5:$G$5004,$K18))) | K18: =IFERROR(MATCH(4,Transactions!$H$5:$H$5004,0),"")
B19: =IF($K19="","",5) | C19: =IF($K19="","",IF(INDEX(Transactions!$A$5:$A$5004,$K19)="","",INDEX(Transactions!$A$5:$A$5004,$K19))) | D19: =IF($K19="","",IF(INDEX(Transactions!$B$5:$B$5004,$K19)="","",INDEX(Transactions!$B$5:$B$5004,$K19))) | E19: =IF($K19="","",IF(INDEX(Transactions!$C$5:$C$5004,$K19)="","",INDEX(Transactions!$C$5:$C$5004,$K19))) | F19: =IF($K19="","",IF(INDEX(Transactions!$D$5:$D$5004,$K19)="","",INDEX(Transactions!$D$5:$D$5004,$K19))) | G19: =IF($K19="","",IF(INDEX(Transactions!$E$5:$E$5004,$K19)="","",INDEX(Transactions!$E$5:$E$5004,$K19))) | H19: =IF($K19="","",IF(INDEX(Transactions!$F$5:$F$5004,$K19)="","",INDEX(Transactions!$F$5:$F$5004,$K19))) | I19: =IF($K19="","",IF(INDEX(Transactions!$G$5:$G$5004,$K19)="","",INDEX(Transactions!$G$5:$G$5004,$K19))) | K19: =IFERROR(MATCH(5,Transactions!$H$5:$H$5004,0),"")
B20: =IF($K20="","",6) | C20: =IF($K20="","",IF(INDEX(Transactions!$A$5:$A$5004,$K20)="","",INDEX(Transactions!$A$5:$A$5004,$K20))) | D20: =IF($K20="","",IF(INDEX(Transactions!$B$5:$B$5004,$K20)="","",INDEX(Transactions!$B$5:$B$5004,$K20))) | E20: =IF($K20="","",IF(INDEX(Transactions!$C$5:$C$5004,$K20)="","",INDEX(Transactions!$C$5:$C$5004,$K20))) | F20: =IF($K20="","",IF(INDEX(Transactions!$D$5:$D$5004,$K20)="","",INDEX(Transactions!$D$5:$D$5004,$K20))) | G20: =IF($K20="","",IF(INDEX(Transactions!$E$5:$E$5004,$K20)="","",INDEX(Transactions!$E$5:$E$5004,$K20))) | H20: =IF($K20="","",IF(INDEX(Transactions!$F$5:$F$5004,$K20)="","",INDEX(Transactions!$F$5:$F$5004,$K20))) | I20: =IF($K20="","",IF(INDEX(Transactions!$G$5:$G$5004,$K20)="","",INDEX(Transactions!$G$5:$G$5004,$K20))) | K20: =IFERROR(MATCH(6,Transactions!$H$5:$H$5004,0),"")
B21: =IF($K21="","",7) | C21: =IF($K21="","",IF(INDEX(Transactions!$A$5:$A$5004,$K21)="","",INDEX(Transactions!$A$5:$A$5004,$K21))) | D21: =IF($K21="","",IF(INDEX(Transactions!$B$5:$B$5004,$K21)="","",INDEX(Transactions!$B$5:$B$5004,$K21))) | E21: =IF($K21="","",IF(INDEX(Transactions!$C$5:$C$5004,$K21)="","",INDEX(Transactions!$C$5:$C$5004,$K21))) | F21: =IF($K21="","",IF(INDEX(Transactions!$D$5:$D$5004,$K21)="","",INDEX(Transactions!$D$5:$D$5004,$K21))) | G21: =IF($K21="","",IF(INDEX(Transactions!$E$5:$E$5004,$K21)="","",INDEX(Transactions!$E$5:$E$5004,$K21))) | H21: =IF($K21="","",IF(INDEX(Transactions!$F$5:$F$5004,$K21)="","",INDEX(Transactions!$F$5:$F$5004,$K21))) | I21: =IF($K21="","",IF(INDEX(Transactions!$G$5:$G$5004,$K21)="","",INDEX(Transactions!$G$5:$G$5004,$K21))) | K21: =IFERROR(MATCH(7,Transactions!$H$5:$H$5004,0),"")
B22: =IF($K22="","",8) | C22: =IF($K22="","",IF(INDEX(Transactions!$A$5:$A$5004,$K22)="","",INDEX(Transactions!$A$5:$A$5004,$K22))) | D22: =IF($K22="","",IF(INDEX(Transactions!$B$5:$B$5004,$K22)="","",INDEX(Transactions!$B$5:$B$5004,$K22))) | E22: =IF($K22="","",IF(INDEX(Transactions!$C$5:$C$5004,$K22)="","",INDEX(Transactions!$C$5:$C$5004,$K22))) | F22: =IF($K22="","",IF(INDEX(Transactions!$D$5:$D$5004,$K22)="","",INDEX(Transactions!$D$5:$D$5004,$K22))) | G22: =IF($K22="","",IF(INDEX(Transactions!$E$5:$E$5004,$K22)="","",INDEX(Transactions!$E$5:$E$5004,$K22))) | H22: =IF($K22="","",IF(INDEX(Transactions!$F$5:$F$5004,$K22)="","",INDEX(Transactions!$F$5:$F$5004,$K22))) | I22: =IF($K22="","",IF(INDEX(Transactions!$G$5:$G$5004,$K22)="","",INDEX(Transactions!$G$5:$G$5004,$K22))) | K22: =IFERROR(MATCH(8,Transactions!$H$5:$H$5004,0),"")
B23: =IF($K23="","",9) | C23: =IF($K23="","",IF(INDEX(Transactions!$A$5:$A$5004,$K23)="","",INDEX(Transactions!$A$5:$A$5004,$K23))) | D23: =IF($K23="","",IF(INDEX(Transactions!$B$5:$B$5004,$K23)="","",INDEX(Transactions!$B$5:$B$5004,$K23))) | E23: =IF($K23="","",IF(INDEX(Transactions!$C$5:$C$5004,$K23)="","",INDEX(Transactions!$C$5:$C$5004,$K23))) | F23: =IF($K23="","",IF(INDEX(Transactions!$D$5:$D$5004,$K23)="","",INDEX(Transactions!$D$5:$D$5004,$K23))) | G23: =IF($K23="","",IF(INDEX(Transactions!$E$5:$E$5004,$K23)="","",INDEX(Transactions!$E$5:$E$5004,$K23))) | H23: =IF($K23="","",IF(INDEX(Transactions!$F$5:$F$5004,$K23)="","",INDEX(Transactions!$F$5:$F$5004,$K23))) | I23: =IF($K23="","",IF(INDEX(Transactions!$G$5:$G$5004,$K23)="","",INDEX(Transactions!$G$5:$G$5004,$K23))) | K23: =IFERROR(MATCH(9,Transactions!$H$5:$H$5004,0),"")
B24: =IF($K24="","",10) | C24: =IF($K24="","",IF(INDEX(Transactions!$A$5:$A$5004,$K24)="","",INDEX(Transactions!$A$5:$A$5004,$K24))) | D24: =IF($K24="","",IF(INDEX(Transactions!$B$5:$B$5004,$K24)="","",INDEX(Transactions!$B$5:$B$5004,$K24))) | E24: =IF($K24="","",IF(INDEX(Transactions!$C$5:$C$5004,$K24)="","",INDEX(Transactions!$C$5:$C$5004,$K24))) | F24: =IF($K24="","",IF(INDEX(Transactions!$D$5:$D$5004,$K24)="","",INDEX(Transactions!$D$5:$D$5004,$K24))) | G24: =IF($K24="","",IF(INDEX(Transactions!$E$5:$E$5004,$K24)="","",INDEX(Transactions!$E$5:$E$5004,$K24))) | H24: =IF($K24="","",IF(INDEX(Transactions!$F$5:$F$5004,$K24)="","",INDEX(Transactions!$F$5:$F$5004,$K24))) | I24: =IF($K24="","",IF(INDEX(Transactions!$G$5:$G$5004,$K24)="","",INDEX(Transactions!$G$5:$G$5004,$K24))) | K24: =IFERROR(MATCH(10,Transactions!$H$5:$H$5004,0),"")
B25: =IF($K25="","",11) | C25: =IF($K25="","",IF(INDEX(Transactions!$A$5:$A$5004,$K25)="","",INDEX(Transactions!$A$5:$A$5004,$K25))) | D25: =IF($K25="","",IF(INDEX(Transactions!$B$5:$B$5004,$K25)="","",INDEX(Transactions!$B$5:$B$5004,$K25))) | E25: =IF($K25="","",IF(INDEX(Transactions!$C$5:$C$5004,$K25)="","",INDEX(Transactions!$C$5:$C$5004,$K25))) | F25: =IF($K25="","",IF(INDEX(Transactions!$D$5:$D$5004,$K25)="","",INDEX(Transactions!$D$5:$D$5004,$K25))) | G25: =IF($K25="","",IF(INDEX(Transactions!$E$5:$E$5004,$K25)="","",INDEX(Transactions!$E$5:$E$5004,$K25))) | H25: =IF($K25="","",IF(INDEX(Transactions!$F$5:$F$5004,$K25)="","",INDEX(Transactions!$F$5:$F$5004,$K25))) | I25: =IF($K25="","",IF(INDEX(Transactions!$G$5:$G$5004,$K25)="","",INDEX(Transactions!$G$5:$G$5004,$K25))) | K25: =IFERROR(MATCH(11,Transactions!$H$5:$H$5004,0),"")
B26: =IF($K26="","",12) | C26: =IF($K26="","",IF(INDEX(Transactions!$A$5:$A$5004,$K26)="","",INDEX(Transactions!$A$5:$A$5004,$K26))) | D26: =IF($K26="","",IF(INDEX(Transactions!$B$5:$B$5004,$K26)="","",INDEX(Transactions!$B$5:$B$5004,$K26))) | E26: =IF($K26="","",IF(INDEX(Transactions!$C$5:$C$5004,$K26)="","",INDEX(Transactions!$C$5:$C$5004,$K26))) | F26: =IF($K26="","",IF(INDEX(Transactions!$D$5:$D$5004,$K26)="","",INDEX(Transactions!$D$5:$D$5004,$K26))) | G26: =IF($K26="","",IF(INDEX(Transactions!$E$5:$E$5004,$K26)="","",INDEX(Transactions!$E$5:$E$5004,$K26))) | H26: =IF($K26="","",IF(INDEX(Transactions!$F$5:$F$5004,$K26)="","",INDEX(Transactions!$F$5:$F$5004,$K26))) | I26: =IF($K26="","",IF(INDEX(Transactions!$G$5:$G$5004,$K26)="","",INDEX(Transactions!$G$5:$G$5004,$K26))) | K26: =IFERROR(MATCH(12,Transactions!$H$5:$H$5004,0),"")
B27: =IF($K27="","",13) | C27: =IF($K27="","",IF(INDEX(Transactions!$A$5:$A$5004,$K27)="","",INDEX(Transactions!$A$5:$A$5004,$K27))) | D27: =IF($K27="","",IF(INDEX(Transactions!$B$5:$B$5004,$K27)="","",INDEX(Transactions!$B$5:$B$5004,$K27))) | E27: =IF($K27="","",IF(INDEX(Transactions!$C$5:$C$5004,$K27)="","",INDEX(Transactions!$C$5:$C$5004,$K27))) | F27: =IF($K27="","",IF(INDEX(Transactions!$D$5:$D$5004,$K27)="","",INDEX(Transactions!$D$5:$D$5004,$K27))) | G27: =IF($K27="","",IF(INDEX(Transactions!$E$5:$E$5004,$K27)="","",INDEX(Transactions!$E$5:$E$5004,$K27))) | H27: =IF($K27="","",IF(INDEX(Transactions!$F$5:$F$5004,$K27)="","",INDEX(Transactions!$F$5:$F$5004,$K27))) | I27: =IF($K27="","",IF(INDEX(Transactions!$G$5:$G$5004,$K27)="","",INDEX(Transactions!$G$5:$G$5004,$K27))) | K27: =IFERROR(MATCH(13,Transactions!$H$5:$H$5004,0),"")
B28: =IF($K28="","",14) | C28: =IF($K28="","",IF(INDEX(Transactions!$A$5:$A$5004,$K28)="","",INDEX(Transactions!$A$5:$A$5004,$K28))) | D28: =IF($K28="","",IF(INDEX(Transactions!$B$5:$B$5004,$K28)="","",INDEX(Transactions!$B$5:$B$5004,$K28))) | E28: =IF($K28="","",IF(INDEX(Transactions!$C$5:$C$5004,$K28)="","",INDEX(Transactions!$C$5:$C$5004,$K28))) | F28: =IF($K28="","",IF(INDEX(Transactions!$D$5:$D$5004,$K28)="","",INDEX(Transactions!$D$5:$D$5004,$K28))) | G28: =IF($K28="","",IF(INDEX(Transactions!$E$5:$E$5004,$K28)="","",INDEX(Transactions!$E$5:$E$5004,$K28))) | H28: =IF($K28="","",IF(INDEX(Transactions!$F$5:$F$5004,$K28)="","",INDEX(Transactions!$F$5:$F$5004,$K28))) | I28: =IF($K28="","",IF(INDEX(Transactions!$G$5:$G$5004,$K28)="","",INDEX(Transactions!$G$5:$G$5004,$K28))) | K28: =IFERROR(MATCH(14,Transactions!$H$5:$H$5004,0),"")
B29: =IF($K29="","",15) | C29: =IF($K29="","",IF(INDEX(Transactions!$A$5:$A$5004,$K29)="","",INDEX(Transactions!$A$5:$A$5004,$K29))) | D29: =IF($K29="","",IF(INDEX(Transactions!$B$5:$B$5004,$K29)="","",INDEX(Transactions!$B$5:$B$5004,$K29))) | E29: =IF($K29="","",IF(INDEX(Transactions!$C$5:$C$5004,$K29)="","",INDEX(Transactions!$C$5:$C$5004,$K29))) | F29: =IF($K29="","",IF(INDEX(Transactions!$D$5:$D$5004,$K29)="","",INDEX(Transactions!$D$5:$D$5004,$K29))) | G29: =IF($K29="","",IF(INDEX(Transactions!$E$5:$E$5004,$K29)="","",INDEX(Transactions!$E$5:$E$5004,$K29))) | H29: =IF($K29="","",IF(INDEX(Transactions!$F$5:$F$5004,$K29)="","",INDEX(Transactions!$F$5:$F$5004,$K29))) | I29: =IF($K29="","",IF(INDEX(Transactions!$G$5:$G$5004,$K29)="","",INDEX(Transactions!$G$5:$G$5004,$K29))) | K29: =IFERROR(MATCH(15,Transactions!$H$5:$H$5004,0),"")
B30: =IF($K30="","",16) | C30: =IF($K30="","",IF(INDEX(Transactions!$A$5:$A$5004,$K30)="","",INDEX(Transactions!$A$5:$A$5004,$K30))) | D30: =IF($K30="","",IF(INDEX(Transactions!$B$5:$B$5004,$K30)="","",INDEX(Transactions!$B$5:$B$5004,$K30))) | E30: =IF($K30="","",IF(INDEX(Transactions!$C$5:$C$5004,$K30)="","",INDEX(Transactions!$C$5:$C$5004,$K30))) | F30: =IF($K30="","",IF(INDEX(Transactions!$D$5:$D$5004,$K30)="","",INDEX(Transactions!$D$5:$D$5004,$K30))) | G30: =IF($K30="","",IF(INDEX(Transactions!$E$5:$E$5004,$K30)="","",INDEX(Transactions!$E$5:$E$5004,$K30))) | H30: =IF($K30="","",IF(INDEX(Transactions!$F$5:$F$5004,$K30)="","",INDEX(Transactions!$F$5:$F$5004,$K30))) | I30: =IF($K30="","",IF(INDEX(Transactions!$G$5:$G$5004,$K30)="","",INDEX(Transactions!$G$5:$G$5004,$K30))) | K30: =IFERROR(MATCH(16,Transactions!$H$5:$H$5004,0),"")
B31: =IF($K31="","",17) | C31: =IF($K31="","",IF(INDEX(Transactions!$A$5:$A$5004,$K31)="","",INDEX(Transactions!$A$5:$A$5004,$K31))) | D31: =IF($K31="","",IF(INDEX(Transactions!$B$5:$B$5004,$K31)="","",INDEX(Transactions!$B$5:$B$5004,$K31))) | E31: =IF($K31="","",IF(INDEX(Transactions!$C$5:$C$5004,$K31)="","",INDEX(Transactions!$C$5:$C$5004,$K31))) | F31: =IF($K31="","",IF(INDEX(Transactions!$D$5:$D$5004,$K31)="","",INDEX(Transactions!$D$5:$D$5004,$K31))) | G31: =IF($K31="","",IF(INDEX(Transactions!$E$5:$E$5004,$K31)="","",INDEX(Transactions!$E$5:$E$5004,$K31))) | H31: =IF($K31="","",IF(INDEX(Transactions!$F$5:$F$5004,$K31)="","",INDEX(Transactions!$F$5:$F$5004,$K31))) | I31: =IF($K31="","",IF(INDEX(Transactions!$G$5:$G$5004,$K31)="","",INDEX(Transactions!$G$5:$G$5004,$K31))) | K31: =IFERROR(MATCH(17,Transactions!$H$5:$H$5004,0),"")
B32: =IF($K32="","",18) | C32: =IF($K32="","",IF(INDEX(Transactions!$A$5:$A$5004,$K32)="","",INDEX(Transactions!$A$5:$A$5004,$K32))) | D32: =IF($K32="","",IF(INDEX(Transactions!$B$5:$B$5004,$K32)="","",INDEX(Transactions!$B$5:$B$5004,$K32))) | E32: =IF($K32="","",IF(INDEX(Transactions!$C$5:$C$5004,$K32)="","",INDEX(Transactions!$C$5:$C$5004,$K32))) | F32: =IF($K32="","",IF(INDEX(Transactions!$D$5:$D$5004,$K32)="","",INDEX(Transactions!$D$5:$D$5004,$K32))) | G32: =IF($K32="","",IF(INDEX(Transactions!$E$5:$E$5004,$K32)="","",INDEX(Transactions!$E$5:$E$5004,$K32))) | H32: =IF($K32="","",IF(INDEX(Transactions!$F$5:$F$5004,$K32)="","",INDEX(Transactions!$F$5:$F$5004,$K32))) | I32: =IF($K32="","",IF(INDEX(Transactions!$G$5:$G$5004,$K32)="","",INDEX(Transactions!$G$5:$G$5004,$K32))) | K32: =IFERROR(MATCH(18,Transactions!$H$5:$H$5004,0),"")
B33: =IF($K33="","",19) | C33: =IF($K33="","",IF(INDEX(Transactions!$A$5:$A$5004,$K33)="","",INDEX(Transactions!$A$5:$A$5004,$K33))) | D33: =IF($K33="","",IF(INDEX(Transactions!$B$5:$B$5004,$K33)="","",INDEX(Transactions!$B$5:$B$5004,$K33))) | E33: =IF($K33="","",IF(INDEX(Transactions!$C$5:$C$5004,$K33)="","",INDEX(Transactions!$C$5:$C$5004,$K33))) | F33: =IF($K33="","",IF(INDEX(Transactions!$D$5:$D$5004,$K33)="","",INDEX(Transactions!$D$5:$D$5004,$K33))) | G33: =IF($K33="","",IF(INDEX(Transactions!$E$5:$E$5004,$K33)="","",INDEX(Transactions!$E$5:$E$5004,$K33))) | H33: =IF($K33="","",IF(INDEX(Transactions!$F$5:$F$5004,$K33)="","",INDEX(Transactions!$F$5:$F$5004,$K33))) | I33: =IF($K33="","",IF(INDEX(Transactions!$G$5:$G$5004,$K33)="","",INDEX(Transactions!$G$5:$G$5004,$K33))) | K33: =IFERROR(MATCH(19,Transactions!$H$5:$H$5004,0),"")
B34: =IF($K34="","",20) | C34: =IF($K34="","",IF(INDEX(Transactions!$A$5:$A$5004,$K34)="","",INDEX(Transactions!$A$5:$A$5004,$K34))) | D34: =IF($K34="","",IF(INDEX(Transactions!$B$5:$B$5004,$K34)="","",INDEX(Transactions!$B$5:$B$5004,$K34))) | E34: =IF($K34="","",IF(INDEX(Transactions!$C$5:$C$5004,$K34)="","",INDEX(Transactions!$C$5:$C$5004,$K34))) | F34: =IF($K34="","",IF(INDEX(Transactions!$D$5:$D$5004,$K34)="","",INDEX(Transactions!$D$5:$D$5004,$K34))) | G34: =IF($K34="","",IF(INDEX(Transactions!$E$5:$E$5004,$K34)="","",INDEX(Transactions!$E$5:$E$5004,$K34))) | H34: =IF($K34="","",IF(INDEX(Transactions!$F$5:$F$5004,$K34)="","",INDEX(Transactions!$F$5:$F$5004,$K34))) | I34: =IF($K34="","",IF(INDEX(Transactions!$G$5:$G$5004,$K34)="","",INDEX(Transactions!$G$5:$G$5004,$K34))) | K34: =IFERROR(MATCH(20,Transactions!$H$5:$H$5004,0),"")
B35: =IF($K35="","",21) | C35: =IF($K35="","",IF(INDEX(Transactions!$A$5:$A$5004,$K35)="","",INDEX(Transactions!$A$5:$A$5004,$K35))) | D35: =IF($K35="","",IF(INDEX(Transactions!$B$5:$B$5004,$K35)="","",INDEX(Transactions!$B$5:$B$5004,$K35))) | E35: =IF($K35="","",IF(INDEX(Transactions!$C$5:$C$5004,$K35)="","",INDEX(Transactions!$C$5:$C$5004,$K35))) | F35: =IF($K35="","",IF(INDEX(Transactions!$D$5:$D$5004,$K35)="","",INDEX(Transactions!$D$5:$D$5004,$K35))) | G35: =IF($K35="","",IF(INDEX(Transactions!$E$5:$E$5004,$K35)="","",INDEX(Transactions!$E$5:$E$5004,$K35))) | H35: =IF($K35="","",IF(INDEX(Transactions!$F$5:$F$5004,$K35)="","",INDEX(Transactions!$F$5:$F$5004,$K35))) | I35: =IF($K35="","",IF(INDEX(Transactions!$G$5:$G$5004,$K35)="","",INDEX(Transactions!$G$5:$G$5004,$K35))) | K35: =IFERROR(MATCH(21,Transactions!$H$5:$H$5004,0),"")
B36: =IF($K36="","",22) | C36: =IF($K36="","",IF(INDEX(Transactions!$A$5:$A$5004,$K36)="","",INDEX(Transactions!$A$5:$A$5004,$K36))) | D36: =IF($K36="","",IF(INDEX(Transactions!$B$5:$B$5004,$K36)="","",INDEX(Transactions!$B$5:$B$5004,$K36))) | E36: =IF($K36="","",IF(INDEX(Transactions!$C$5:$C$5004,$K36)="","",INDEX(Transactions!$C$5:$C$5004,$K36))) | F36: =IF($K36="","",IF(INDEX(Transactions!$D$5:$D$5004,$K36)="","",INDEX(Transactions!$D$5:$D$5004,$K36))) | G36: =IF($K36="","",IF(INDEX(Transactions!$E$5:$E$5004,$K36)="","",INDEX(Transactions!$E$5:$E$5004,$K36))) | H36: =IF($K36="","",IF(INDEX(Transactions!$F$5:$F$5004,$K36)="","",INDEX(Transactions!$F$5:$F$5004,$K36))) | I36: =IF($K36="","",IF(INDEX(Transactions!$G$5:$G$5004,$K36)="","",INDEX(Transactions!$G$5:$G$5004,$K36))) | K36: =IFERROR(MATCH(22,Transactions!$H$5:$H$5004,0),"")
B37: =IF($K37="","",23) | C37: =IF($K37="","",IF(INDEX(Transactions!$A$5:$A$5004,$K37)="","",INDEX(Transactions!$A$5:$A$5004,$K37))) | D37: =IF($K37="","",IF(INDEX(Transactions!$B$5:$B$5004,$K37)="","",INDEX(Transactions!$B$5:$B$5004,$K37))) | E37: =IF($K37="","",IF(INDEX(Transactions!$C$5:$C$5004,$K37)="","",INDEX(Transactions!$C$5:$C$5004,$K37))) | F37: =IF($K37="","",IF(INDEX(Transactions!$D$5:$D$5004,$K37)="","",INDEX(Transactions!$D$5:$D$5004,$K37))) | G37: =IF($K37="","",IF(INDEX(Transactions!$E$5:$E$5004,$K37)="","",INDEX(Transactions!$E$5:$E$5004,$K37))) | H37: =IF($K37="","",IF(INDEX(Transactions!$F$5:$F$5004,$K37)="","",INDEX(Transactions!$F$5:$F$5004,$K37))) | I37: =IF($K37="","",IF(INDEX(Transactions!$G$5:$G$5004,$K37)="","",INDEX(Transactions!$G$5:$G$5004,$K37))) | K37: =IFERROR(MATCH(23,Transactions!$H$5:$H$5004,0),"")
B38: =IF($K38="","",24) | C38: =IF($K38="","",IF(INDEX(Transactions!$A$5:$A$5004,$K38)="","",INDEX(Transactions!$A$5:$A$5004,$K38))) | D38: =IF($K38="","",IF(INDEX(Transactions!$B$5:$B$5004,$K38)="","",INDEX(Transactions!$B$5:$B$5004,$K38))) | E38: =IF($K38="","",IF(INDEX(Transactions!$C$5:$C$5004,$K38)="","",INDEX(Transactions!$C$5:$C$5004,$K38))) | F38: =IF($K38="","",IF(INDEX(Transactions!$D$5:$D$5004,$K38)="","",INDEX(Transactions!$D$5:$D$5004,$K38))) | G38: =IF($K38="","",IF(INDEX(Transactions!$E$5:$E$5004,$K38)="","",INDEX(Transactions!$E$5:$E$5004,$K38))) | H38: =IF($K38="","",IF(INDEX(Transactions!$F$5:$F$5004,$K38)="","",INDEX(Transactions!$F$5:$F$5004,$K38))) | I38: =IF($K38="","",IF(INDEX(Transactions!$G$5:$G$5004,$K38)="","",INDEX(Transactions!$G$5:$G$5004,$K38))) | K38: =IFERROR(MATCH(24,Transactions!$H$5:$H$5004,0),"")
B39: =IF($K39="","",25) | C39: =IF($K39="","",IF(INDEX(Transactions!$A$5:$A$5004,$K39)="","",INDEX(Transactions!$A$5:$A$5004,$K39))) | D39: =IF($K39="","",IF(INDEX(Transactions!$B$5:$B$5004,$K39)="","",INDEX(Transactions!$B$5:$B$5004,$K39))) | E39: =IF($K39="","",IF(INDEX(Transactions!$C$5:$C$5004,$K39)="","",INDEX(Transactions!$C$5:$C$5004,$K39))) | F39: =IF($K39="","",IF(INDEX(Transactions!$D$5:$D$5004,$K39)="","",INDEX(Transactions!$D$5:$D$5004,$K39))) | G39: =IF($K39="","",IF(INDEX(Transactions!$E$5:$E$5004,$K39)="","",INDEX(Transactions!$E$5:$E$5004,$K39))) | H39: =IF($K39="","",IF(INDEX(Transactions!$F$5:$F$5004,$K39)="","",INDEX(Transactions!$F$5:$F$5004,$K39))) | I39: =IF($K39="","",IF(INDEX(Transactions!$G$5:$G$5004,$K39)="","",INDEX(Transactions!$G$5:$G$5004,$K39))) | K39: =IFERROR(MATCH(25,Transactions!$H$5:$H$5004,0),"")
B40: =IF($K40="","",26) | C40: =IF($K40="","",IF(INDEX(Transactions!$A$5:$A$5004,$K40)="","",INDEX(Transactions!$A$5:$A$5004,$K40))) | D40: =IF($K40="","",IF(INDEX(Transactions!$B$5:$B$5004,$K40)="","",INDEX(Transactions!$B$5:$B$5004,$K40))) | E40: =IF($K40="","",IF(INDEX(Transactions!$C$5:$C$5004,$K40)="","",INDEX(Transactions!$C$5:$C$5004,$K40))) | F40: =IF($K40="","",IF(INDEX(Transactions!$D$5:$D$5004,$K40)="","",INDEX(Transactions!$D$5:$D$5004,$K40))) | G40: =IF($K40="","",IF(INDEX(Transactions!$E$5:$E$5004,$K40)="","",INDEX(Transactions!$E$5:$E$5004,$K40))) | H40: =IF($K40="","",IF(INDEX(Transactions!$F$5:$F$5004,$K40)="","",INDEX(Transactions!$F$5:$F$5004,$K40))) | I40: =IF($K40="","",IF(INDEX(Transactions!$G$5:$G$5004,$K40)="","",INDEX(Transactions!$G$5:$G$5004,$K40))) | K40: =IFERROR(MATCH(26,Transactions!$H$5:$H$5004,0),"")
B41: =IF($K41="","",27) | C41: =IF($K41="","",IF(INDEX(Transactions!$A$5:$A$5004,$K41)="","",INDEX(Transactions!$A$5:$A$5004,$K41))) | D41: =IF($K41="","",IF(INDEX(Transactions!$B$5:$B$5004,$K41)="","",INDEX(Transactions!$B$5:$B$5004,$K41))) | E41: =IF($K41="","",IF(INDEX(Transactions!$C$5:$C$5004,$K41)="","",INDEX(Transactions!$C$5:$C$5004,$K41))) | F41: =IF($K41="","",IF(INDEX(Transactions!$D$5:$D$5004,$K41)="","",INDEX(Transactions!$D$5:$D$5004,$K41))) | G41: =IF($K41="","",IF(INDEX(Transactions!$E$5:$E$5004,$K41)="","",INDEX(Transactions!$E$5:$E$5004,$K41))) | H41: =IF($K41="","",IF(INDEX(Transactions!$F$5:$F$5004,$K41)="","",INDEX(Transactions!$F$5:$F$5004,$K41))) | I41: =IF($K41="","",IF(INDEX(Transactions!$G$5:$G$5004,$K41)="","",INDEX(Transactions!$G$5:$G$5004,$K41))) | K41: =IFERROR(MATCH(27,Transactions!$H$5:$H$5004,0),"")
B42: =IF($K42="","",28) | C42: =IF($K42="","",IF(INDEX(Transactions!$A$5:$A$5004,$K42)="","",INDEX(Transactions!$A$5:$A$5004,$K42))) | D42: =IF($K42="","",IF(INDEX(Transactions!$B$5:$B$5004,$K42)="","",INDEX(Transactions!$B$5:$B$5004,$K42))) | E42: =IF($K42="","",IF(INDEX(Transactions!$C$5:$C$5004,$K42)="","",INDEX(Transactions!$C$5:$C$5004,$K42))) | F42: =IF($K42="","",IF(INDEX(Transactions!$D$5:$D$5004,$K42)="","",INDEX(Transactions!$D$5:$D$5004,$K42))) | G42: =IF($K42="","",IF(INDEX(Transactions!$E$5:$E$5004,$K42)="","",INDEX(Transactions!$E$5:$E$5004,$K42))) | H42: =IF($K42="","",IF(INDEX(Transactions!$F$5:$F$5004,$K42)="","",INDEX(Transactions!$F$5:$F$5004,$K42))) | I42: =IF($K42="","",IF(INDEX(Transactions!$G$5:$G$5004,$K42)="","",INDEX(Transactions!$G$5:$G$5004,$K42))) | K42: =IFERROR(MATCH(28,Transactions!$H$5:$H$5004,0),"")
B43: =IF($K43="","",29) | C43: =IF($K43="","",IF(INDEX(Transactions!$A$5:$A$5004,$K43)="","",INDEX(Transactions!$A$5:$A$5004,$K43))) | D43: =IF($K43="","",IF(INDEX(Transactions!$B$5:$B$5004,$K43)="","",INDEX(Transactions!$B$5:$B$5004,$K43))) | E43: =IF($K43="","",IF(INDEX(Transactions!$C$5:$C$5004,$K43)="","",INDEX(Transactions!$C$5:$C$5004,$K43))) | F43: =IF($K43="","",IF(INDEX(Transactions!$D$5:$D$5004,$K43)="","",INDEX(Transactions!$D$5:$D$5004,$K43))) | G43: =IF($K43="","",IF(INDEX(Transactions!$E$5:$E$5004,$K43)="","",INDEX(Transactions!$E$5:$E$5004,$K43))) | H43: =IF($K43="","",IF(INDEX(Transactions!$F$5:$F$5004,$K43)="","",INDEX(Transactions!$F$5:$F$5004,$K43))) | I43: =IF($K43="","",IF(INDEX(Transactions!$G$5:$G$5004,$K43)="","",INDEX(Transactions!$G$5:$G$5004,$K43))) | K43: =IFERROR(MATCH(29,Transactions!$H$5:$H$5004,0),"")
B44: =IF($K44="","",30) | C44: =IF($K44="","",IF(INDEX(Transactions!$A$5:$A$5004,$K44)="","",INDEX(Transactions!$A$5:$A$5004,$K44))) | D44: =IF($K44="","",IF(INDEX(Transactions!$B$5:$B$5004,$K44)="","",INDEX(Transactions!$B$5:$B$5004,$K44))) | E44: =IF($K44="","",IF(INDEX(Transactions!$C$5:$C$5004,$K44)="","",INDEX(Transactions!$C$5:$C$5004,$K44))) | F44: =IF($K44="","",IF(INDEX(Transactions!$D$5:$D$5004,$K44)="","",INDEX(Transactions!$D$5:$D$5004,$K44))) | G44: =IF($K44="","",IF(INDEX(Transactions!$E$5:$E$5004,$K44)="","",INDEX(Transactions!$E$5:$E$5004,$K44))) | H44: =IF($K44="","",IF(INDEX(Transactions!$F$5:$F$5004,$K44)="","",INDEX(Transactions!$F$5:$F$5004,$K44))) | I44: =IF($K44="","",IF(INDEX(Transactions!$G$5:$G$5004,$K44)="","",INDEX(Transactions!$G$5:$G$5004,$K44))) | K44: =IFERROR(MATCH(30,Transactions!$H$5:$H$5004,0),"")
B45: =IF($K45="","",31) | C45: =IF($K45="","",IF(INDEX(Transactions!$A$5:$A$5004,$K45)="","",INDEX(Transactions!$A$5:$A$5004,$K45))) | D45: =IF($K45="","",IF(INDEX(Transactions!$B$5:$B$5004,$K45)="","",INDEX(Transactions!$B$5:$B$5004,$K45))) | E45: =IF($K45="","",IF(INDEX(Transactions!$C$5:$C$5004,$K45)="","",INDEX(Transactions!$C$5:$C$5004,$K45))) | F45: =IF($K45="","",IF(INDEX(Transactions!$D$5:$D$5004,$K45)="","",INDEX(Transactions!$D$5:$D$5004,$K45))) | G45: =IF($K45="","",IF(INDEX(Transactions!$E$5:$E$5004,$K45)="","",INDEX(Transactions!$E$5:$E$5004,$K45))) | H45: =IF($K45="","",IF(INDEX(Transactions!$F$5:$F$5004,$K45)="","",INDEX(Transactions!$F$5:$F$5004,$K45))) | I45: =IF($K45="","",IF(INDEX(Transactions!$G$5:$G$5004,$K45)="","",INDEX(Transactions!$G$5:$G$5004,$K45))) | K45: =IFERROR(MATCH(31,Transactions!$H$5:$H$5004,0),"")
B46: =IF($K46="","",32) | C46: =IF($K46="","",IF(INDEX(Transactions!$A$5:$A$5004,$K46)="","",INDEX(Transactions!$A$5:$A$5004,$K46))) | D46: =IF($K46="","",IF(INDEX(Transactions!$B$5:$B$5004,$K46)="","",INDEX(Transactions!$B$5:$B$5004,$K46))) | E46: =IF($K46="","",IF(INDEX(Transactions!$C$5:$C$5004,$K46)="","",INDEX(Transactions!$C$5:$C$5004,$K46))) | F46: =IF($K46="","",IF(INDEX(Transactions!$D$5:$D$5004,$K46)="","",INDEX(Transactions!$D$5:$D$5004,$K46))) | G46: =IF($K46="","",IF(INDEX(Transactions!$E$5:$E$5004,$K46)="","",INDEX(Transactions!$E$5:$E$5004,$K46))) | H46: =IF($K46="","",IF(INDEX(Transactions!$F$5:$F$5004,$K46)="","",INDEX(Transactions!$F$5:$F$5004,$K46))) | I46: =IF($K46="","",IF(INDEX(Transactions!$G$5:$G$5004,$K46)="","",INDEX(Transactions!$G$5:$G$5004,$K46))) | K46: =IFERROR(MATCH(32,Transactions!$H$5:$H$5004,0),"")
B47: =IF($K47="","",33) | C47: =IF($K47="","",IF(INDEX(Transactions!$A$5:$A$5004,$K47)="","",INDEX(Transactions!$A$5:$A$5004,$K47))) | D47: =IF($K47="","",IF(INDEX(Transactions!$B$5:$B$5004,$K47)="","",INDEX(Transactions!$B$5:$B$5004,$K47))) | E47: =IF($K47="","",IF(INDEX(Transactions!$C$5:$C$5004,$K47)="","",INDEX(Transactions!$C$5:$C$5004,$K47))) | F47: =IF($K47="","",IF(INDEX(Transactions!$D$5:$D$5004,$K47)="","",INDEX(Transactions!$D$5:$D$5004,$K47))) | G47: =IF($K47="","",IF(INDEX(Transactions!$E$5:$E$5004,$K47)="","",INDEX(Transactions!$E$5:$E$5004,$K47))) | H47: =IF($K47="","",IF(INDEX(Transactions!$F$5:$F$5004,$K47)="","",INDEX(Transactions!$F$5:$F$5004,$K47))) | I47: =IF($K47="","",IF(INDEX(Transactions!$G$5:$G$5004,$K47)="","",INDEX(Transactions!$G$5:$G$5004,$K47))) | K47: =IFERROR(MATCH(33,Transactions!$H$5:$H$5004,0),"")
B48: =IF($K48="","",34) | C48: =IF($K48="","",IF(INDEX(Transactions!$A$5:$A$5004,$K48)="","",INDEX(Transactions!$A$5:$A$5004,$K48))) | D48: =IF($K48="","",IF(INDEX(Transactions!$B$5:$B$5004,$K48)="","",INDEX(Transactions!$B$5:$B$5004,$K48))) | E48: =IF($K48="","",IF(INDEX(Transactions!$C$5:$C$5004,$K48)="","",INDEX(Transactions!$C$5:$C$5004,$K48))) | F48: =IF($K48="","",IF(INDEX(Transactions!$D$5:$D$5004,$K48)="","",INDEX(Transactions!$D$5:$D$5004,$K48))) | G48: =IF($K48="","",IF(INDEX(Transactions!$E$5:$E$5004,$K48)="","",INDEX(Transactions!$E$5:$E$5004,$K48))) | H48: =IF($K48="","",IF(INDEX(Transactions!$F$5:$F$5004,$K48)="","",INDEX(Transactions!$F$5:$F$5004,$K48))) | I48: =IF($K48="","",IF(INDEX(Transactions!$G$5:$G$5004,$K48)="","",INDEX(Transactions!$G$5:$G$5004,$K48))) | K48: =IFERROR(MATCH(34,Transactions!$H$5:$H$5004,0),"")
B49: =IF($K49="","",35) | C49: =IF($K49="","",IF(INDEX(Transactions!$A$5:$A$5004,$K49)="","",INDEX(Transactions!$A$5:$A$5004,$K49))) | D49: =IF($K49="","",IF(INDEX(Transactions!$B$5:$B$5004,$K49)="","",INDEX(Transactions!$B$5:$B$5004,$K49))) | E49: =IF($K49="","",IF(INDEX(Transactions!$C$5:$C$5004,$K49)="","",INDEX(Transactions!$C$5:$C$5004,$K49))) | F49: =IF($K49="","",IF(INDEX(Transactions!$D$5:$D$5004,$K49)="","",INDEX(Transactions!$D$5:$D$5004,$K49))) | G49: =IF($K49="","",IF(INDEX(Transactions!$E$5:$E$5004,$K49)="","",INDEX(Transactions!$E$5:$E$5004,$K49))) | H49: =IF($K49="","",IF(INDEX(Transactions!$F$5:$F$5004,$K49)="","",INDEX(Transactions!$F$5:$F$5004,$K49))) | I49: =IF($K49="","",IF(INDEX(Transactions!$G$5:$G$5004,$K49)="","",INDEX(Transactions!$G$5:$G$5004,$K49))) | K49: =IFERROR(MATCH(35,Transactions!$H$5:$H$5004,0),"")
B50: =IF($K50="","",36) | C50: =IF($K50="","",IF(INDEX(Transactions!$A$5:$A$5004,$K50)="","",INDEX(Transactions!$A$5:$A$5004,$K50))) | D50: =IF($K50="","",IF(INDEX(Transactions!$B$5:$B$5004,$K50)="","",INDEX(Transactions!$B$5:$B$5004,$K50))) | E50: =IF($K50="","",IF(INDEX(Transactions!$C$5:$C$5004,$K50)="","",INDEX(Transactions!$C$5:$C$5004,$K50))) | F50: =IF($K50="","",IF(INDEX(Transactions!$D$5:$D$5004,$K50)="","",INDEX(Transactions!$D$5:$D$5004,$K50))) | G50: =IF($K50="","",IF(INDEX(Transactions!$E$5:$E$5004,$K50)="","",INDEX(Transactions!$E$5:$E$5004,$K50))) | H50: =IF($K50="","",IF(INDEX(Transactions!$F$5:$F$5004,$K50)="","",INDEX(Transactions!$F$5:$F$5004,$K50))) | I50: =IF($K50="","",IF(INDEX(Transactions!$G$5:$G$5004,$K50)="","",INDEX(Transactions!$G$5:$G$5004,$K50))) | K50: =IFERROR(MATCH(36,Transactions!$H$5:$H$5004,0),"")
B51: =IF($K51="","",37) | C51: =IF($K51="","",IF(INDEX(Transactions!$A$5:$A$5004,$K51)="","",INDEX(Transactions!$A$5:$A$5004,$K51))) | D51: =IF($K51="","",IF(INDEX(Transactions!$B$5:$B$5004,$K51)="","",INDEX(Transactions!$B$5:$B$5004,$K51))) | E51: =IF($K51="","",IF(INDEX(Transactions!$C$5:$C$5004,$K51)="","",INDEX(Transactions!$C$5:$C$5004,$K51))) | F51: =IF($K51="","",IF(INDEX(Transactions!$D$5:$D$5004,$K51)="","",INDEX(Transactions!$D$5:$D$5004,$K51))) | G51: =IF($K51="","",IF(INDEX(Transactions!$E$5:$E$5004,$K51)="","",INDEX(Transactions!$E$5:$E$5004,$K51))) | H51: =IF($K51="","",IF(INDEX(Transactions!$F$5:$F$5004,$K51)="","",INDEX(Transactions!$F$5:$F$5004,$K51))) | I51: =IF($K51="","",IF(INDEX(Transactions!$G$5:$G$5004,$K51)="","",INDEX(Transactions!$G$5:$G$5004,$K51))) | K51: =IFERROR(MATCH(37,Transactions!$H$5:$H$5004,0),"")
B52: =IF($K52="","",38) | C52: =IF($K52="","",IF(INDEX(Transactions!$A$5:$A$5004,$K52)="","",INDEX(Transactions!$A$5:$A$5004,$K52))) | D52: =IF($K52="","",IF(INDEX(Transactions!$B$5:$B$5004,$K52)="","",INDEX(Transactions!$B$5:$B$5004,$K52))) | E52: =IF($K52="","",IF(INDEX(Transactions!$C$5:$C$5004,$K52)="","",INDEX(Transactions!$C$5:$C$5004,$K52))) | F52: =IF($K52="","",IF(INDEX(Transactions!$D$5:$D$5004,$K52)="","",INDEX(Transactions!$D$5:$D$5004,$K52))) | G52: =IF($K52="","",IF(INDEX(Transactions!$E$5:$E$5004,$K52)="","",INDEX(Transactions!$E$5:$E$5004,$K52))) | H52: =IF($K52="","",IF(INDEX(Transactions!$F$5:$F$5004,$K52)="","",INDEX(Transactions!$F$5:$F$5004,$K52))) | I52: =IF($K52="","",IF(INDEX(Transactions!$G$5:$G$5004,$K52)="","",INDEX(Transactions!$G$5:$G$5004,$K52))) | K52: =IFERROR(MATCH(38,Transactions!$H$5:$H$5004,0),"")
B53: =IF($K53="","",39) | C53: =IF($K53="","",IF(INDEX(Transactions!$A$5:$A$5004,$K53)="","",INDEX(Transactions!$A$5:$A$5004,$K53))) | D53: =IF($K53="","",IF(INDEX(Transactions!$B$5:$B$5004,$K53)="","",INDEX(Transactions!$B$5:$B$5004,$K53))) | E53: =IF($K53="","",IF(INDEX(Transactions!$C$5:$C$5004,$K53)="","",INDEX(Transactions!$C$5:$C$5004,$K53))) | F53: =IF($K53="","",IF(INDEX(Transactions!$D$5:$D$5004,$K53)="","",INDEX(Transactions!$D$5:$D$5004,$K53))) | G53: =IF($K53="","",IF(INDEX(Transactions!$E$5:$E$5004,$K53)="","",INDEX(Transactions!$E$5:$E$5004,$K53))) | H53: =IF($K53="","",IF(INDEX(Transactions!$F$5:$F$5004,$K53)="","",INDEX(Transactions!$F$5:$F$5004,$K53))) | I53: =IF($K53="","",IF(INDEX(Transactions!$G$5:$G$5004,$K53)="","",INDEX(Transactions!$G$5:$G$5004,$K53))) | K53: =IFERROR(MATCH(39,Transactions!$H$5:$H$5004,0),"")
B54: =IF($K54="","",40) | C54: =IF($K54="","",IF(INDEX(Transactions!$A$5:$A$5004,$K54)="","",INDEX(Transactions!$A$5:$A$5004,$K54))) | D54: =IF($K54="","",IF(INDEX(Transactions!$B$5:$B$5004,$K54)="","",INDEX(Transactions!$B$5:$B$5004,$K54))) | E54: =IF($K54="","",IF(INDEX(Transactions!$C$5:$C$5004,$K54)="","",INDEX(Transactions!$C$5:$C$5004,$K54))) | F54: =IF($K54="","",IF(INDEX(Transactions!$D$5:$D$5004,$K54)="","",INDEX(Transactions!$D$5:$D$5004,$K54))) | G54: =IF($K54="","",IF(INDEX(Transactions!$E$5:$E$5004,$K54)="","",INDEX(Transactions!$E$5:$E$5004,$K54))) | H54: =IF($K54="","",IF(INDEX(Transactions!$F$5:$F$5004,$K54)="","",INDEX(Transactions!$F$5:$F$5004,$K54))) | I54: =IF($K54="","",IF(INDEX(Transactions!$G$5:$G$5004,$K54)="","",INDEX(Transactions!$G$5:$G$5004,$K54))) | K54: =IFERROR(MATCH(40,Transactions!$H$5:$H$5004,0),"")
B55: =IF($K55="","",41) | C55: =IF($K55="","",IF(INDEX(Transactions!$A$5:$A$5004,$K55)="","",INDEX(Transactions!$A$5:$A$5004,$K55))) | D55: =IF($K55="","",IF(INDEX(Transactions!$B$5:$B$5004,$K55)="","",INDEX(Transactions!$B$5:$B$5004,$K55))) | E55: =IF($K55="","",IF(INDEX(Transactions!$C$5:$C$5004,$K55)="","",INDEX(Transactions!$C$5:$C$5004,$K55))) | F55: =IF($K55="","",IF(INDEX(Transactions!$D$5:$D$5004,$K55)="","",INDEX(Transactions!$D$5:$D$5004,$K55))) | G55: =IF($K55="","",IF(INDEX(Transactions!$E$5:$E$5004,$K55)="","",INDEX(Transactions!$E$5:$E$5004,$K55))) | H55: =IF($K55="","",IF(INDEX(Transactions!$F$5:$F$5004,$K55)="","",INDEX(Transactions!$F$5:$F$5004,$K55))) | I55: =IF($K55="","",IF(INDEX(Transactions!$G$5:$G$5004,$K55)="","",INDEX(Transactions!$G$5:$G$5004,$K55))) | K55: =IFERROR(MATCH(41,Transactions!$H$5:$H$5004,0),"")
B56: =IF($K56="","",42) | C56: =IF($K56="","",IF(INDEX(Transactions!$A$5:$A$5004,$K56)="","",INDEX(Transactions!$A$5:$A$5004,$K56))) | D56: =IF($K56="","",IF(INDEX(Transactions!$B$5:$B$5004,$K56)="","",INDEX(Transactions!$B$5:$B$5004,$K56))) | E56: =IF($K56="","",IF(INDEX(Transactions!$C$5:$C$5004,$K56)="","",INDEX(Transactions!$C$5:$C$5004,$K56))) | F56: =IF($K56="","",IF(INDEX(Transactions!$D$5:$D$5004,$K56)="","",INDEX(Transactions!$D$5:$D$5004,$K56))) | G56: =IF($K56="","",IF(INDEX(Transactions!$E$5:$E$5004,$K56)="","",INDEX(Transactions!$E$5:$E$5004,$K56))) | H56: =IF($K56="","",IF(INDEX(Transactions!$F$5:$F$5004,$K56)="","",INDEX(Transactions!$F$5:$F$5004,$K56))) | I56: =IF($K56="","",IF(INDEX(Transactions!$G$5:$G$5004,$K56)="","",INDEX(Transactions!$G$5:$G$5004,$K56))) | K56: =IFERROR(MATCH(42,Transactions!$H$5:$H$5004,0),"")
B57: =IF($K57="","",43) | C57: =IF($K57="","",IF(INDEX(Transactions!$A$5:$A$5004,$K57)="","",INDEX(Transactions!$A$5:$A$5004,$K57))) | D57: =IF($K57="","",IF(INDEX(Transactions!$B$5:$B$5004,$K57)="","",INDEX(Transactions!$B$5:$B$5004,$K57))) | E57: =IF($K57="","",IF(INDEX(Transactions!$C$5:$C$5004,$K57)="","",INDEX(Transactions!$C$5:$C$5004,$K57))) | F57: =IF($K57="","",IF(INDEX(Transactions!$D$5:$D$5004,$K57)="","",INDEX(Transactions!$D$5:$D$5004,$K57))) | G57: =IF($K57="","",IF(INDEX(Transactions!$E$5:$E$5004,$K57)="","",INDEX(Transactions!$E$5:$E$5004,$K57))) | H57: =IF($K57="","",IF(INDEX(Transactions!$F$5:$F$5004,$K57)="","",INDEX(Transactions!$F$5:$F$5004,$K57))) | I57: =IF($K57="","",IF(INDEX(Transactions!$G$5:$G$5004,$K57)="","",INDEX(Transactions!$G$5:$G$5004,$K57))) | K57: =IFERROR(MATCH(43,Transactions!$H$5:$H$5004,0),"")
B58: =IF($K58="","",44) | C58: =IF($K58="","",IF(INDEX(Transactions!$A$5:$A$5004,$K58)="","",INDEX(Transactions!$A$5:$A$5004,$K58))) | D58: =IF($K58="","",IF(INDEX(Transactions!$B$5:$B$5004,$K58)="","",INDEX(Transactions!$B$5:$B$5004,$K58))) | E58: =IF($K58="","",IF(INDEX(Transactions!$C$5:$C$5004,$K58)="","",INDEX(Transactions!$C$5:$C$5004,$K58))) | F58: =IF($K58="","",IF(INDEX(Transactions!$D$5:$D$5004,$K58)="","",INDEX(Transactions!$D$5:$D$5004,$K58))) | G58: =IF($K58="","",IF(INDEX(Transactions!$E$5:$E$5004,$K58)="","",INDEX(Transactions!$E$5:$E$5004,$K58))) | H58: =IF($K58="","",IF(INDEX(Transactions!$F$5:$F$5004,$K58)="","",INDEX(Transactions!$F$5:$F$5004,$K58))) | I58: =IF($K58="","",IF(INDEX(Transactions!$G$5:$G$5004,$K58)="","",INDEX(Transactions!$G$5:$G$5004,$K58))) | K58: =IFERROR(MATCH(44,Transactions!$H$5:$H$5004,0),"")
B59: =IF($K59="","",45) | C59: =IF($K59="","",IF(INDEX(Transactions!$A$5:$A$5004,$K59)="","",INDEX(Transactions!$A$5:$A$5004,$K59))) | D59: =IF($K59="","",IF(INDEX(Transactions!$B$5:$B$5004,$K59)="","",INDEX(Transactions!$B$5:$B$5004,$K59))) | E59: =IF($K59="","",IF(INDEX(Transactions!$C$5:$C$5004,$K59)="","",INDEX(Transactions!$C$5:$C$5004,$K59))) | F59: =IF($K59="","",IF(INDEX(Transactions!$D$5:$D$5004,$K59)="","",INDEX(Transactions!$D$5:$D$5004,$K59))) | G59: =IF($K59="","",IF(INDEX(Transactions!$E$5:$E$5004,$K59)="","",INDEX(Transactions!$E$5:$E$5004,$K59))) | H59: =IF($K59="","",IF(INDEX(Transactions!$F$5:$F$5004,$K59)="","",INDEX(Transactions!$F$5:$F$5004,$K59))) | I59: =IF($K59="","",IF(INDEX(Transactions!$G$5:$G$5004,$K59)="","",INDEX(Transactions!$G$5:$G$5004,$K59))) | K59: =IFERROR(MATCH(45,Transactions!$H$5:$H$5004,0),"")
B60: =IF($K60="","",46) | C60: =IF($K60="","",IF(INDEX(Transactions!$A$5:$A$5004,$K60)="","",INDEX(Transactions!$A$5:$A$5004,$K60))) | D60: =IF($K60="","",IF(INDEX(Transactions!$B$5:$B$5004,$K60)="","",INDEX(Transactions!$B$5:$B$5004,$K60))) | E60: =IF($K60="","",IF(INDEX(Transactions!$C$5:$C$5004,$K60)="","",INDEX(Transactions!$C$5:$C$5004,$K60))) | F60: =IF($K60="","",IF(INDEX(Transactions!$D$5:$D$5004,$K60)="","",INDEX(Transactions!$D$5:$D$5004,$K60))) | G60: =IF($K60="","",IF(INDEX(Transactions!$E$5:$E$5004,$K60)="","",INDEX(Transactions!$E$5:$E$5004,$K60))) | H60: =IF($K60="","",IF(INDEX(Transactions!$F$5:$F$5004,$K60)="","",INDEX(Transactions!$F$5:$F$5004,$K60))) | I60: =IF($K60="","",IF(INDEX(Transactions!$G$5:$G$5004,$K60)="","",INDEX(Transactions!$G$5:$G$5004,$K60))) | K60: =IFERROR(MATCH(46,Transactions!$H$5:$H$5004,0),"")
B61: =IF($K61="","",47) | C61: =IF($K61="","",IF(INDEX(Transactions!$A$5:$A$5004,$K61)="","",INDEX(Transactions!$A$5:$A$5004,$K61))) | D61: =IF($K61="","",IF(INDEX(Transactions!$B$5:$B$5004,$K61)="","",INDEX(Transactions!$B$5:$B$5004,$K61))) | E61: =IF($K61="","",IF(INDEX(Transactions!$C$5:$C$5004,$K61)="","",INDEX(Transactions!$C$5:$C$5004,$K61))) | F61: =IF($K61="","",IF(INDEX(Transactions!$D$5:$D$5004,$K61)="","",INDEX(Transactions!$D$5:$D$5004,$K61))) | G61: =IF($K61="","",IF(INDEX(Transactions!$E$5:$E$5004,$K61)="","",INDEX(Transactions!$E$5:$E$5004,$K61))) | H61: =IF($K61="","",IF(INDEX(Transactions!$F$5:$F$5004,$K61)="","",INDEX(Transactions!$F$5:$F$5004,$K61))) | I61: =IF($K61="","",IF(INDEX(Transactions!$G$5:$G$5004,$K61)="","",INDEX(Transactions!$G$5:$G$5004,$K61))) | K61: =IFERROR(MATCH(47,Transactions!$H$5:$H$5004,0),"")
B62: =IF($K62="","",48) | C62: =IF($K62="","",IF(INDEX(Transactions!$A$5:$A$5004,$K62)="","",INDEX(Transactions!$A$5:$A$5004,$K62))) | D62: =IF($K62="","",IF(INDEX(Transactions!$B$5:$B$5004,$K62)="","",INDEX(Transactions!$B$5:$B$5004,$K62))) | E62: =IF($K62="","",IF(INDEX(Transactions!$C$5:$C$5004,$K62)="","",INDEX(Transactions!$C$5:$C$5004,$K62))) | F62: =IF($K62="","",IF(INDEX(Transactions!$D$5:$D$5004,$K62)="","",INDEX(Transactions!$D$5:$D$5004,$K62))) | G62: =IF($K62="","",IF(INDEX(Transactions!$E$5:$E$5004,$K62)="","",INDEX(Transactions!$E$5:$E$5004,$K62))) | H62: =IF($K62="","",IF(INDEX(Transactions!$F$5:$F$5004,$K62)="","",INDEX(Transactions!$F$5:$F$5004,$K62))) | I62: =IF($K62="","",IF(INDEX(Transactions!$G$5:$G$5004,$K62)="","",INDEX(Transactions!$G$5:$G$5004,$K62))) | K62: =IFERROR(MATCH(48,Transactions!$H$5:$H$5004,0),"")
B63: =IF($K63="","",49) | C63: =IF($K63="","",IF(INDEX(Transactions!$A$5:$A$5004,$K63)="","",INDEX(Transactions!$A$5:$A$5004,$K63))) | D63: =IF($K63="","",IF(INDEX(Transactions!$B$5:$B$5004,$K63)="","",INDEX(Transactions!$B$5:$B$5004,$K63))) | E63: =IF($K63="","",IF(INDEX(Transactions!$C$5:$C$5004,$K63)="","",INDEX(Transactions!$C$5:$C$5004,$K63))) | F63: =IF($K63="","",IF(INDEX(Transactions!$D$5:$D$5004,$K63)="","",INDEX(Transactions!$D$5:$D$5004,$K63))) | G63: =IF($K63="","",IF(INDEX(Transactions!$E$5:$E$5004,$K63)="","",INDEX(Transactions!$E$5:$E$5004,$K63))) | H63: =IF($K63="","",IF(INDEX(Transactions!$F$5:$F$5004,$K63)="","",INDEX(Transactions!$F$5:$F$5004,$K63))) | I63: =IF($K63="","",IF(INDEX(Transactions!$G$5:$G$5004,$K63)="","",INDEX(Transactions!$G$5:$G$5004,$K63))) | K63: =IFERROR(MATCH(49,Transactions!$H$5:$H$5004,0),"")
B64: =IF($K64="","",50) | C64: =IF($K64="","",IF(INDEX(Transactions!$A$5:$A$5004,$K64)="","",INDEX(Transactions!$A$5:$A$5004,$K64))) | D64: =IF($K64="","",IF(INDEX(Transactions!$B$5:$B$5004,$K64)="","",INDEX(Transactions!$B$5:$B$5004,$K64))) | E64: =IF($K64="","",IF(INDEX(Transactions!$C$5:$C$5004,$K64)="","",INDEX(Transactions!$C$5:$C$5004,$K64))) | F64: =IF($K64="","",IF(INDEX(Transactions!$D$5:$D$5004,$K64)="","",INDEX(Transactions!$D$5:$D$5004,$K64))) | G64: =IF($K64="","",IF(INDEX(Transactions!$E$5:$E$5004,$K64)="","",INDEX(Transactions!$E$5:$E$5004,$K64))) | H64: =IF($K64="","",IF(INDEX(Transactions!$F$5:$F$5004,$K64)="","",INDEX(Transactions!$F$5:$F$5004,$K64))) | I64: =IF($K64="","",IF(INDEX(Transactions!$G$5:$G$5004,$K64)="","",INDEX(Transactions!$G$5:$G$5004,$K64))) | K64: =IFERROR(MATCH(50,Transactions!$H$5:$H$5004,0),"")
B65: =IF($K65="","",51) | C65: =IF($K65="","",IF(INDEX(Transactions!$A$5:$A$5004,$K65)="","",INDEX(Transactions!$A$5:$A$5004,$K65))) | D65: =IF($K65="","",IF(INDEX(Transactions!$B$5:$B$5004,$K65)="","",INDEX(Transactions!$B$5:$B$5004,$K65))) | E65: =IF($K65="","",IF(INDEX(Transactions!$C$5:$C$5004,$K65)="","",INDEX(Transactions!$C$5:$C$5004,$K65))) | F65: =IF($K65="","",IF(INDEX(Transactions!$D$5:$D$5004,$K65)="","",INDEX(Transactions!$D$5:$D$5004,$K65))) | G65: =IF($K65="","",IF(INDEX(Transactions!$E$5:$E$5004,$K65)="","",INDEX(Transactions!$E$5:$E$5004,$K65))) | H65: =IF($K65="","",IF(INDEX(Transactions!$F$5:$F$5004,$K65)="","",INDEX(Transactions!$F$5:$F$5004,$K65))) | I65: =IF($K65="","",IF(INDEX(Transactions!$G$5:$G$5004,$K65)="","",INDEX(Transactions!$G$5:$G$5004,$K65))) | K65: =IFERROR(MATCH(51,Transactions!$H$5:$H$5004,0),"")
B66: =IF($K66="","",52) | C66: =IF($K66="","",IF(INDEX(Transactions!$A$5:$A$5004,$K66)="","",INDEX(Transactions!$A$5:$A$5004,$K66))) | D66: =IF($K66="","",IF(INDEX(Transactions!$B$5:$B$5004,$K66)="","",INDEX(Transactions!$B$5:$B$5004,$K66))) | E66: =IF($K66="","",IF(INDEX(Transactions!$C$5:$C$5004,$K66)="","",INDEX(Transactions!$C$5:$C$5004,$K66))) | F66: =IF($K66="","",IF(INDEX(Transactions!$D$5:$D$5004,$K66)="","",INDEX(Transactions!$D$5:$D$5004,$K66))) | G66: =IF($K66="","",IF(INDEX(Transactions!$E$5:$E$5004,$K66)="","",INDEX(Transactions!$E$5:$E$5004,$K66))) | H66: =IF($K66="","",IF(INDEX(Transactions!$F$5:$F$5004,$K66)="","",INDEX(Transactions!$F$5:$F$5004,$K66))) | I66: =IF($K66="","",IF(INDEX(Transactions!$G$5:$G$5004,$K66)="","",INDEX(Transactions!$G$5:$G$5004,$K66))) | K66: =IFERROR(MATCH(52,Transactions!$H$5:$H$5004,0),"")
B67: =IF($K67="","",53) | C67: =IF($K67="","",IF(INDEX(Transactions!$A$5:$A$5004,$K67)="","",INDEX(Transactions!$A$5:$A$5004,$K67))) | D67: =IF($K67="","",IF(INDEX(Transactions!$B$5:$B$5004,$K67)="","",INDEX(Transactions!$B$5:$B$5004,$K67))) | E67: =IF($K67="","",IF(INDEX(Transactions!$C$5:$C$5004,$K67)="","",INDEX(Transactions!$C$5:$C$5004,$K67))) | F67: =IF($K67="","",IF(INDEX(Transactions!$D$5:$D$5004,$K67)="","",INDEX(Transactions!$D$5:$D$5004,$K67))) | G67: =IF($K67="","",IF(INDEX(Transactions!$E$5:$E$5004,$K67)="","",INDEX(Transactions!$E$5:$E$5004,$K67))) | H67: =IF($K67="","",IF(INDEX(Transactions!$F$5:$F$5004,$K67)="","",INDEX(Transactions!$F$5:$F$5004,$K67))) | I67: =IF($K67="","",IF(INDEX(Transactions!$G$5:$G$5004,$K67)="","",INDEX(Transactions!$G$5:$G$5004,$K67))) | K67: =IFERROR(MATCH(53,Transactions!$H$5:$H$5004,0),"")
B68: =IF($K68="","",54) | C68: =IF($K68="","",IF(INDEX(Transactions!$A$5:$A$5004,$K68)="","",INDEX(Transactions!$A$5:$A$5004,$K68))) | D68: =IF($K68="","",IF(INDEX(Transactions!$B$5:$B$5004,$K68)="","",INDEX(Transactions!$B$5:$B$5004,$K68))) | E68: =IF($K68="","",IF(INDEX(Transactions!$C$5:$C$5004,$K68)="","",INDEX(Transactions!$C$5:$C$5004,$K68))) | F68: =IF($K68="","",IF(INDEX(Transactions!$D$5:$D$5004,$K68)="","",INDEX(Transactions!$D$5:$D$5004,$K68))) | G68: =IF($K68="","",IF(INDEX(Transactions!$E$5:$E$5004,$K68)="","",INDEX(Transactions!$E$5:$E$5004,$K68))) | H68: =IF($K68="","",IF(INDEX(Transactions!$F$5:$F$5004,$K68)="","",INDEX(Transactions!$F$5:$F$5004,$K68))) | I68: =IF($K68="","",IF(INDEX(Transactions!$G$5:$G$5004,$K68)="","",INDEX(Transactions!$G$5:$G$5004,$K68))) | K68: =IFERROR(MATCH(54,Transactions!$H$5:$H$5004,0),"")
B69: =IF($K69="","",55) | C69: =IF($K69="","",IF(INDEX(Transactions!$A$5:$A$5004,$K69)="","",INDEX(Transactions!$A$5:$A$5004,$K69))) | D69: =IF($K69="","",IF(INDEX(Transactions!$B$5:$B$5004,$K69)="","",INDEX(Transactions!$B$5:$B$5004,$K69))) | E69: =IF($K69="","",IF(INDEX(Transactions!$C$5:$C$5004,$K69)="","",INDEX(Transactions!$C$5:$C$5004,$K69))) | F69: =IF($K69="","",IF(INDEX(Transactions!$D$5:$D$5004,$K69)="","",INDEX(Transactions!$D$5:$D$5004,$K69))) | G69: =IF($K69="","",IF(INDEX(Transactions!$E$5:$E$5004,$K69)="","",INDEX(Transactions!$E$5:$E$5004,$K69))) | H69: =IF($K69="","",IF(INDEX(Transactions!$F$5:$F$5004,$K69)="","",INDEX(Transactions!$F$5:$F$5004,$K69))) | I69: =IF($K69="","",IF(INDEX(Transactions!$G$5:$G$5004,$K69)="","",INDEX(Transactions!$G$5:$G$5004,$K69))) | K69: =IFERROR(MATCH(55,Transactions!$H$5:$H$5004,0),"")
B70: =IF($K70="","",56) | C70: =IF($K70="","",IF(INDEX(Transactions!$A$5:$A$5004,$K70)="","",INDEX(Transactions!$A$5:$A$5004,$K70))) | D70: =IF($K70="","",IF(INDEX(Transactions!$B$5:$B$5004,$K70)="","",INDEX(Transactions!$B$5:$B$5004,$K70))) | E70: =IF($K70="","",IF(INDEX(Transactions!$C$5:$C$5004,$K70)="","",INDEX(Transactions!$C$5:$C$5004,$K70))) | F70: =IF($K70="","",IF(INDEX(Transactions!$D$5:$D$5004,$K70)="","",INDEX(Transactions!$D$5:$D$5004,$K70))) | G70: =IF($K70="","",IF(INDEX(Transactions!$E$5:$E$5004,$K70)="","",INDEX(Transactions!$E$5:$E$5004,$K70))) | H70: =IF($K70="","",IF(INDEX(Transactions!$F$5:$F$5004,$K70)="","",INDEX(Transactions!$F$5:$F$5004,$K70))) | I70: =IF($K70="","",IF(INDEX(Transactions!$G$5:$G$5004,$K70)="","",INDEX(Transactions!$G$5:$G$5004,$K70))) | K70: =IFERROR(MATCH(56,Transactions!$H$5:$H$5004,0),"")
B71: =IF($K71="","",57) | C71: =IF($K71="","",IF(INDEX(Transactions!$A$5:$A$5004,$K71)="","",INDEX(Transactions!$A$5:$A$5004,$K71))) | D71: =IF($K71="","",IF(INDEX(Transactions!$B$5:$B$5004,$K71)="","",INDEX(Transactions!$B$5:$B$5004,$K71))) | E71: =IF($K71="","",IF(INDEX(Transactions!$C$5:$C$5004,$K71)="","",INDEX(Transactions!$C$5:$C$5004,$K71))) | F71: =IF($K71="","",IF(INDEX(Transactions!$D$5:$D$5004,$K71)="","",INDEX(Transactions!$D$5:$D$5004,$K71))) | G71: =IF($K71="","",IF(INDEX(Transactions!$E$5:$E$5004,$K71)="","",INDEX(Transactions!$E$5:$E$5004,$K71))) | H71: =IF($K71="","",IF(INDEX(Transactions!$F$5:$F$5004,$K71)="","",INDEX(Transactions!$F$5:$F$5004,$K71))) | I71: =IF($K71="","",IF(INDEX(Transactions!$G$5:$G$5004,$K71)="","",INDEX(Transactions!$G$5:$G$5004,$K71))) | K71: =IFERROR(MATCH(57,Transactions!$H$5:$H$5004,0),"")
B72: =IF($K72="","",58) | C72: =IF($K72="","",IF(INDEX(Transactions!$A$5:$A$5004,$K72)="","",INDEX(Transactions!$A$5:$A$5004,$K72))) | D72: =IF($K72="","",IF(INDEX(Transactions!$B$5:$B$5004,$K72)="","",INDEX(Transactions!$B$5:$B$5004,$K72))) | E72: =IF($K72="","",IF(INDEX(Transactions!$C$5:$C$5004,$K72)="","",INDEX(Transactions!$C$5:$C$5004,$K72))) | F72: =IF($K72="","",IF(INDEX(Transactions!$D$5:$D$5004,$K72)="","",INDEX(Transactions!$D$5:$D$5004,$K72))) | G72: =IF($K72="","",IF(INDEX(Transactions!$E$5:$E$5004,$K72)="","",INDEX(Transactions!$E$5:$E$5004,$K72))) | H72: =IF($K72="","",IF(INDEX(Transactions!$F$5:$F$5004,$K72)="","",INDEX(Transactions!$F$5:$F$5004,$K72))) | I72: =IF($K72="","",IF(INDEX(Transactions!$G$5:$G$5004,$K72)="","",INDEX(Transactions!$G$5:$G$5004,$K72))) | K72: =IFERROR(MATCH(58,Transactions!$H$5:$H$5004,0),"")
B73: =IF($K73="","",59) | C73: =IF($K73="","",IF(INDEX(Transactions!$A$5:$A$5004,$K73)="","",INDEX(Transactions!$A$5:$A$5004,$K73))) | D73: =IF($K73="","",IF(INDEX(Transactions!$B$5:$B$5004,$K73)="","",INDEX(Transactions!$B$5:$B$5004,$K73))) | E73: =IF($K73="","",IF(INDEX(Transactions!$C$5:$C$5004,$K73)="","",INDEX(Transactions!$C$5:$C$5004,$K73))) | F73: =IF($K73="","",IF(INDEX(Transactions!$D$5:$D$5004,$K73)="","",INDEX(Transactions!$D$5:$D$5004,$K73))) | G73: =IF($K73="","",IF(INDEX(Transactions!$E$5:$E$5004,$K73)="","",INDEX(Transactions!$E$5:$E$5004,$K73))) | H73: =IF($K73="","",IF(INDEX(Transactions!$F$5:$F$5004,$K73)="","",INDEX(Transactions!$F$5:$F$5004,$K73))) | I73: =IF($K73="","",IF(INDEX(Transactions!$G$5:$G$5004,$K73)="","",INDEX(Transactions!$G$5:$G$5004,$K73))) | K73: =IFERROR(MATCH(59,Transactions!$H$5:$H$5004,0),"")
B74: =IF($K74="","",60) | C74: =IF($K74="","",IF(INDEX(Transactions!$A$5:$A$5004,$K74)="","",INDEX(Transactions!$A$5:$A$5004,$K74))) | D74: =IF($K74="","",IF(INDEX(Transactions!$B$5:$B$5004,$K74)="","",INDEX(Transactions!$B$5:$B$5004,$K74))) | E74: =IF($K74="","",IF(INDEX(Transactions!$C$5:$C$5004,$K74)="","",INDEX(Transactions!$C$5:$C$5004,$K74))) | F74: =IF($K74="","",IF(INDEX(Transactions!$D$5:$D$5004,$K74)="","",INDEX(Transactions!$D$5:$D$5004,$K74))) | G74: =IF($K74="","",IF(INDEX(Transactions!$E$5:$E$5004,$K74)="","",INDEX(Transactions!$E$5:$E$5004,$K74))) | H74: =IF($K74="","",IF(INDEX(Transactions!$F$5:$F$5004,$K74)="","",INDEX(Transactions!$F$5:$F$5004,$K74))) | I74: =IF($K74="","",IF(INDEX(Transactions!$G$5:$G$5004,$K74)="","",INDEX(Transactions!$G$5:$G$5004,$K74))) | K74: =IFERROR(MATCH(60,Transactions!$H$5:$H$5004,0),"")
B75: =IF($K75="","",61) | C75: =IF($K75="","",IF(INDEX(Transactions!$A$5:$A$5004,$K75)="","",INDEX(Transactions!$A$5:$A$5004,$K75))) | D75: =IF($K75="","",IF(INDEX(Transactions!$B$5:$B$5004,$K75)="","",INDEX(Transactions!$B$5:$B$5004,$K75))) | E75: =IF($K75="","",IF(INDEX(Transactions!$C$5:$C$5004,$K75)="","",INDEX(Transactions!$C$5:$C$5004,$K75))) | F75: =IF($K75="","",IF(INDEX(Transactions!$D$5:$D$5004,$K75)="","",INDEX(Transactions!$D$5:$D$5004,$K75))) | G75: =IF($K75="","",IF(INDEX(Transactions!$E$5:$E$5004,$K75)="","",INDEX(Transactions!$E$5:$E$5004,$K75))) | H75: =IF($K75="","",IF(INDEX(Transactions!$F$5:$F$5004,$K75)="","",INDEX(Transactions!$F$5:$F$5004,$K75))) | I75: =IF($K75="","",IF(INDEX(Transactions!$G$5:$G$5004,$K75)="","",INDEX(Transactions!$G$5:$G$5004,$K75))) | K75: =IFERROR(MATCH(61,Transactions!$H$5:$H$5004,0),"")
B76: =IF($K76="","",62) | C76: =IF($K76="","",IF(INDEX(Transactions!$A$5:$A$5004,$K76)="","",INDEX(Transactions!$A$5:$A$5004,$K76))) | D76: =IF($K76="","",IF(INDEX(Transactions!$B$5:$B$5004,$K76)="","",INDEX(Transactions!$B$5:$B$5004,$K76))) | E76: =IF($K76="","",IF(INDEX(Transactions!$C$5:$C$5004,$K76)="","",INDEX(Transactions!$C$5:$C$5004,$K76))) | F76: =IF($K76="","",IF(INDEX(Transactions!$D$5:$D$5004,$K76)="","",INDEX(Transactions!$D$5:$D$5004,$K76))) | G76: =IF($K76="","",IF(INDEX(Transactions!$E$5:$E$5004,$K76)="","",INDEX(Transactions!$E$5:$E$5004,$K76))) | H76: =IF($K76="","",IF(INDEX(Transactions!$F$5:$F$5004,$K76)="","",INDEX(Transactions!$F$5:$F$5004,$K76))) | I76: =IF($K76="","",IF(INDEX(Transactions!$G$5:$G$5004,$K76)="","",INDEX(Transactions!$G$5:$G$5004,$K76))) | K76: =IFERROR(MATCH(62,Transactions!$H$5:$H$5004,0),"")
B77: =IF($K77="","",63) | C77: =IF($K77="","",IF(INDEX(Transactions!$A$5:$A$5004,$K77)="","",INDEX(Transactions!$A$5:$A$5004,$K77))) | D77: =IF($K77="","",IF(INDEX(Transactions!$B$5:$B$5004,$K77)="","",INDEX(Transactions!$B$5:$B$5004,$K77))) | E77: =IF($K77="","",IF(INDEX(Transactions!$C$5:$C$5004,$K77)="","",INDEX(Transactions!$C$5:$C$5004,$K77))) | F77: =IF($K77="","",IF(INDEX(Transactions!$D$5:$D$5004,$K77)="","",INDEX(Transactions!$D$5:$D$5004,$K77))) | G77: =IF($K77="","",IF(INDEX(Transactions!$E$5:$E$5004,$K77)="","",INDEX(Transactions!$E$5:$E$5004,$K77))) | H77: =IF($K77="","",IF(INDEX(Transactions!$F$5:$F$5004,$K77)="","",INDEX(Transactions!$F$5:$F$5004,$K77))) | I77: =IF($K77="","",IF(INDEX(Transactions!$G$5:$G$5004,$K77)="","",INDEX(Transactions!$G$5:$G$5004,$K77))) | K77: =IFERROR(MATCH(63,Transactions!$H$5:$H$5004,0),"")
B78: =IF($K78="","",64) | C78: =IF($K78="","",IF(INDEX(Transactions!$A$5:$A$5004,$K78)="","",INDEX(Transactions!$A$5:$A$5004,$K78))) | D78: =IF($K78="","",IF(INDEX(Transactions!$B$5:$B$5004,$K78)="","",INDEX(Transactions!$B$5:$B$5004,$K78))) | E78: =IF($K78="","",IF(INDEX(Transactions!$C$5:$C$5004,$K78)="","",INDEX(Transactions!$C$5:$C$5004,$K78))) | F78: =IF($K78="","",IF(INDEX(Transactions!$D$5:$D$5004,$K78)="","",INDEX(Transactions!$D$5:$D$5004,$K78))) | G78: =IF($K78="","",IF(INDEX(Transactions!$E$5:$E$5004,$K78)="","",INDEX(Transactions!$E$5:$E$5004,$K78))) | H78: =IF($K78="","",IF(INDEX(Transactions!$F$5:$F$5004,$K78)="","",INDEX(Transactions!$F$5:$F$5004,$K78))) | I78: =IF($K78="","",IF(INDEX(Transactions!$G$5:$G$5004,$K78)="","",INDEX(Transactions!$G$5:$G$5004,$K78))) | K78: =IFERROR(MATCH(64,Transactions!$H$5:$H$5004,0),"")
B79: =IF($K79="","",65) | C79: =IF($K79="","",IF(INDEX(Transactions!$A$5:$A$5004,$K79)="","",INDEX(Transactions!$A$5:$A$5004,$K79))) | D79: =IF($K79="","",IF(INDEX(Transactions!$B$5:$B$5004,$K79)="","",INDEX(Transactions!$B$5:$B$5004,$K79))) | E79: =IF($K79="","",IF(INDEX(Transactions!$C$5:$C$5004,$K79)="","",INDEX(Transactions!$C$5:$C$5004,$K79))) | F79: =IF($K79="","",IF(INDEX(Transactions!$D$5:$D$5004,$K79)="","",INDEX(Transactions!$D$5:$D$5004,$K79))) | G79: =IF($K79="","",IF(INDEX(Transactions!$E$5:$E$5004,$K79)="","",INDEX(Transactions!$E$5:$E$5004,$K79))) | H79: =IF($K79="","",IF(INDEX(Transactions!$F$5:$F$5004,$K79)="","",INDEX(Transactions!$F$5:$F$5004,$K79))) | I79: =IF($K79="","",IF(INDEX(Transactions!$G$5:$G$5004,$K79)="","",INDEX(Transactions!$G$5:$G$5004,$K79))) | K79: =IFERROR(MATCH(65,Transactions!$H$5:$H$5004,0),"")
B80: =IF($K80="","",66) | C80: =IF($K80="","",IF(INDEX(Transactions!$A$5:$A$5004,$K80)="","",INDEX(Transactions!$A$5:$A$5004,$K80))) | D80: =IF($K80="","",IF(INDEX(Transactions!$B$5:$B$5004,$K80)="","",INDEX(Transactions!$B$5:$B$5004,$K80))) | E80: =IF($K80="","",IF(INDEX(Transactions!$C$5:$C$5004,$K80)="","",INDEX(Transactions!$C$5:$C$5004,$K80))) | F80: =IF($K80="","",IF(INDEX(Transactions!$D$5:$D$5004,$K80)="","",INDEX(Transactions!$D$5:$D$5004,$K80))) | G80: =IF($K80="","",IF(INDEX(Transactions!$E$5:$E$5004,$K80)="","",INDEX(Transactions!$E$5:$E$5004,$K80))) | H80: =IF($K80="","",IF(INDEX(Transactions!$F$5:$F$5004,$K80)="","",INDEX(Transactions!$F$5:$F$5004,$K80))) | I80: =IF($K80="","",IF(INDEX(Transactions!$G$5:$G$5004,$K80)="","",INDEX(Transactions!$G$5:$G$5004,$K80))) | K80: =IFERROR(MATCH(66,Transactions!$H$5:$H$5004,0),"")
B81: =IF($K81="","",67) | C81: =IF($K81="","",IF(INDEX(Transactions!$A$5:$A$5004,$K81)="","",INDEX(Transactions!$A$5:$A$5004,$K81))) | D81: =IF($K81="","",IF(INDEX(Transactions!$B$5:$B$5004,$K81)="","",INDEX(Transactions!$B$5:$B$5004,$K81))) | E81: =IF($K81="","",IF(INDEX(Transactions!$C$5:$C$5004,$K81)="","",INDEX(Transactions!$C$5:$C$5004,$K81))) | F81: =IF($K81="","",IF(INDEX(Transactions!$D$5:$D$5004,$K81)="","",INDEX(Transactions!$D$5:$D$5004,$K81))) | G81: =IF($K81="","",IF(INDEX(Transactions!$E$5:$E$5004,$K81)="","",INDEX(Transactions!$E$5:$E$5004,$K81))) | H81: =IF($K81="","",IF(INDEX(Transactions!$F$5:$F$5004,$K81)="","",INDEX(Transactions!$F$5:$F$5004,$K81))) | I81: =IF($K81="","",IF(INDEX(Transactions!$G$5:$G$5004,$K81)="","",INDEX(Transactions!$G$5:$G$5004,$K81))) | K81: =IFERROR(MATCH(67,Transactions!$H$5:$H$5004,0),"")
B82: =IF($K82="","",68) | C82: =IF($K82="","",IF(INDEX(Transactions!$A$5:$A$5004,$K82)="","",INDEX(Transactions!$A$5:$A$5004,$K82))) | D82: =IF($K82="","",IF(INDEX(Transactions!$B$5:$B$5004,$K82)="","",INDEX(Transactions!$B$5:$B$5004,$K82))) | E82: =IF($K82="","",IF(INDEX(Transactions!$C$5:$C$5004,$K82)="","",INDEX(Transactions!$C$5:$C$5004,$K82))) | F82: =IF($K82="","",IF(INDEX(Transactions!$D$5:$D$5004,$K82)="","",INDEX(Transactions!$D$5:$D$5004,$K82))) | G82: =IF($K82="","",IF(INDEX(Transactions!$E$5:$E$5004,$K82)="","",INDEX(Transactions!$E$5:$E$5004,$K82))) | H82: =IF($K82="","",IF(INDEX(Transactions!$F$5:$F$5004,$K82)="","",INDEX(Transactions!$F$5:$F$5004,$K82))) | I82: =IF($K82="","",IF(INDEX(Transactions!$G$5:$G$5004,$K82)="","",INDEX(Transactions!$G$5:$G$5004,$K82))) | K82: =IFERROR(MATCH(68,Transactions!$H$5:$H$5004,0),"")
B83: =IF($K83="","",69) | C83: =IF($K83="","",IF(INDEX(Transactions!$A$5:$A$5004,$K83)="","",INDEX(Transactions!$A$5:$A$5004,$K83))) | D83: =IF($K83="","",IF(INDEX(Transactions!$B$5:$B$5004,$K83)="","",INDEX(Transactions!$B$5:$B$5004,$K83))) | E83: =IF($K83="","",IF(INDEX(Transactions!$C$5:$C$5004,$K83)="","",INDEX(Transactions!$C$5:$C$5004,$K83))) | F83: =IF($K83="","",IF(INDEX(Transactions!$D$5:$D$5004,$K83)="","",INDEX(Transactions!$D$5:$D$5004,$K83))) | G83: =IF($K83="","",IF(INDEX(Transactions!$E$5:$E$5004,$K83)="","",INDEX(Transactions!$E$5:$E$5004,$K83))) | H83: =IF($K83="","",IF(INDEX(Transactions!$F$5:$F$5004,$K83)="","",INDEX(Transactions!$F$5:$F$5004,$K83))) | I83: =IF($K83="","",IF(INDEX(Transactions!$G$5:$G$5004,$K83)="","",INDEX(Transactions!$G$5:$G$5004,$K83))) | K83: =IFERROR(MATCH(69,Transactions!$H$5:$H$5004,0),"")
B84: =IF($K84="","",70) | C84: =IF($K84="","",IF(INDEX(Transactions!$A$5:$A$5004,$K84)="","",INDEX(Transactions!$A$5:$A$5004,$K84))) | D84: =IF($K84="","",IF(INDEX(Transactions!$B$5:$B$5004,$K84)="","",INDEX(Transactions!$B$5:$B$5004,$K84))) | E84: =IF($K84="","",IF(INDEX(Transactions!$C$5:$C$5004,$K84)="","",INDEX(Transactions!$C$5:$C$5004,$K84))) | F84: =IF($K84="","",IF(INDEX(Transactions!$D$5:$D$5004,$K84)="","",INDEX(Transactions!$D$5:$D$5004,$K84))) | G84: =IF($K84="","",IF(INDEX(Transactions!$E$5:$E$5004,$K84)="","",INDEX(Transactions!$E$5:$E$5004,$K84))) | H84: =IF($K84="","",IF(INDEX(Transactions!$F$5:$F$5004,$K84)="","",INDEX(Transactions!$F$5:$F$5004,$K84))) | I84: =IF($K84="","",IF(INDEX(Transactions!$G$5:$G$5004,$K84)="","",INDEX(Transactions!$G$5:$G$5004,$K84))) | K84: =IFERROR(MATCH(70,Transactions!$H$5:$H$5004,0),"")
B85: =IF($K85="","",71) | C85: =IF($K85="","",IF(INDEX(Transactions!$A$5:$A$5004,$K85)="","",INDEX(Transactions!$A$5:$A$5004,$K85))) | D85: =IF($K85="","",IF(INDEX(Transactions!$B$5:$B$5004,$K85)="","",INDEX(Transactions!$B$5:$B$5004,$K85))) | E85: =IF($K85="","",IF(INDEX(Transactions!$C$5:$C$5004,$K85)="","",INDEX(Transactions!$C$5:$C$5004,$K85))) | F85: =IF($K85="","",IF(INDEX(Transactions!$D$5:$D$5004,$K85)="","",INDEX(Transactions!$D$5:$D$5004,$K85))) | G85: =IF($K85="","",IF(INDEX(Transactions!$E$5:$E$5004,$K85)="","",INDEX(Transactions!$E$5:$E$5004,$K85))) | H85: =IF($K85="","",IF(INDEX(Transactions!$F$5:$F$5004,$K85)="","",INDEX(Transactions!$F$5:$F$5004,$K85))) | I85: =IF($K85="","",IF(INDEX(Transactions!$G$5:$G$5004,$K85)="","",INDEX(Transactions!$G$5:$G$5004,$K85))) | K85: =IFERROR(MATCH(71,Transactions!$H$5:$H$5004,0),"")
B86: =IF($K86="","",72) | C86: =IF($K86="","",IF(INDEX(Transactions!$A$5:$A$5004,$K86)="","",INDEX(Transactions!$A$5:$A$5004,$K86))) | D86: =IF($K86="","",IF(INDEX(Transactions!$B$5:$B$5004,$K86)="","",INDEX(Transactions!$B$5:$B$5004,$K86))) | E86: =IF($K86="","",IF(INDEX(Transactions!$C$5:$C$5004,$K86)="","",INDEX(Transactions!$C$5:$C$5004,$K86))) | F86: =IF($K86="","",IF(INDEX(Transactions!$D$5:$D$5004,$K86)="","",INDEX(Transactions!$D$5:$D$5004,$K86))) | G86: =IF($K86="","",IF(INDEX(Transactions!$E$5:$E$5004,$K86)="","",INDEX(Transactions!$E$5:$E$5004,$K86))) | H86: =IF($K86="","",IF(INDEX(Transactions!$F$5:$F$5004,$K86)="","",INDEX(Transactions!$F$5:$F$5004,$K86))) | I86: =IF($K86="","",IF(INDEX(Transactions!$G$5:$G$5004,$K86)="","",INDEX(Transactions!$G$5:$G$5004,$K86))) | K86: =IFERROR(MATCH(72,Transactions!$H$5:$H$5004,0),"")
B87: =IF($K87="","",73) | C87: =IF($K87="","",IF(INDEX(Transactions!$A$5:$A$5004,$K87)="","",INDEX(Transactions!$A$5:$A$5004,$K87))) | D87: =IF($K87="","",IF(INDEX(Transactions!$B$5:$B$5004,$K87)="","",INDEX(Transactions!$B$5:$B$5004,$K87))) | E87: =IF($K87="","",IF(INDEX(Transactions!$C$5:$C$5004,$K87)="","",INDEX(Transactions!$C$5:$C$5004,$K87))) | F87: =IF($K87="","",IF(INDEX(Transactions!$D$5:$D$5004,$K87)="","",INDEX(Transactions!$D$5:$D$5004,$K87))) | G87: =IF($K87="","",IF(INDEX(Transactions!$E$5:$E$5004,$K87)="","",INDEX(Transactions!$E$5:$E$5004,$K87))) | H87: =IF($K87="","",IF(INDEX(Transactions!$F$5:$F$5004,$K87)="","",INDEX(Transactions!$F$5:$F$5004,$K87))) | I87: =IF($K87="","",IF(INDEX(Transactions!$G$5:$G$5004,$K87)="","",INDEX(Transactions!$G$5:$G$5004,$K87))) | K87: =IFERROR(MATCH(73,Transactions!$H$5:$H$5004,0),"")
B88: =IF($K88="","",74) | C88: =IF($K88="","",IF(INDEX(Transactions!$A$5:$A$5004,$K88)="","",INDEX(Transactions!$A$5:$A$5004,$K88))) | D88: =IF($K88="","",IF(INDEX(Transactions!$B$5:$B$5004,$K88)="","",INDEX(Transactions!$B$5:$B$5004,$K88))) | E88: =IF($K88="","",IF(INDEX(Transactions!$C$5:$C$5004,$K88)="","",INDEX(Transactions!$C$5:$C$5004,$K88))) | F88: =IF($K88="","",IF(INDEX(Transactions!$D$5:$D$5004,$K88)="","",INDEX(Transactions!$D$5:$D$5004,$K88))) | G88: =IF($K88="","",IF(INDEX(Transactions!$E$5:$E$5004,$K88)="","",INDEX(Transactions!$E$5:$E$5004,$K88))) | H88: =IF($K88="","",IF(INDEX(Transactions!$F$5:$F$5004,$K88)="","",INDEX(Transactions!$F$5:$F$5004,$K88))) | I88: =IF($K88="","",IF(INDEX(Transactions!$G$5:$G$5004,$K88)="","",INDEX(Transactions!$G$5:$G$5004,$K88))) | K88: =IFERROR(MATCH(74,Transactions!$H$5:$H$5004,0),"")
B89: =IF($K89="","",75) | C89: =IF($K89="","",IF(INDEX(Transactions!$A$5:$A$5004,$K89)="","",INDEX(Transactions!$A$5:$A$5004,$K89))) | D89: =IF($K89="","",IF(INDEX(Transactions!$B$5:$B$5004,$K89)="","",INDEX(Transactions!$B$5:$B$5004,$K89))) | E89: =IF($K89="","",IF(INDEX(Transactions!$C$5:$C$5004,$K89)="","",INDEX(Transactions!$C$5:$C$5004,$K89))) | F89: =IF($K89="","",IF(INDEX(Transactions!$D$5:$D$5004,$K89)="","",INDEX(Transactions!$D$5:$D$5004,$K89))) | G89: =IF($K89="","",IF(INDEX(Transactions!$E$5:$E$5004,$K89)="","",INDEX(Transactions!$E$5:$E$5004,$K89))) | H89: =IF($K89="","",IF(INDEX(Transactions!$F$5:$F$5004,$K89)="","",INDEX(Transactions!$F$5:$F$5004,$K89))) | I89: =IF($K89="","",IF(INDEX(Transactions!$G$5:$G$5004,$K89)="","",INDEX(Transactions!$G$5:$G$5004,$K89))) | K89: =IFERROR(MATCH(75,Transactions!$H$5:$H$5004,0),"")
B90: =IF($K90="","",76) | C90: =IF($K90="","",IF(INDEX(Transactions!$A$5:$A$5004,$K90)="","",INDEX(Transactions!$A$5:$A$5004,$K90))) | D90: =IF($K90="","",IF(INDEX(Transactions!$B$5:$B$5004,$K90)="","",INDEX(Transactions!$B$5:$B$5004,$K90))) | E90: =IF($K90="","",IF(INDEX(Transactions!$C$5:$C$5004,$K90)="","",INDEX(Transactions!$C$5:$C$5004,$K90))) | F90: =IF($K90="","",IF(INDEX(Transactions!$D$5:$D$5004,$K90)="","",INDEX(Transactions!$D$5:$D$5004,$K90))) | G90: =IF($K90="","",IF(INDEX(Transactions!$E$5:$E$5004,$K90)="","",INDEX(Transactions!$E$5:$E$5004,$K90))) | H90: =IF($K90="","",IF(INDEX(Transactions!$F$5:$F$5004,$K90)="","",INDEX(Transactions!$F$5:$F$5004,$K90))) | I90: =IF($K90="","",IF(INDEX(Transactions!$G$5:$G$5004,$K90)="","",INDEX(Transactions!$G$5:$G$5004,$K90))) | K90: =IFERROR(MATCH(76,Transactions!$H$5:$H$5004,0),"")
B91: =IF($K91="","",77) | C91: =IF($K91="","",IF(INDEX(Transactions!$A$5:$A$5004,$K91)="","",INDEX(Transactions!$A$5:$A$5004,$K91))) | D91: =IF($K91="","",IF(INDEX(Transactions!$B$5:$B$5004,$K91)="","",INDEX(Transactions!$B$5:$B$5004,$K91))) | E91: =IF($K91="","",IF(INDEX(Transactions!$C$5:$C$5004,$K91)="","",INDEX(Transactions!$C$5:$C$5004,$K91))) | F91: =IF($K91="","",IF(INDEX(Transactions!$D$5:$D$5004,$K91)="","",INDEX(Transactions!$D$5:$D$5004,$K91))) | G91: =IF($K91="","",IF(INDEX(Transactions!$E$5:$E$5004,$K91)="","",INDEX(Transactions!$E$5:$E$5004,$K91))) | H91: =IF($K91="","",IF(INDEX(Transactions!$F$5:$F$5004,$K91)="","",INDEX(Transactions!$F$5:$F$5004,$K91))) | I91: =IF($K91="","",IF(INDEX(Transactions!$G$5:$G$5004,$K91)="","",INDEX(Transactions!$G$5:$G$5004,$K91))) | K91: =IFERROR(MATCH(77,Transactions!$H$5:$H$5004,0),"")
B92: =IF($K92="","",78) | C92: =IF($K92="","",IF(INDEX(Transactions!$A$5:$A$5004,$K92)="","",INDEX(Transactions!$A$5:$A$5004,$K92))) | D92: =IF($K92="","",IF(INDEX(Transactions!$B$5:$B$5004,$K92)="","",INDEX(Transactions!$B$5:$B$5004,$K92))) | E92: =IF($K92="","",IF(INDEX(Transactions!$C$5:$C$5004,$K92)="","",INDEX(Transactions!$C$5:$C$5004,$K92))) | F92: =IF($K92="","",IF(INDEX(Transactions!$D$5:$D$5004,$K92)="","",INDEX(Transactions!$D$5:$D$5004,$K92))) | G92: =IF($K92="","",IF(INDEX(Transactions!$E$5:$E$5004,$K92)="","",INDEX(Transactions!$E$5:$E$5004,$K92))) | H92: =IF($K92="","",IF(INDEX(Transactions!$F$5:$F$5004,$K92)="","",INDEX(Transactions!$F$5:$F$5004,$K92))) | I92: =IF($K92="","",IF(INDEX(Transactions!$G$5:$G$5004,$K92)="","",INDEX(Transactions!$G$5:$G$5004,$K92))) | K92: =IFERROR(MATCH(78,Transactions!$H$5:$H$5004,0),"")
B93: =IF($K93="","",79) | C93: =IF($K93="","",IF(INDEX(Transactions!$A$5:$A$5004,$K93)="","",INDEX(Transactions!$A$5:$A$5004,$K93))) | D93: =IF($K93="","",IF(INDEX(Transactions!$B$5:$B$5004,$K93)="","",INDEX(Transactions!$B$5:$B$5004,$K93))) | E93: =IF($K93="","",IF(INDEX(Transactions!$C$5:$C$5004,$K93)="","",INDEX(Transactions!$C$5:$C$5004,$K93))) | F93: =IF($K93="","",IF(INDEX(Transactions!$D$5:$D$5004,$K93)="","",INDEX(Transactions!$D$5:$D$5004,$K93))) | G93: =IF($K93="","",IF(INDEX(Transactions!$E$5:$E$5004,$K93)="","",INDEX(Transactions!$E$5:$E$5004,$K93))) | H93: =IF($K93="","",IF(INDEX(Transactions!$F$5:$F$5004,$K93)="","",INDEX(Transactions!$F$5:$F$5004,$K93))) | I93: =IF($K93="","",IF(INDEX(Transactions!$G$5:$G$5004,$K93)="","",INDEX(Transactions!$G$5:$G$5004,$K93))) | K93: =IFERROR(MATCH(79,Transactions!$H$5:$H$5004,0),"")
B94: =IF($K94="","",80) | C94: =IF($K94="","",IF(INDEX(Transactions!$A$5:$A$5004,$K94)="","",INDEX(Transactions!$A$5:$A$5004,$K94))) | D94: =IF($K94="","",IF(INDEX(Transactions!$B$5:$B$5004,$K94)="","",INDEX(Transactions!$B$5:$B$5004,$K94))) | E94: =IF($K94="","",IF(INDEX(Transactions!$C$5:$C$5004,$K94)="","",INDEX(Transactions!$C$5:$C$5004,$K94))) | F94: =IF($K94="","",IF(INDEX(Transactions!$D$5:$D$5004,$K94)="","",INDEX(Transactions!$D$5:$D$5004,$K94))) | G94: =IF($K94="","",IF(INDEX(Transactions!$E$5:$E$5004,$K94)="","",INDEX(Transactions!$E$5:$E$5004,$K94))) | H94: =IF($K94="","",IF(INDEX(Transactions!$F$5:$F$5004,$K94)="","",INDEX(Transactions!$F$5:$F$5004,$K94))) | I94: =IF($K94="","",IF(INDEX(Transactions!$G$5:$G$5004,$K94)="","",INDEX(Transactions!$G$5:$G$5004,$K94))) | K94: =IFERROR(MATCH(80,Transactions!$H$5:$H$5004,0),"")
B95: =IF($K95="","",81) | C95: =IF($K95="","",IF(INDEX(Transactions!$A$5:$A$5004,$K95)="","",INDEX(Transactions!$A$5:$A$5004,$K95))) | D95: =IF($K95="","",IF(INDEX(Transactions!$B$5:$B$5004,$K95)="","",INDEX(Transactions!$B$5:$B$5004,$K95))) | E95: =IF($K95="","",IF(INDEX(Transactions!$C$5:$C$5004,$K95)="","",INDEX(Transactions!$C$5:$C$5004,$K95))) | F95: =IF($K95="","",IF(INDEX(Transactions!$D$5:$D$5004,$K95)="","",INDEX(Transactions!$D$5:$D$5004,$K95))) | G95: =IF($K95="","",IF(INDEX(Transactions!$E$5:$E$5004,$K95)="","",INDEX(Transactions!$E$5:$E$5004,$K95))) | H95: =IF($K95="","",IF(INDEX(Transactions!$F$5:$F$5004,$K95)="","",INDEX(Transactions!$F$5:$F$5004,$K95))) | I95: =IF($K95="","",IF(INDEX(Transactions!$G$5:$G$5004,$K95)="","",INDEX(Transactions!$G$5:$G$5004,$K95))) | K95: =IFERROR(MATCH(81,Transactions!$H$5:$H$5004,0),"")
B96: =IF($K96="","",82) | C96: =IF($K96="","",IF(INDEX(Transactions!$A$5:$A$5004,$K96)="","",INDEX(Transactions!$A$5:$A$5004,$K96))) | D96: =IF($K96="","",IF(INDEX(Transactions!$B$5:$B$5004,$K96)="","",INDEX(Transactions!$B$5:$B$5004,$K96))) | E96: =IF($K96="","",IF(INDEX(Transactions!$C$5:$C$5004,$K96)="","",INDEX(Transactions!$C$5:$C$5004,$K96))) | F96: =IF($K96="","",IF(INDEX(Transactions!$D$5:$D$5004,$K96)="","",INDEX(Transactions!$D$5:$D$5004,$K96))) | G96: =IF($K96="","",IF(INDEX(Transactions!$E$5:$E$5004,$K96)="","",INDEX(Transactions!$E$5:$E$5004,$K96))) | H96: =IF($K96="","",IF(INDEX(Transactions!$F$5:$F$5004,$K96)="","",INDEX(Transactions!$F$5:$F$5004,$K96))) | I96: =IF($K96="","",IF(INDEX(Transactions!$G$5:$G$5004,$K96)="","",INDEX(Transactions!$G$5:$G$5004,$K96))) | K96: =IFERROR(MATCH(82,Transactions!$H$5:$H$5004,0),"")
B97: =IF($K97="","",83) | C97: =IF($K97="","",IF(INDEX(Transactions!$A$5:$A$5004,$K97)="","",INDEX(Transactions!$A$5:$A$5004,$K97))) | D97: =IF($K97="","",IF(INDEX(Transactions!$B$5:$B$5004,$K97)="","",INDEX(Transactions!$B$5:$B$5004,$K97))) | E97: =IF($K97="","",IF(INDEX(Transactions!$C$5:$C$5004,$K97)="","",INDEX(Transactions!$C$5:$C$5004,$K97))) | F97: =IF($K97="","",IF(INDEX(Transactions!$D$5:$D$5004,$K97)="","",INDEX(Transactions!$D$5:$D$5004,$K97))) | G97: =IF($K97="","",IF(INDEX(Transactions!$E$5:$E$5004,$K97)="","",INDEX(Transactions!$E$5:$E$5004,$K97))) | H97: =IF($K97="","",IF(INDEX(Transactions!$F$5:$F$5004,$K97)="","",INDEX(Transactions!$F$5:$F$5004,$K97))) | I97: =IF($K97="","",IF(INDEX(Transactions!$G$5:$G$5004,$K97)="","",INDEX(Transactions!$G$5:$G$5004,$K97))) | K97: =IFERROR(MATCH(83,Transactions!$H$5:$H$5004,0),"")
B98: =IF($K98="","",84) | C98: =IF($K98="","",IF(INDEX(Transactions!$A$5:$A$5004,$K98)="","",INDEX(Transactions!$A$5:$A$5004,$K98))) | D98: =IF($K98="","",IF(INDEX(Transactions!$B$5:$B$5004,$K98)="","",INDEX(Transactions!$B$5:$B$5004,$K98))) | E98: =IF($K98="","",IF(INDEX(Transactions!$C$5:$C$5004,$K98)="","",INDEX(Transactions!$C$5:$C$5004,$K98))) | F98: =IF($K98="","",IF(INDEX(Transactions!$D$5:$D$5004,$K98)="","",INDEX(Transactions!$D$5:$D$5004,$K98))) | G98: =IF($K98="","",IF(INDEX(Transactions!$E$5:$E$5004,$K98)="","",INDEX(Transactions!$E$5:$E$5004,$K98))) | H98: =IF($K98="","",IF(INDEX(Transactions!$F$5:$F$5004,$K98)="","",INDEX(Transactions!$F$5:$F$5004,$K98))) | I98: =IF($K98="","",IF(INDEX(Transactions!$G$5:$G$5004,$K98)="","",INDEX(Transactions!$G$5:$G$5004,$K98))) | K98: =IFERROR(MATCH(84,Transactions!$H$5:$H$5004,0),"")
B99: =IF($K99="","",85) | C99: =IF($K99="","",IF(INDEX(Transactions!$A$5:$A$5004,$K99)="","",INDEX(Transactions!$A$5:$A$5004,$K99))) | D99: =IF($K99="","",IF(INDEX(Transactions!$B$5:$B$5004,$K99)="","",INDEX(Transactions!$B$5:$B$5004,$K99))) | E99: =IF($K99="","",IF(INDEX(Transactions!$C$5:$C$5004,$K99)="","",INDEX(Transactions!$C$5:$C$5004,$K99))) | F99: =IF($K99="","",IF(INDEX(Transactions!$D$5:$D$5004,$K99)="","",INDEX(Transactions!$D$5:$D$5004,$K99))) | G99: =IF($K99="","",IF(INDEX(Transactions!$E$5:$E$5004,$K99)="","",INDEX(Transactions!$E$5:$E$5004,$K99))) | H99: =IF($K99="","",IF(INDEX(Transactions!$F$5:$F$5004,$K99)="","",INDEX(Transactions!$F$5:$F$5004,$K99))) | I99: =IF($K99="","",IF(INDEX(Transactions!$G$5:$G$5004,$K99)="","",INDEX(Transactions!$G$5:$G$5004,$K99))) | K99: =IFERROR(MATCH(85,Transactions!$H$5:$H$5004,0),"")
B100: =IF($K100="","",86) | C100: =IF($K100="","",IF(INDEX(Transactions!$A$5:$A$5004,$K100)="","",INDEX(Transactions!$A$5:$A$5004,$K100))) | D100: =IF($K100="","",IF(INDEX(Transactions!$B$5:$B$5004,$K100)="","",INDEX(Transactions!$B$5:$B$5004,$K100))) | E100: =IF($K100="","",IF(INDEX(Transactions!$C$5:$C$5004,$K100)="","",INDEX(Transactions!$C$5:$C$5004,$K100))) | F100: =IF($K100="","",IF(INDEX(Transactions!$D$5:$D$5004,$K100)="","",INDEX(Transactions!$D$5:$D$5004,$K100))) | G100: =IF($K100="","",IF(INDEX(Transactions!$E$5:$E$5004,$K100)="","",INDEX(Transactions!$E$5:$E$5004,$K100))) | H100: =IF($K100="","",IF(INDEX(Transactions!$F$5:$F$5004,$K100)="","",INDEX(Transactions!$F$5:$F$5004,$K100))) | I100: =IF($K100="","",IF(INDEX(Transactions!$G$5:$G$5004,$K100)="","",INDEX(Transactions!$G$5:$G$5004,$K100))) | K100: =IFERROR(MATCH(86,Transactions!$H$5:$H$5004,0),"")
B101: =IF($K101="","",87) | C101: =IF($K101="","",IF(INDEX(Transactions!$A$5:$A$5004,$K101)="","",INDEX(Transactions!$A$5:$A$5004,$K101))) | D101: =IF($K101="","",IF(INDEX(Transactions!$B$5:$B$5004,$K101)="","",INDEX(Transactions!$B$5:$B$5004,$K101))) | E101: =IF($K101="","",IF(INDEX(Transactions!$C$5:$C$5004,$K101)="","",INDEX(Transactions!$C$5:$C$5004,$K101))) | F101: =IF($K101="","",IF(INDEX(Transactions!$D$5:$D$5004,$K101)="","",INDEX(Transactions!$D$5:$D$5004,$K101))) | G101: =IF($K101="","",IF(INDEX(Transactions!$E$5:$E$5004,$K101)="","",INDEX(Transactions!$E$5:$E$5004,$K101))) | H101: =IF($K101="","",IF(INDEX(Transactions!$F$5:$F$5004,$K101)="","",INDEX(Transactions!$F$5:$F$5004,$K101))) | I101: =IF($K101="","",IF(INDEX(Transactions!$G$5:$G$5004,$K101)="","",INDEX(Transactions!$G$5:$G$5004,$K101))) | K101: =IFERROR(MATCH(87,Transactions!$H$5:$H$5004,0),"")
B102: =IF($K102="","",88) | C102: =IF($K102="","",IF(INDEX(Transactions!$A$5:$A$5004,$K102)="","",INDEX(Transactions!$A$5:$A$5004,$K102))) | D102: =IF($K102="","",IF(INDEX(Transactions!$B$5:$B$5004,$K102)="","",INDEX(Transactions!$B$5:$B$5004,$K102))) | E102: =IF($K102="","",IF(INDEX(Transactions!$C$5:$C$5004,$K102)="","",INDEX(Transactions!$C$5:$C$5004,$K102))) | F102: =IF($K102="","",IF(INDEX(Transactions!$D$5:$D$5004,$K102)="","",INDEX(Transactions!$D$5:$D$5004,$K102))) | G102: =IF($K102="","",IF(INDEX(Transactions!$E$5:$E$5004,$K102)="","",INDEX(Transactions!$E$5:$E$5004,$K102))) | H102: =IF($K102="","",IF(INDEX(Transactions!$F$5:$F$5004,$K102)="","",INDEX(Transactions!$F$5:$F$5004,$K102))) | I102: =IF($K102="","",IF(INDEX(Transactions!$G$5:$G$5004,$K102)="","",INDEX(Transactions!$G$5:$G$5004,$K102))) | K102: =IFERROR(MATCH(88,Transactions!$H$5:$H$5004,0),"")
B103: =IF($K103="","",89) | C103: =IF($K103="","",IF(INDEX(Transactions!$A$5:$A$5004,$K103)="","",INDEX(Transactions!$A$5:$A$5004,$K103))) | D103: =IF($K103="","",IF(INDEX(Transactions!$B$5:$B$5004,$K103)="","",INDEX(Transactions!$B$5:$B$5004,$K103))) | E103: =IF($K103="","",IF(INDEX(Transactions!$C$5:$C$5004,$K103)="","",INDEX(Transactions!$C$5:$C$5004,$K103))) | F103: =IF($K103="","",IF(INDEX(Transactions!$D$5:$D$5004,$K103)="","",INDEX(Transactions!$D$5:$D$5004,$K103))) | G103: =IF($K103="","",IF(INDEX(Transactions!$E$5:$E$5004,$K103)="","",INDEX(Transactions!$E$5:$E$5004,$K103))) | H103: =IF($K103="","",IF(INDEX(Transactions!$F$5:$F$5004,$K103)="","",INDEX(Transactions!$F$5:$F$5004,$K103))) | I103: =IF($K103="","",IF(INDEX(Transactions!$G$5:$G$5004,$K103)="","",INDEX(Transactions!$G$5:$G$5004,$K103))) | K103: =IFERROR(MATCH(89,Transactions!$H$5:$H$5004,0),"")
...

Sheet Year View
B1: ="Year Overview - "&Dashboard!$C$4 -> Year Overview - 2026
B2: Month-by-month income, spending and budget performance. Change the year on the Dashboard.
B4: Month | C4: Income | D4: Spent | E4: Net Savings | F4: Savings Rate | G4: Budget | H4: Budget Used | I4: Status
A5: 1 | B5: January | C5: =SUMIFS(Income!$D$5:$D$2004,Income!$A$5:$A$2004,">="&DATE(Dashboard!$C$4,$A5,1),Income!$A$5:$A$2004,"<="&EOMONTH(DATE(Dashboard!$C$4,$A5,1),0)) -> 0 | D5: =SUMIFS(Transactions!$E$5:$E$5004,Transactions!$A$5:$A$5004,">="&DATE(Dashboard!$C$4,$A5,1),Transactions!$A$5:$A$5004,"<="&EOMONTH(DATE(Dashboard!$C$4,$A5,1),0)) -> 0 | E5: =C5-D5 -> 0 | F5: =IF(C5=0,0,E5/C5) -> 0 | G5: =SUMPRODUCT(Budget!$C$5:$C$44*((Budget!$B$5:$B$44="Monthly")+(Budget!$B$5:$B$44="Daily")*DAY(EOMONTH(DATE(Dashboard!$C$4,$A5,1),0))+(Budget!$B$5:$B$44="Weekly")*DAY(EOMONTH(DATE(Dashboard!$C$4,$A5,1),0))/7)*(Budget!$D$5:$D$44<=EOMONTH(DATE(Dashboard!$C$4,$A5,1),0))*(((Budget!$E$5:$E$44="")+(Budget!$E$5:$E$44>=DATE(Dashboard!$C$4,$A5,1)))>0)) -> 0 | H5: =IF(G5=0,0,D5/G5) -> 0 | I5: =IF(OR(G5=0,AND(D5=0,C5=0)),"-",IF(D5>G5,"OVER",IF(D5>=WarnPct*G5,"Watch","OK"))) -> -
A6: 2 | B6: February | C6: =SUMIFS(Income!$D$5:$D$2004,Income!$A$5:$A$2004,">="&DATE(Dashboard!$C$4,$A6,1),Income!$A$5:$A$2004,"<="&EOMONTH(DATE(Dashboard!$C$4,$A6,1),0)) -> 0 | D6: =SUMIFS(Transactions!$E$5:$E$5004,Transactions!$A$5:$A$5004,">="&DATE(Dashboard!$C$4,$A6,1),Transactions!$A$5:$A$5004,"<="&EOMONTH(DATE(Dashboard!$C$4,$A6,1),0)) -> 0 | E6: =C6-D6 -> 0 | F6: =IF(C6=0,0,E6/C6) -> 0 | G6: =SUMPRODUCT(Budget!$C$5:$C$44*((Budget!$B$5:$B$44="Monthly")+(Budget!$B$5:$B$44="Daily")*DAY(EOMONTH(DATE(Dashboard!$C$4,$A6,1),0))+(Budget!$B$5:$B$44="Weekly")*DAY(EOMONTH(DATE(Dashboard!$C$4,$A6,1),0))/7)*(Budget!$D$5:$D$44<=EOMONTH(DATE(Dashboard!$C$4,$A6,1),0))*(((Budget!$E$5:$E$44="")+(Budget!$E$5:$E$44>=DATE(Dashboard!$C$4,$A6,1)))>0)) -> 0 | H6: =IF(G6=0,0,D6/G6) -> 0 | I6: =IF(OR(G6=0,AND(D6=0,C6=0)),"-",IF(D6>G6,"OVER",IF(D6>=WarnPct*G6,"Watch","OK"))) -> -
A7: 3 | B7: March | C7: =SUMIFS(Income!$D$5:$D$2004,Income!$A$5:$A$2004,">="&DATE(Dashboard!$C$4,$A7,1),Income!$A$5:$A$2004,"<="&EOMONTH(DATE(Dashboard!$C$4,$A7,1),0)) -> 0 | D7: =SUMIFS(Transactions!$E$5:$E$5004,Transactions!$A$5:$A$5004,">="&DATE(Dashboard!$C$4,$A7,1),Transactions!$A$5:$A$5004,"<="&EOMONTH(DATE(Dashboard!$C$4,$A7,1),0)) -> 0 | E7: =C7-D7 -> 0 | F7: =IF(C7=0,0,E7/C7) -> 0 | G7: =SUMPRODUCT(Budget!$C$5:$C$44*((Budget!$B$5:$B$44="Monthly")+(Budget!$B$5:$B$44="Daily")*DAY(EOMONTH(DATE(Dashboard!$C$4,$A7,1),0))+(Budget!$B$5:$B$44="Weekly")*DAY(EOMONTH(DATE(Dashboard!$C$4,$A7,1),0))/7)*(Budget!$D$5:$D$44<=EOMONTH(DATE(Dashboard!$C$4,$A7,1),0))*(((Budget!$E$5:$E$44="")+(Budget!$E$5:$E$44>=DATE(Dashboard!$C$4,$A7,1)))>0)) -> 0 | H7: =IF(G7=0,0,D7/G7) -> 0 | I7: =IF(OR(G7=0,AND(D7=0,C7=0)),"-",IF(D7>G7,"OVER",IF(D7>=WarnPct*G7,"Watch","OK"))) -> -
A8: 4 | B8: April | C8: =SUMIFS(Income!$D$5:$D$2004,Income!$A$5:$A$2004,">="&DATE(Dashboard!$C$4,$A8,1),Income!$A$5:$A$2004,"<="&EOMONTH(DATE(Dashboard!$C$4,$A8,1),0)) -> 0 | D8: =SUMIFS(Transactions!$E$5:$E$5004,Transactions!$A$5:$A$5004,">="&DATE(Dashboard!$C$4,$A8,1),Transactions!$A$5:$A$5004,"<="&EOMONTH(DATE(Dashboard!$C$4,$A8,1),0)) -> 0 | E8: =C8-D8 -> 0 | F8: =IF(C8=0,0,E8/C8) -> 0 | G8: =SUMPRODUCT(Budget!$C$5:$C$44*((Budget!$B$5:$B$44="Monthly")+(Budget!$B$5:$B$44="Daily")*DAY(EOMONTH(DATE(Dashboard!$C$4,$A8,1),0))+(Budget!$B$5:$B$44="Weekly")*DAY(EOMONTH(DATE(Dashboard!$C$4,$A8,1),0))/7)*(Budget!$D$5:$D$44<=EOMONTH(DATE(Dashboard!$C$4,$A8,1),0))*(((Budget!$E$5:$E$44="")+(Budget!$E$5:$E$44>=DATE(Dashboard!$C$4,$A8,1)))>0)) -> 0 | H8: =IF(G8=0,0,D8/G8) -> 0 | I8: =IF(OR(G8=0,AND(D8=0,C8=0)),"-",IF(D8>G8,"OVER",IF(D8>=WarnPct*G8,"Watch","OK"))) -> -
A9: 5 | B9: May | C9: =SUMIFS(Income!$D$5:$D$2004,Income!$A$5:$A$2004,">="&DATE(Dashboard!$C$4,$A9,1),Income!$A$5:$A$2004,"<="&EOMONTH(DATE(Dashboard!$C$4,$A9,1),0)) -> 0 | D9: =SUMIFS(Transactions!$E$5:$E$5004,Transactions!$A$5:$A$5004,">="&DATE(Dashboard!$C$4,$A9,1),Transactions!$A$5:$A$5004,"<="&EOMONTH(DATE(Dashboard!$C$4,$A9,1),0)) -> 0 | E9: =C9-D9 -> 0 | F9: =IF(C9=0,0,E9/C9) -> 0 | G9: =SUMPRODUCT(Budget!$C$5:$C$44*((Budget!$B$5:$B$44="Monthly")+(Budget!$B$5:$B$44="Daily")*DAY(EOMONTH(DATE(Dashboard!$C$4,$A9,1),0))+(Budget!$B$5:$B$44="Weekly")*DAY(EOMONTH(DATE(Dashboard!$C$4,$A9,1),0))/7)*(Budget!$D$5:$D$44<=EOMONTH(DATE(Dashboard!$C$4,$A9,1),0))*(((Budget!$E$5:$E$44="")+(Budget!$E$5:$E$44>=DATE(Dashboard!$C$4,$A9,1)))>0)) -> 0 | H9: =IF(G9=0,0,D9/G9) -> 0 | I9: =IF(OR(G9=0,AND(D9=0,C9=0)),"-",IF(D9>G9,"OVER",IF(D9>=WarnPct*G9,"Watch","OK"))) -> -
A10: 6 | B10: June | C10: =SUMIFS(Income!$D$5:$D$2004,Income!$A$5:$A$2004,">="&DATE(Dashboard!$C$4,$A10,1),Income!$A$5:$A$2004,"<="&EOMONTH(DATE(Dashboard!$C$4,$A10,1),0)) -> 0 | D10: =SUMIFS(Transactions!$E$5:$E$5004,Transactions!$A$5:$A$5004,">="&DATE(Dashboard!$C$4,$A10,1),Transactions!$A$5:$A$5004,"<="&EOMONTH(DATE(Dashboard!$C$4,$A10,1),0)) -> 0 | E10: =C10-D10 -> 0 | F10: =IF(C10=0,0,E10/C10) -> 0 | G10: =SUMPRODUCT(Budget!$C$5:$C$44*((Budget!$B$5:$B$44="Monthly")+(Budget!$B$5:$B$44="Daily")*DAY(EOMONTH(DATE(Dashboard!$C$4,$A10,1),0))+(Budget!$B$5:$B$44="Weekly")*DAY(EOMONTH(DATE(Dashboard!$C$4,$A10,1),0))/7)*(Budget!$D$5:$D$44<=EOMONTH(DATE(Dashboard!$C$4,$A10,1),0))*(((Budget!$E$5:$E$44="")+(Budget!$E$5:$E$44>=DATE(Dashboard!$C$4,$A10,1)))>0)) -> 0 | H10: =IF(G10=0,0,D10/G10) -> 0 | I10: =IF(OR(G10=0,AND(D10=0,C10=0)),"-",IF(D10>G10,"OVER",IF(D10>=WarnPct*G10,"Watch","OK"))) -> -
A11: 7 | B11: July | C11: =SUMIFS(Income!$D$5:$D$2004,Income!$A$5:$A$2004,">="&DATE(Dashboard!$C$4,$A11,1),Income!$A$5:$A$2004,"<="&EOMONTH(DATE(Dashboard!$C$4,$A11,1),0)) -> 0 | D11: =SUMIFS(Transactions!$E$5:$E$5004,Transactions!$A$5:$A$5004,">="&DATE(Dashboard!$C$4,$A11,1),Transactions!$A$5:$A$5004,"<="&EOMONTH(DATE(Dashboard!$C$4,$A11,1),0)) -> 0 | E11: =C11-D11 -> 0 | F11: =IF(C11=0,0,E11/C11) -> 0 | G11: =SUMPRODUCT(Budget!$C$5:$C$44*((Budget!$B$5:$B$44="Monthly")+(Budget!$B$5:$B$44="Daily")*DAY(EOMONTH(DATE(Dashboard!$C$4,$A11,1),0))+(Budget!$B$5:$B$44="Weekly")*DAY(EOMONTH(DATE(Dashboard!$C$4,$A11,1),0))/7)*(Budget!$D$5:$D$44<=EOMONTH(DATE(Dashboard!$C$4,$A11,1),0))*(((Budget!$E$5:$E$44="")+(Budget!$E$5:$E$44>=DATE(Dashboard!$C$4,$A11,1)))>0)) -> 0 | H11: =IF(G11=0,0,D11/G11) -> 0 | I11: =IF(OR(G11=0,AND(D11=0,C11=0)),"-",IF(D11>G11,"OVER",IF(D11>=WarnPct*G11,"Watch","OK"))) -> -
A12: 8 | B12: August | C12: =SUMIFS(Income!$D$5:$D$2004,Income!$A$5:$A$2004,">="&DATE(Dashboard!$C$4,$A12,1),Income!$A$5:$A$2004,"<="&EOMONTH(DATE(Dashboard!$C$4,$A12,1),0)) -> 0 | D12: =SUMIFS(Transactions!$E$5:$E$5004,Transactions!$A$5:$A$5004,">="&DATE(Dashboard!$C$4,$A12,1),Transactions!$A$5:$A$5004,"<="&EOMONTH(DATE(Dashboard!$C$4,$A12,1),0)) -> 0 | E12: =C12-D12 -> 0 | F12: =IF(C12=0,0,E12/C12) -> 0 | G12: =SUMPRODUCT(Budget!$C$5:$C$44*((Budget!$B$5:$B$44="Monthly")+(Budget!$B$5:$B$44="Daily")*DAY(EOMONTH(DATE(Dashboard!$C$4,$A12,1),0))+(Budget!$B$5:$B$44="Weekly")*DAY(EOMONTH(DATE(Dashboard!$C$4,$A12,1),0))/7)*(Budget!$D$5:$D$44<=EOMONTH(DATE(Dashboard!$C$4,$A12,1),0))*(((Budget!$E$5:$E$44="")+(Budget!$E$5:$E$44>=DATE(Dashboard!$C$4,$A12,1)))>0)) -> 0 | H12: =IF(G12=0,0,D12/G12) -> 0 | I12: =IF(OR(G12=0,AND(D12=0,C12=0)),"-",IF(D12>G12,"OVER",IF(D12>=WarnPct*G12,"Watch","OK"))) -> -
A13: 9 | B13: September | C13: =SUMIFS(Income!$D$5:$D$2004,Income!$A$5:$A$2004,">="&DATE(Dashboard!$C$4,$A13,1),Income!$A$5:$A$2004,"<="&EOMONTH(DATE(Dashboard!$C$4,$A13,1),0)) -> 0 | D13: =SUMIFS(Transactions!$E$5:$E$5004,Transactions!$A$5:$A$5004,">="&DATE(Dashboard!$C$4,$A13,1),Transactions!$A$5:$A$5004,"<="&EOMONTH(DATE(Dashboard!$C$4,$A13,1),0)) -> 0 | E13: =C13-D13 -> 0 | F13: =IF(C13=0,0,E13/C13) -> 0 | G13: =SUMPRODUCT(Budget!$C$5:$C$44*((Budget!$B$5:$B$44="Monthly")+(Budget!$B$5:$B$44="Daily")*DAY(EOMONTH(DATE(Dashboard!$C$4,$A13,1),0))+(Budget!$B$5:$B$44="Weekly")*DAY(EOMONTH(DATE(Dashboard!$C$4,$A13,1),0))/7)*(Budget!$D$5:$D$44<=EOMONTH(DATE(Dashboard!$C$4,$A13,1),0))*(((Budget!$E$5:$E$44="")+(Budget!$E$5:$E$44>=DATE(Dashboard!$C$4,$A13,1)))>0)) -> 0 | H13: =IF(G13=0,0,D13/G13) -> 0 | I13: =IF(OR(G13=0,AND(D13=0,C13=0)),"-",IF(D13>G13,"OVER",IF(D13>=WarnPct*G13,"Watch","OK"))) -> -
A14: 10 | B14: October | C14: =SUMIFS(Income!$D$5:$D$2004,Income!$A$5:$A$2004,">="&DATE(Dashboard!$C$4,$A14,1),Income!$A$5:$A$2004,"<="&EOMONTH(DATE(Dashboard!$C$4,$A14,1),0)) -> 0 | D14: =SUMIFS(Transactions!$E$5:$E$5004,Transactions!$A$5:$A$5004,">="&DATE(Dashboard!$C$4,$A14,1),Transactions!$A$5:$A$5004,"<="&EOMONTH(DATE(Dashboard!$C$4,$A14,1),0)) -> 0 | E14: =C14-D14 -> 0 | F14: =IF(C14=0,0,E14/C14) -> 0 | G14: =SUMPRODUCT(Budget!$C$5:$C$44*((Budget!$B$5:$B$44="Monthly")+(Budget!$B$5:$B$44="Daily")*DAY(EOMONTH(DATE(Dashboard!$C$4,$A14,1),0))+(Budget!$B$5:$B$44="Weekly")*DAY(EOMONTH(DATE(Dashboard!$C$4,$A14,1),0))/7)*(Budget!$D$5:$D$44<=EOMONTH(DATE(Dashboard!$C$4,$A14,1),0))*(((Budget!$E$5:$E$44="")+(Budget!$E$5:$E$44>=DATE(Dashboard!$C$4,$A14,1)))>0)) -> 0 | H14: =IF(G14=0,0,D14/G14) -> 0 | I14: =IF(OR(G14=0,AND(D14=0,C14=0)),"-",IF(D14>G14,"OVER",IF(D14>=WarnPct*G14,"Watch","OK"))) -> -
A15: 11 | B15: November | C15: =SUMIFS(Income!$D$5:$D$2004,Income!$A$5:$A$2004,">="&DATE(Dashboard!$C$4,$A15,1),Income!$A$5:$A$2004,"<="&EOMONTH(DATE(Dashboard!$C$4,$A15,1),0)) -> 0 | D15: =SUMIFS(Transactions!$E$5:$E$5004,Transactions!$A$5:$A$5004,">="&DATE(Dashboard!$C$4,$A15,1),Transactions!$A$5:$A$5004,"<="&EOMONTH(DATE(Dashboard!$C$4,$A15,1),0)) -> 0 | E15: =C15-D15 -> 0 | F15: =IF(C15=0,0,E15/C15) -> 0 | G15: =SUMPRODUCT(Budget!$C$5:$C$44*((Budget!$B$5:$B$44="Monthly")+(Budget!$B$5:$B$44="Daily")*DAY(EOMONTH(DATE(Dashboard!$C$4,$A15,1),0))+(Budget!$B$5:$B$44="Weekly")*DAY(EOMONTH(DATE(Dashboard!$C$4,$A15,1),0))/7)*(Budget!$D$5:$D$44<=EOMONTH(DATE(Dashboard!$C$4,$A15,1),0))*(((Budget!$E$5:$E$44="")+(Budget!$E$5:$E$44>=DATE(Dashboard!$C$4,$A15,1)))>0)) -> 0 | H15: =IF(G15=0,0,D15/G15) -> 0 | I15: =IF(OR(G15=0,AND(D15=0,C15=0)),"-",IF(D15>G15,"OVER",IF(D15>=WarnPct*G15,"Watch","OK"))) -> -
A16: 12 | B16: December | C16: =SUMIFS(Income!$D$5:$D$2004,Income!$A$5:$A$2004,">="&DATE(Dashboard!$C$4,$A16,1),Income!$A$5:$A$2004,"<="&EOMONTH(DATE(Dashboard!$C$4,$A16,1),0)) -> 0 | D16: =SUMIFS(Transactions!$E$5:$E$5004,Transactions!$A$5:$A$5004,">="&DATE(Dashboard!$C$4,$A16,1),Transactions!$A$5:$A$5004,"<="&EOMONTH(DATE(Dashboard!$C$4,$A16,1),0)) -> 0 | E16: =C16-D16 -> 0 | F16: =IF(C16=0,0,E16/C16) -> 0 | G16: =SUMPRODUCT(Budget!$C$5:$C$44*((Budget!$B$5:$B$44="Monthly")+(Budget!$B$5:$B$44="Daily")*DAY(EOMONTH(DATE(Dashboard!$C$4,$A16,1),0))+(Budget!$B$5:$B$44="Weekly")*DAY(EOMONTH(DATE(Dashboard!$C$4,$A16,1),0))/7)*(Budget!$D$5:$D$44<=EOMONTH(DATE(Dashboard!$C$4,$A16,1),0))*(((Budget!$E$5:$E$44="")+(Budget!$E$5:$E$44>=DATE(Dashboard!$C$4,$A16,1)))>0)) -> 0 | H16: =IF(G16=0,0,D16/G16) -> 0 | I16: =IF(OR(G16=0,AND(D16=0,C16=0)),"-",IF(D16>G16,"OVER",IF(D16>=WarnPct*G16,"Watch","OK"))) -> -
B17: YEAR TOTAL | C17: =SUM(C5:C16) -> 0 | D17: =SUM(D5:D16) -> 0 | E17: =SUM(E5:E16) -> 0 | F17: =IF(C17=0,0,E17/C17) -> 0 | G17: =SUM(G5:G16) -> 0 | H17: =IF(G17=0,0,D17/G17) -> 0

Sheet Settings
B1: Settings & Lists
B2: Rename the items below to suit you. These lists feed every dropdown in the workbook. Tip: rename a category only if it has no transactions yet - otherwise old entries will no longer match.
B5: Expense Categories (16) | C5: Category filter (auto) | D5: Payment Methods (8) | E5: Income Sources (8) | F5: Budget Periods | G5: Months | H5: Years | J5: Period calculations (automatic - do not edit)
B6: Food & Groceries | C6: All | D6: Cash | E6: Salary | F6: Daily | G6: January | H6: 2024 | J6: Period start | K6: =DATE(Dashboard!$C$4,MATCH(Dashboard!$D$4,$G$6:$G$17,0),1) -> 46296
B7: Eating Out | C7: =IF(B6="","",B6) -> Food & Groceries | D7: M-Pesa | E7: Business Income | F7: Weekly | G7: February | H7: 2025 | J7: Period end | K7: =EOMONTH(K6,0) -> 46326
B8: Rent & Housing | C8: =IF(B7="","",B7) -> Eating Out | D8: Bank Card | E8: Freelance / Client Project | F8: Monthly | G8: March | H8: 2026 | J8: Days in month | K8: =DAY(K7) -> 31
B9: Utilities | C9: =IF(B8="","",B8) -> Rent & Housing | D9: Bank Transfer | E9: Side Hustle | G9: April | H9: 2027 | J9: Today | K9: =TODAY() -> 46322
B10: Transport & Fuel | C10: =IF(B9="","",B9) -> Utilities | D10: Airtel Money | E10: Gift / Support | G10: May | H10: 2028 | J10: Days elapsed | K10: =IF(K9<K6,0,IF(K9>K7,K8,K9-K6+1)) -> 27
B11: Airtime & Data | C11: =IF(B10="","",B10) -> Transport & Fuel | D11: Other | E11: Interest & Dividends | G11: June | H11: 2029 | J11: Days remaining | K11: =K8-K10 -> 4
B12: Health & Medical | C12: =IF(B11="","",B11) -> Airtime & Data | E12: Rental Income | G12: July | H12: 2030 | J12: Is this the current month? (1=yes) | K12: =IF(AND(K9>=K6,K9<=K7),1,0) -> 1
B13: Education & School Fees | C13: =IF(B12="","",B12) -> Health & Medical | E13: Other Income | G13: August | H13: 2031
B14: Business Expenses | C14: =IF(B13="","",B13) -> Education & School Fees | G14: September | H14: 2032
B15: Shopping & Clothing | C15: =IF(B14="","",B14) -> Business Expenses | G15: October | H15: 2033 | J15: Alert settings
B16: Entertainment & Leisure | C16: =IF(B15="","",B15) -> Shopping & Clothing | G16: November | H16: 2034 | J16: Warn me when budget used reaches | K16: 0.8
B17: Personal Care | C17: =IF(B16="","",B16) -> Entertainment & Leisure | G17: December | H17: 2035
B18: Family & Support | C18: =IF(B17="","",B17) -> Personal Care | J18: At or above this level a category shows 'Watch' (amber). Above 100% it shows 'OVER' (red).
B19: Giving & Church | C19: =IF(B18="","",B18) -> Family & Support
B20: Loans & Debt | C20: =IF(B19="","",B19) -> Giving & Church
B21: Other | C21: =IF(B20="","",B20) -> Loans & Debt
C22: =IF(B21="","",B21) -> Other
